Workbook

Sheet CONTROL DE VERSIONES
D8: Diseño de registro de la interfaz de datos fiscales y personales IRPF 2025 para empresas de desarrollo
D9: Ejercicio.: | F9: 2025
D10: Autor: | E10: SG Aplicaciones | F10: Fecha: | G10: 46083 | H10: versión | I10: 1.0
D13: Revisiones
D15: Edi. | E15: Rev. | F15: Fecha | G15: Descripción de los cambios | H15: A (*) | I15: Páginas
D21: (*) Acción: A= Añadir; R= Reemplazar;
D26: Estado de aceptación
F28: Fecha | G28: Nombre
D29: Preparado por:
D30: Autorizado por:
D31: Aceptado por:
E63: Interfaz V1.3
E66: IRPF | F66: =F9 -> 2025 | G66: =CONCATENATE(" ",E66," ",F66) -> IRPF 2025
E67: IRPF | F67: =F9 -> 2025 | G67: =CONCATENATE(" ",E67," ",F67) -> IRPF 2025
E68: IRPF | F68: =F9 -> 2025 | G68: =CONCATENATE(" ",E68," ",F68) -> IRPF 2025
E69: versión | F69: =I10 -> 1.0 | G69: =CONCATENATE(E69," ",F69) -> versión 1.0

Sheet Introduccion y datos tecnicos
C2: ='CONTROL DE VERSIONES'!G69 -> versión 1.0 | G2: Diseño de registro de datos fiscales y personales
G3: ='CONTROL DE VERSIONES'!G66 -> IRPF 2025
G4: Introducción y datos técnicos.
C9: Introducción al documento de interfaz de datos fiscales y personales Este documento describe los diferentes conceptos de la interfaz de datos fiscales y personales IRPF 2025 que se ofrece para programas de ayuda desarrollados por empresas externas a la AEAT. El documento no incluye descripción ni asistencia sobre los criterios de tratamiento fiscal de los datos. No hay indicación de las partidas del modelo 100 sobre las que dichos datos tengan que ser reflejados (no hay una relación directa, pues puede haber combinaciones de varios datos sobre una partida, condiciones, etc.). Los datos ofrecidos son los utilizados por RentaWeb, y no denotan correspondencia directa con declaraciones presentadas relacionadas con el contribuyente. El contribuyente (y sus representantes) debe revisar la información antes de presentar la declaración. Se proporcionará en un documento aparte los detalles técnicos de conexión y autenticación frente al servicio de entrega del fichero de datos fiscales y personales. Todos los importes se entregan en céntimos de euro salvo que se especifique lo contrario. Los importes negativos se representan con una N en la primera posición. Ejemplo, para un importe de longitud 13, y cuantía '-100,00' se representaría con el valor N000000010000
C11: =IF(P11=TRUE,#REF!+1,) -> 0 | N11: =ISTEXT(D11) -> FALSE | O11: =ISNUMBER(D11) -> FALSE | P11: =OR(N11=TRUE,O11=TRUE) -> FALSE
C12: =IF(P12=TRUE,C11+1,) -> 0 | N12: =ISTEXT(D12) -> FALSE | O12: =ISNUMBER(D12) -> FALSE | P12: =OR(N12=TRUE,O12=TRUE) -> FALSE
C13: =IF(P13=TRUE,C12+1,) -> 0 | N13: =ISTEXT(D13) -> FALSE | O13: =ISNUMBER(D13) -> FALSE | P13: =OR(N13=TRUE,O13=TRUE) -> FALSE
C14: =IF(P14=TRUE,C13+1,) -> 0 | N14: =ISTEXT(D14) -> FALSE | O14: =ISNUMBER(D14) -> FALSE | P14: =OR(N14=TRUE,O14=TRUE) -> FALSE
C15: =IF(P15=TRUE,C14+1,) -> 0 | N15: =ISTEXT(D15) -> FALSE | O15: =ISNUMBER(D15) -> FALSE | P15: =OR(N15=TRUE,O15=TRUE) -> FALSE
C16: =IF(P16=TRUE,C15+1,) -> 0 | N16: =ISTEXT(D16) -> FALSE | O16: =ISNUMBER(D16) -> FALSE | P16: =OR(N16=TRUE,O16=TRUE) -> FALSE
C17: =IF(P17=TRUE,C16+1,) -> 0 | N17: =ISTEXT(D17) -> FALSE | O17: =ISNUMBER(D17) -> FALSE | P17: =OR(N17=TRUE,O17=TRUE) -> FALSE
C18: =IF(P18=TRUE,C17+1,) -> 0 | N18: =ISTEXT(D18) -> FALSE | O18: =ISNUMBER(D18) -> FALSE | P18: =OR(N18=TRUE,O18=TRUE) -> FALSE
C19: =IF(P19=TRUE,C18+1,) -> 0 | N19: =ISTEXT(D19) -> FALSE | O19: =ISNUMBER(D19) -> FALSE | P19: =OR(N19=TRUE,O19=TRUE) -> FALSE
C20: =IF(P20=TRUE,C19+1,) -> 0 | N20: =ISTEXT(D20) -> FALSE | O20: =ISNUMBER(D20) -> FALSE | P20: =OR(N20=TRUE,O20=TRUE) -> FALSE
C21: =IF(P21=TRUE,C20+1,) -> 0 | N21: =ISTEXT(D21) -> FALSE | O21: =ISNUMBER(D21) -> FALSE | P21: =OR(N21=TRUE,O21=TRUE) -> FALSE
C22: =IF(P22=TRUE,C21+1,) -> 0 | N22: =ISTEXT(D22) -> FALSE | O22: =ISNUMBER(D22) -> FALSE | P22: =OR(N22=TRUE,O22=TRUE) -> FALSE
C23: =IF(P23=TRUE,C22+1,) -> 0 | N23: =ISTEXT(D23) -> FALSE | O23: =ISNUMBER(D23) -> FALSE | P23: =OR(N23=TRUE,O23=TRUE) -> FALSE
... C93: =IF(P93=TRUE,C92+1,) -> 0 | N93: =ISTEXT(D93) -> FALSE | O93: =ISNUMBER(D93) -> FALSE | P93: =OR(N93=TRUE,O93=TRUE) -> FALSE

Sheet INDICE
C2: ='CONTROL DE VERSIONES'!G69 -> versión 1.0 | G2: Diseño de registro de datos fiscales y personales para Empresas Externas
G3: ='CONTROL DE VERSIONES'!G67 -> IRPF 2025
E8: Registro tipo 0
E11: Registro de tipo 0
E14: Registro de tipo 1
D16: Código
E17: Registros de tipo 2
E106: Registros de tipo 3
E112: Registros de tipo 9
G116: Observaciones:
G117: Se señalan en color azul los conceptos de datos fiscales NUEVOS para IRPF 2025
G118: Se señalan en color verde los conceptos de datos fiscales que hayan sufrido algún cambio en el número de campos o en el listado de claves de sus campos para IRPF 2025 (dentro del concepto se señalan en color verde los campos que hayan sufrido algún cambio)

Sheet Registro de Cabecera
D2: Diseño de registro de datos fiscales y personales
D3: ='CONTROL DE VERSIONES'!G68 -> IRPF 2025
D4: Registro de cabecera
C5: =IF(P5=TRUE,C4+1,) -> 0
C6: =IF(P6=TRUE,C5+1,) -> 0
C7: Este concepto contiene el código del registro de cabecera.
C9: Nº | D9: Nombre | E9: Posición | F9: Longitud | G9: Descripción
C10: =IF(P10=TRUE,1,) -> 1 | D10: Tipo | E10: =IF(P10=TRUE,1,) -> 1 | F10: 1 | G10: Tipo de registro = '0' | N10: =ISTEXT(D10) -> TRUE | O10: =ISNUMBER(D10) -> FALSE | P10: =OR(N10=TRUE,O10=TRUE) -> TRUE
C11: =IF(P11=TRUE,C10+1,) -> 2 | D11: Código | E11: =IF(P11=TRUE,E10+F10,) -> 2 | F11: 8 | G11: Contenido: 'DDFF2025' | N11: =ISTEXT(D11) -> TRUE | O11: =ISNUMBER(D11) -> FALSE | P11: =OR(N11=TRUE,O11=TRUE) -> TRUE
C12: =IF(P12=TRUE,C11+1,) -> 0 | N12: =ISTEXT(D12) -> FALSE | O12: =ISNUMBER(D12) -> FALSE | P12: =OR(N12=TRUE,O12=TRUE) -> FALSE
C13: =IF(P13=TRUE,C12+1,) -> 0 | N13: =ISTEXT(D13) -> FALSE | O13: =ISNUMBER(D13) -> FALSE | P13: =OR(N13=TRUE,O13=TRUE) -> FALSE
C14: =IF(P14=TRUE,C13+1,) -> 0 | N14: =ISTEXT(D14) -> FALSE | O14: =ISNUMBER(D14) -> FALSE | P14: =OR(N14=TRUE,O14=TRUE) -> FALSE
C15: =IF(P15=TRUE,C14+1,) -> 0 | N15: =ISTEXT(D15) -> FALSE | O15: =ISNUMBER(D15) -> FALSE | P15: =OR(N15=TRUE,O15=TRUE) -> FALSE
C16: =IF(P16=TRUE,C15+1,) -> 0 | N16: =ISTEXT(D16) -> FALSE | O16: =ISNUMBER(D16) -> FALSE | P16: =OR(N16=TRUE,O16=TRUE) -> FALSE
C17: =IF(P17=TRUE,C16+1,) -> 0 | N17: =ISTEXT(D17) -> FALSE | O17: =ISNUMBER(D17) -> FALSE | P17: =OR(N17=TRUE,O17=TRUE) -> FALSE
C18: =IF(P18=TRUE,C17+1,) -> 0 | N18: =ISTEXT(D18) -> FALSE | O18: =ISNUMBER(D18) -> FALSE | P18: =OR(N18=TRUE,O18=TRUE) -> FALSE
C19: =IF(P19=TRUE,C18+1,) -> 0 | N19: =ISTEXT(D19) -> FALSE | O19: =ISNUMBER(D19) -> FALSE | P19: =OR(N19=TRUE,O19=TRUE) -> FALSE
C20: =IF(P20=TRUE,C19+1,) -> 0 | N20: =ISTEXT(D20) -> FALSE | O20: =ISNUMBER(D20) -> FALSE | P20: =OR(N20=TRUE,O20=TRUE) -> FALSE
C21: =IF(P21=TRUE,C20+1,) -> 0 | N21: =ISTEXT(D21) -> FALSE | O21: =ISNUMBER(D21) -> FALSE | P21: =OR(N21=TRUE,O21=TRUE) -> FALSE
C22: =IF(P22=TRUE,C21+1,) -> 0 | N22: =ISTEXT(D22) -> FALSE | O22: =ISNUMBER(D22) -> FALSE | P22: =OR(N22=TRUE,O22=TRUE) -> FALSE
C23: =IF(P23=TRUE,C22+1,) -> 0 | N23: =ISTEXT(D23) -> FALSE | O23: =ISNUMBER(D23) -> FALSE | P23: =OR(N23=TRUE,O23=TRUE) -> FALSE
... C97: =IF(P97=TRUE,C96+1,) -> 0 | N97: =ISTEXT(D97) -> FALSE | O97: =ISNUMBER(D97) -> FALSE | P97: =OR(N97=TRUE,O97=TRUE) -> FALSE

Sheet Fecha de proceso
D2: Diseño de registro de datos fiscales y personales
D3: ='CONTROL DE VERSIONES'!G68 -> IRPF 2025
D4: Fecha de proceso
C5: =IF(P5=TRUE,C4+1,) -> 0
C6: =IF(P6=TRUE,C5+1,) -> 0
C7: Este concepto de datos fiscales incluye la fecha de proceso donde se han generado los datos fiscales.
C9: Nº | D9: Nombre | E9: Posición | F9: Longitud | G9: Descripción
C10: =IF(P10=TRUE,1,) -> 1 | D10: Tipo | E10: =IF(P10=TRUE,1,) -> 1 | F10: 1 | G10: Tipo de registro = '1' | N10: =ISTEXT(D10) -> TRUE | O10: =ISNUMBER(D10) -> FALSE | P10: =OR(N10=TRUE,O10=TRUE) -> TRUE
C11: =IF(P11=TRUE,C10+1,) -> 2 | D11: Posiciones reservadas para la AEAT | E11: =IF(P11=TRUE,E10+F10,) -> 2 | F11: 50 | N11: =ISTEXT(D11) -> TRUE | O11: =ISNUMBER(D11) -> FALSE | P11: =OR(N11=TRUE,O11=TRUE) -> TRUE
C12: =IF(P12=TRUE,C11+1,) -> 3 | D12: Fecha de proceso | E12: =IF(P12=TRUE,E11+F11,) -> 52 | F12: 8 | G12: Fecha del proceso con formato AAAAMMDD | N12: =ISTEXT(D12) -> TRUE | O12: =ISNUMBER(D12) -> FALSE | P12: =OR(N12=TRUE,O12=TRUE) -> TRUE
C13: =IF(P13=TRUE,C12+1,) -> 0 | N13: =ISTEXT(D13) -> FALSE | O13: =ISNUMBER(D13) -> FALSE | P13: =OR(N13=TRUE,O13=TRUE) -> FALSE
C14: =IF(P14=TRUE,C13+1,) -> 0 | N14: =ISTEXT(D14) -> FALSE | O14: =ISNUMBER(D14) -> FALSE | P14: =OR(N14=TRUE,O14=TRUE) -> FALSE
C15: =IF(P15=TRUE,C14+1,) -> 0 | N15: =ISTEXT(D15) -> FALSE | O15: =ISNUMBER(D15) -> FALSE | P15: =OR(N15=TRUE,O15=TRUE) -> FALSE
C16: =IF(P16=TRUE,C15+1,) -> 0 | N16: =ISTEXT(D16) -> FALSE | O16: =ISNUMBER(D16) -> FALSE | P16: =OR(N16=TRUE,O16=TRUE) -> FALSE
C17: =IF(P17=TRUE,C16+1,) -> 0 | N17: =ISTEXT(D17) -> FALSE | O17: =ISNUMBER(D17) -> FALSE | P17: =OR(N17=TRUE,O17=TRUE) -> FALSE
C18: =IF(P18=TRUE,C17+1,) -> 0 | N18: =ISTEXT(D18) -> FALSE | O18: =ISNUMBER(D18) -> FALSE | P18: =OR(N18=TRUE,O18=TRUE) -> FALSE
C19: =IF(P19=TRUE,C18+1,) -> 0 | N19: =ISTEXT(D19) -> FALSE | O19: =ISNUMBER(D19) -> FALSE | P19: =OR(N19=TRUE,O19=TRUE) -> FALSE
C20: =IF(P20=TRUE,C19+1,) -> 0 | N20: =ISTEXT(D20) -> FALSE | O20: =ISNUMBER(D20) -> FALSE | P20: =OR(N20=TRUE,O20=TRUE) -> FALSE
C21: =IF(P21=TRUE,C20+1,) -> 0 | N21: =ISTEXT(D21) -> FALSE | O21: =ISNUMBER(D21) -> FALSE | P21: =OR(N21=TRUE,O21=TRUE) -> FALSE
C22: =IF(P22=TRUE,C21+1,) -> 0 | N22: =ISTEXT(D22) -> FALSE | O22: =ISNUMBER(D22) -> FALSE | P22: =OR(N22=TRUE,O22=TRUE) -> FALSE
C23: =IF(P23=TRUE,C22+1,) -> 0 | N23: =ISTEXT(D23) -> FALSE | O23: =ISNUMBER(D23) -> FALSE | P23: =OR(N23=TRUE,O23=TRUE) -> FALSE
C24: =IF(P24=TRUE,C23+1,) -> 0 | N24: =ISTEXT(D24) -> FALSE | O24: =ISNUMBER(D24) -> FALSE | P24: =OR(N24=TRUE,O24=TRUE) -> FALSE
... C97: =IF(P97=TRUE,C96+1,) -> 0 | N97: =ISTEXT(D97) -> FALSE | O97: =ISNUMBER(D97) -> FALSE | P97: =OR(N97=TRUE,O97=TRUE) -> FALSE

Sheet DOM - Datos del domicilio
D2: Diseño de registro de datos fiscales y personales
D3: ='CONTROL DE VERSIONES'!G68 -> IRPF 2025
D4: Datos del domicilio
C5: =IF(P5=TRUE,C4+1,) -> 0
C6: =IF(P6=TRUE,C5+1,) -> 0
C7: Este concepto de datos fiscales incluye los datos del domicilio
C9: Nº | D9: Nombre | E9: Posición | F9: Longitud | G9: Descripción
C10: =IF(P10=TRUE,1,) -> 1 | D10: Tipo | E10: =IF(P10=TRUE,1,) -> 1 | F10: 1 | G10: Tipo de registro = '2' | N10: =ISTEXT(D10) -> TRUE | O10: =ISNUMBER(D10) -> FALSE | P10: =OR(N10=TRUE,O10=TRUE) -> TRUE
C11: =IF(P11=TRUE,C10+1,) -> 2 | D11: Código | E11: =IF(P11=TRUE,E10+F10,) -> 2 | F11: 7 | G11: 'DOMnnnn' | N11: =ISTEXT(D11) -> TRUE | O11: =ISNUMBER(D11) -> FALSE | P11: =OR(N11=TRUE,O11=TRUE) -> TRUE
C12: =IF(P12=TRUE,C11+1,) -> 3 | D12: Posiciones reservadas para la AEAT | E12: =IF(P12=TRUE,E11+F11,) -> 9 | F12: 1 | N12: =ISTEXT(D12) -> TRUE | O12: =ISNUMBER(D12) -> FALSE | P12: =OR(N12=TRUE,O12=TRUE) -> TRUE
C13: =IF(P13=TRUE,C12+1,) -> 4 | D13: Tipo domicilio | E13: =IF(P13=TRUE,E12+F12,) -> 10 | F13: 2 | G13: Valores: '20' - Domicilio fiscal en territorio español '21' - Domicilio fiscal en el extranjero | N13: =ISTEXT(D13) -> TRUE | O13: =ISNUMBER(D13) -> FALSE | P13: =OR(N13=TRUE,O13=TRUE) -> TRUE
C14: =IF(P14=TRUE,C13+1,) -> 5 | D14: Datos domicilio | E14: =IF(P14=TRUE,E13+F13,) -> 12 | F14: XXX | G14: Longitud dependiente del tipo de domicilio "20" o "21" | N14: =ISTEXT(D14) -> TRUE | O14: =ISNUMBER(D14) -> FALSE | P14: =OR(N14=TRUE,O14=TRUE) -> TRUE
C15: =IF(P15=TRUE,C14+1,) -> 0 | N15: =ISTEXT(D15) -> FALSE | O15: =ISNUMBER(D15) -> FALSE | P15: =OR(N15=TRUE,O15=TRUE) -> FALSE
C16: =IF(P16=TRUE,C15+1,) -> 0 | N16: =ISTEXT(D16) -> FALSE | O16: =ISNUMBER(D16) -> FALSE | P16: =OR(N16=TRUE,O16=TRUE) -> FALSE
C17: REDEFINICION DEL CAMPO 'DATOS DOMICILIO' PARA REGISTRO TIPO DE DOMICILIO '20' (en territorio español) | N17: =ISTEXT(D17) -> FALSE | O17: =ISNUMBER(D17) -> FALSE | P17: =OR(N17=TRUE,O17=TRUE) -> FALSE
N18: =ISTEXT(D18) -> FALSE | O18: =ISNUMBER(D18) -> FALSE | P18: =OR(N18=TRUE,O18=TRUE) -> FALSE
C19: =IF(P19=TRUE,1,) -> 1 | D19: Tipo de via | E19: =IF(P19=TRUE,12,) -> 12 | F19: 5 | G19: Tipo de vía según las tablas INE "Tipos de vías" | N19: =ISTEXT(D19) -> TRUE | O19: =ISNUMBER(D19) -> FALSE | P19: =OR(N19=TRUE,O19=TRUE) -> TRUE
C20: =IF(P20=TRUE,C19+1,) -> 2 | D20: Codigo de via | E20: =IF(P20=TRUE,E19+F19,) -> 17 | F20: 5 | G20: Código de vía según las tablas INE | N20: =ISTEXT(D20) -> TRUE | O20: =ISNUMBER(D20) -> FALSE | P20: =OR(N20=TRUE,O20=TRUE) -> TRUE
C21: =IF(P21=TRUE,C20+1,) -> 3 | D21: Nombre largo de la via | E21: =IF(P21=TRUE,E20+F20,) -> 22 | F21: 50 | N21: =ISTEXT(D21) -> TRUE | O21: =ISNUMBER(D21) -> FALSE | P21: =OR(N21=TRUE,O21=TRUE) -> TRUE
C22: =IF(P22=TRUE,C21+1,) -> 4 | D22: Nombre corto de la via | E22: =IF(P22=TRUE,E21+F21,) -> 72 | F22: 25 | N22: =ISTEXT(D22) -> TRUE | O22: =ISNUMBER(D22) -> FALSE | P22: =OR(N22=TRUE,O22=TRUE) -> TRUE
C23: =IF(P23=TRUE,C22+1,) -> 5 | D23: Tipo de numeracion | E23: =IF(P23=TRUE,E22+F22,) -> 97 | F23: 3 | G23: Valores: NUM; KM; S/N; APC; etc | N23: =ISTEXT(D23) -> TRUE | O23: =ISNUMBER(D23) -> FALSE | P23: =OR(N23=TRUE,O23=TRUE) -> TRUE
C24: =IF(P24=TRUE,C23+1,) -> 6 | D24: Numero | E24: =IF(P24=TRUE,E23+F23,) -> 100 | F24: 5 | N24: =ISTEXT(D24) -> TRUE | O24: =ISNUMBER(D24) -> FALSE | P24: =OR(N24=TRUE,O24=TRUE) -> TRUE
C25: =IF(P25=TRUE,C24+1,) -> 7 | D25: Calificador numero | E25: =IF(P25=TRUE,E24+F24,) -> 105 | F25: 3 | G25: Valores: BIS; DUP; MOD; ANT; etc | N25: =ISTEXT(D25) -> TRUE | O25: =ISNUMBER(D25) -> FALSE | P25: =OR(N25=TRUE,O25=TRUE) -> TRUE
C26: =IF(P26=TRUE,C25+1,) -> 8 | D26: Bloque | E26: =IF(P26=TRUE,E25+F25,) -> 108 | F26: 3 | N26: =ISTEXT(D26) -> TRUE | O26: =ISNUMBER(D26) -> FALSE | P26: =OR(N26=TRUE,O26=TRUE) -> TRUE
C27: =IF(P27=TRUE,C26+1,) -> 9 | D27: Portal | E27: =IF(P27=TRUE,E26+F26,) -> 111 | F27: 3 | N27: =ISTEXT(D27) -> TRUE | O27: =ISNUMBER(D27) -> FALSE | P27: =OR(N27=TRUE,O27=TRUE) -> TRUE
C28: =IF(P28=TRUE,C27+1,) -> 10 | D28: Escalera | E28: =IF(P28=TRUE,E27+F27,) -> 114 | F28: 3 | N28: =ISTEXT(D28) -> TRUE | O28: =ISNUMBER(D28) -> FALSE | P28: =OR(N28=TRUE,O28=TRUE) -> TRUE
C29: =IF(P29=TRUE,C28+1,) -> 11 | D29: Planta-piso | E29: =IF(P29=TRUE,E28+F28,) -> 117 | F29: 3 | N29: =ISTEXT(D29) -> TRUE | O29: =ISNUMBER(D29) -> FALSE | P29: =OR(N29=TRUE,O29=TRUE) -> TRUE
C30: =IF(P30=TRUE,C29+1,) -> 12 | D30: Puerta | E30: =IF(P30=TRUE,E29+F29,) -> 120 | F30: 3 | N30: =ISTEXT(D30) -> TRUE | O30: =ISNUMBER(D30) -> FALSE | P30: =OR(N30=TRUE,O30=TRUE) -> TRUE
C31: =IF(P31=TRUE,C30+1,) -> 13 | D31: Datos complementarios | E31: =IF(P31=TRUE,E30+F30,) -> 123 | F31: 40 | N31: =ISTEXT(D31) -> TRUE | O31: =ISNUMBER(D31) -> FALSE | P31: =OR(N31=TRUE,O31=TRUE) -> TRUE
C32: =IF(P32=TRUE,C31+1,) -> 14 | D32: Poblacion | E32: =IF(P32=TRUE,E31+F31,) -> 163 | F32: 30 | G32: Nombre Localidad, Población, etc. Si es distinta al municipio | N32: =ISTEXT(D32) -> TRUE | O32: =ISNUMBER(D32) -> FALSE | P32: =OR(N32=TRUE,O32=TRUE) -> TRUE
C33: =IF(P33=TRUE,C32+1,) -> 15 | D33: Codigo postal | E33: =IF(P33=TRUE,E32+F32,) -> 193 | F33: 5 | N33: =ISTEXT(D33) -> TRUE | O33: =ISNUMBER(D33) -> FALSE | P33: =OR(N33=TRUE,O33=TRUE) -> TRUE
C34: =IF(P34=TRUE,C33+1,) -> 16 | D34: Codigo de municipio INE | E34: =IF(P34=TRUE,E33+F33,) -> 198 | F34: 5 | G34: Código Municipio INE | N34: =ISTEXT(D34) -> TRUE | O34: =ISNUMBER(D34) -> FALSE | P34: =OR(N34=TRUE,O34=TRUE) -> TRUE
C35: =IF(P35=TRUE,C34+1,) -> 17 | D35: Municipio | E35: =IF(P35=TRUE,E34+F34,) -> 203 | F35: 30 | G35: Nombre del municipio | N35: =ISTEXT(D35) -> TRUE | O35: =ISNUMBER(D35) -> FALSE | P35: =OR(N35=TRUE,O35=TRUE) -> TRUE
C36: =IF(P36=TRUE,C35+1,) -> 18 | D36: Codigo de provincia | E36: =IF(P36=TRUE,E35+F35,) -> 233 | F36: 2 | G36: Posibles valores: de 01 a 52 | N36: =ISTEXT(D36) -> TRUE | O36: =ISNUMBER(D36) -> FALSE | P36: =OR(N36=TRUE,O36=TRUE) -> TRUE
C37: =IF(P37=TRUE,C36+1,) -> 19 | D37: Provincia | E37: =IF(P37=TRUE,E36+F36,) -> 235 | F37: 20 | G37: Nombre de la provincia | N37: =ISTEXT(D37) -> TRUE | O37: =ISNUMBER(D37) -> FALSE | P37: =OR(N37=TRUE,O37=TRUE) -> TRUE
C38: =IF(P38=TRUE,C37+1,) -> 20 | D38: Referencia catastral | E38: =IF(P38=TRUE,E37+F37,) -> 255 | F38: 20 | G38: Referencia catastral del domicilio fiscal | N38: =ISTEXT(D38) -> TRUE | O38: =ISNUMBER(D38) -> FALSE | P38: =OR(N38=TRUE,O38=TRUE) -> TRUE
C39: =IF(P39=TRUE,C38+1,) -> 21 | D39: Fecha de modificación | E39: =IF(P39=TRUE,E38+F38,) -> 275 | F39: 8 | N39: =ISTEXT(D39) -> TRUE | O39: =ISNUMBER(D39) -> FALSE | P39: =OR(N39=TRUE,O39=TRUE) -> TRUE
N40: =ISTEXT(D40) -> FALSE | O40: =ISNUMBER(D40) -> FALSE | P40: =OR(N40=TRUE,O40=TRUE) -> FALSE
C41: =IF(P41=TRUE,C40+1,) -> 0 | N41: =ISTEXT(D41) -> FALSE | O41: =ISNUMBER(D41) -> FALSE | P41: =OR(N41=TRUE,O41=TRUE) -> FALSE
C42: REDEFINICION DEL CAMPO 'DATOS DOMICILIO' PARA REGISTRO TIPO DE DOMICILIO '21' (en el extranjero) | N42: =ISTEXT(D42) -> FALSE | O42: =ISNUMBER(D42) -> FALSE | P42: =OR(N42=TRUE,O42=TRUE) -> FALSE
N43: =ISTEXT(D43) -> FALSE | O43: =ISNUMBER(D43) -> FALSE | P43: =OR(N43=TRUE,O43=TRUE) -> FALSE
C44: =IF(P44=TRUE,1,) -> 1 | D44: Domicilio 1 / Address 1 | E44: =IF(P44=TRUE,12,) -> 12 | F44: 50 | G44: Nombre de la vía, domicilio 1 en el extranjero | N44: =ISTEXT(D44) -> TRUE | O44: =ISNUMBER(D44) -> FALSE | P44: =OR(N44=TRUE,O44=TRUE) -> TRUE
C45: =IF(P45=TRUE,C44+1,) -> 2 | D45: Datos complementarios del domicilio | E45: =IF(P45=TRUE,E44+F44,) -> 62 | F45: 40 | G45: Datos complementarios del domicilio | N45: =ISTEXT(D45) -> TRUE | O45: =ISNUMBER(D45) -> FALSE | P45: =OR(N45=TRUE,O45=TRUE) -> TRUE
C46: =IF(P46=TRUE,C45+1,) -> 3 | D46: Poblacion / Ciudad | E46: =IF(P46=TRUE,E45+F45,) -> 102 | F46: 30 | G46: Nombre localidad, población, etc. en el extranjero | N46: =ISTEXT(D46) -> TRUE | O46: =ISNUMBER(D46) -> FALSE | P46: =OR(N46=TRUE,O46=TRUE) -> TRUE
C47: =IF(P47=TRUE,C46+1,) -> 4 | D47: Codigo postal (ZIP) | E47: =IF(P47=TRUE,E46+F46,) -> 132 | F47: 10 | N47: =ISTEXT(D47) -> TRUE | O47: =ISNUMBER(D47) -> FALSE | P47: =OR(N47=TRUE,O47=TRUE) -> TRUE
C48: =IF(P48=TRUE,C47+1,) -> 5 | D48: Provincia / Region / Estado | E48: =IF(P48=TRUE,E47+F47,) -> 142 | F48: 30 | G48: Nombre de la Provincia / Region / Estado en el extranjero | N48: =ISTEXT(D48) -> TRUE | O48: =ISNUMBER(D48) -> FALSE | P48: =OR(N48=TRUE,O48=TRUE) -> TRUE
C49: =IF(P49=TRUE,C48+1,) -> 6 | D49: Pais | E49: =IF(P49=TRUE,E48+F48,) -> 172 | F49: 30 | N49: =ISTEXT(D49) -> TRUE | O49: =ISNUMBER(D49) -> FALSE | P49: =OR(N49=TRUE,O49=TRUE) -> TRUE
C50: =IF(P50=TRUE,C49+1,) -> 7 | D50: Codigo de pais | E50: =IF(P50=TRUE,E49+F49,) -> 202 | F50: 2 | G50: Código del país ISO-3166 (alfabético de dos letras) | N50: =ISTEXT(D50) -> TRUE | O50: =ISNUMBER(D50) -> FALSE | P50: =OR(N50=TRUE,O50=TRUE) -> TRUE
C51: =IF(P51=TRUE,C50+1,) -> 8 | D51: Posiciones reservadas para la AEAT | E51: =IF(P51=TRUE,E50+F50,) -> 204 | F51: 2 | N51: =ISTEXT(D51) -> TRUE | O51: =ISNUMBER(D51) -> FALSE | P51: =OR(N51=TRUE,O51=TRUE) -> TRUE
C52: =IF(P52=TRUE,C51+1,) -> 9 | D52: Fecha de modificación | E52: =IF(P52=TRUE,E51+F51,) -> 206 | F52: 8 | N52: =ISTEXT(D52) -> TRUE | O52: =ISNUMBER(D52) -> FALSE | P52: =OR(N52=TRUE,O52=TRUE) -> TRUE
C53: =IF(P53=TRUE,C52+1,) -> 0 | E53: =IF(P53=TRUE,E52+F52,) -> 0 | N53: =ISTEXT(D53) -> FALSE | O53: =ISNUMBER(D53) -> FALSE | P53: =OR(N53=TRUE,O53=TRUE) -> FALSE
C54: =IF(P54=TRUE,#REF!+1,) -> 0 | N54: =ISTEXT(D54) -> FALSE | O54: =ISNUMBER(D54) -> FALSE | P54: =OR(N54=TRUE,O54=TRUE) -> FALSE
C55: =IF(P55=TRUE,C54+1,) -> 0 | N55: =ISTEXT(D55) -> FALSE | O55: =ISNUMBER(D55) -> FALSE | P55: =OR(N55=TRUE,O55=TRUE) -> FALSE
C56: =IF(P56=TRUE,C55+1,) -> 0 | N56: =ISTEXT(D56) -> FALSE | O56: =ISNUMBER(D56) -> FALSE | P56: =OR(N56=TRUE,O56=TRUE) -> FALSE
C57: =IF(P57=TRUE,C56+1,) -> 0 | N57: =ISTEXT(D57) -> FALSE | O57: =ISNUMBER(D57) -> FALSE | P57: =OR(N57=TRUE,O57=TRUE) -> FALSE
C58: =IF(P58=TRUE,C57+1,) -> 0 | N58: =ISTEXT(D58) -> FALSE | O58: =ISNUMBER(D58) -> FALSE | P58: =OR(N58=TRUE,O58=TRUE) -> FALSE
C59: =IF(P59=TRUE,C58+1,) -> 0 | N59: =ISTEXT(D59) -> FALSE | O59: =ISNUMBER(D59) -> FALSE | P59: =OR(N59=TRUE,O59=TRUE) -> FALSE
C60: =IF(P60=TRUE,C59+1,) -> 0 | N60: =ISTEXT(D60) -> FALSE | O60: =ISNUMBER(D60) -> FALSE | P60: =OR(N60=TRUE,O60=TRUE) -> FALSE
C61: =IF(P61=TRUE,C60+1,) -> 0 | N61: =ISTEXT(D61) -> FALSE | O61: =ISNUMBER(D61) -> FALSE | P61: =OR(N61=TRUE,O61=TRUE) -> FALSE
C62: =IF(P62=TRUE,C61+1,) -> 0 | N62: =ISTEXT(D62) -> FALSE | O62: =ISNUMBER(D62) -> FALSE | P62: =OR(N62=TRUE,O62=TRUE) -> FALSE
C63: =IF(P63=TRUE,C62+1,) -> 0 | N63: =ISTEXT(D63) -> FALSE | O63: =ISNUMBER(D63) -> FALSE | P63: =OR(N63=TRUE,O63=TRUE) -> FALSE
C64: =IF(P64=TRUE,C63+1,) -> 0 | N64: =ISTEXT(D64) -> FALSE | O64: =ISNUMBER(D64) -> FALSE | P64: =OR(N64=TRUE,O64=TRUE) -> FALSE
C65: =IF(P65=TRUE,C64+1,) -> 0 | N65: =ISTEXT(D65) -> FALSE | O65: =ISNUMBER(D65) -> FALSE | P65: =OR(N65=TRUE,O65=TRUE) -> FALSE
C66: =IF(P66=TRUE,C65+1,) -> 0 | N66: =ISTEXT(D66) -> FALSE | O66: =ISNUMBER(D66) -> FALSE | P66: =OR(N66=TRUE,O66=TRUE) -> FALSE
... C89: =IF(P89=TRUE,C88+1,) -> 0 | N89: =ISTEXT(D89) -> FALSE | O89: =ISNUMBER(D89) -> FALSE | P89: =OR(N89=TRUE,O89=TRUE) -> FALSE

Sheet FA - Familia numerosa
D2: Diseño de registro de datos fiscales y personales
D3: ='CONTROL DE VERSIONES'!G68 -> IRPF 2025
D4: Familia numerosa
C5: =IF(P5=TRUE,C4+1,) -> 0
C6: =IF(P6=TRUE,C5+1,) -> 0
C7: Este concepto de datos fiscales incluye los datos de familia numerosa con origen en el modelo 990
C9: Nº | D9: Nombre | E9: Posición | F9: Longitud | G9: Descripción
C10: =IF(P10=TRUE,1,) -> 1 | D10: Tipo | E10: =IF(P10=TRUE,1,) -> 1 | F10: 1 | G10: Tipo de registro = '2' | N10: =ISTEXT(D10) -> TRUE | O10: =ISNUMBER(D10) -> FALSE | P10: =OR(N10=TRUE,O10=TRUE) -> TRUE
C11: =IF(P11=TRUE,C10+1,) -> 2 | D11: Código | E11: =IF(P11=TRUE,E10+F10,) -> 2 | F11: 7 | G11: 'FAnnnnn' Donde 'Fannnnn' será siempre igual a 'FA00001' | N11: =ISTEXT(D11) -> TRUE | O11: =ISNUMBER(D11) -> FALSE | P11: =OR(N11=TRUE,O11=TRUE) -> TRUE
C12: =IF(P12=TRUE,C11+1,) -> 3 | D12: NIF del declarante | E12: =IF(P12=TRUE,E11+F11,) -> 9 | F12: 9 | N12: =ISTEXT(D12) -> TRUE | O12: =ISNUMBER(D12) -> FALSE | P12: =OR(N12=TRUE,O12=TRUE) -> TRUE
C13: =IF(P13=TRUE,C12+1,) -> 4 | D13: Nombre del declarante | E13: =IF(P13=TRUE,E12+F12,) -> 18 | F13: 40 | N13: =ISTEXT(D13) -> TRUE | O13: =ISNUMBER(D13) -> FALSE | P13: =OR(N13=TRUE,O13=TRUE) -> TRUE
C14: =IF(P14=TRUE,C13+1,) -> 5 | D14: Tipo de familia numerosa | E14: =IF(P14=TRUE,E13+F13,) -> 58 | F14: 1 | G14: Valores: 'G' - General 'E' - Especial | N14: =ISTEXT(D14) -> TRUE | O14: =ISNUMBER(D14) -> FALSE | P14: =OR(N14=TRUE,O14=TRUE) -> TRUE
C15: =IF(P15=TRUE,C14+1,) -> 6 | D15: Número de identificación familia numerosa | E15: =IF(P15=TRUE,E14+F14,) -> 59 | F15: 30 | N15: =ISTEXT(D15) -> TRUE | O15: =ISNUMBER(D15) -> FALSE | P15: =OR(N15=TRUE,O15=TRUE) -> TRUE
C16: =IF(P16=TRUE,C15+1,) -> 7 | D16: Posiciones reservadas para la AEAT | E16: =IF(P16=TRUE,E15+F15,) -> 89 | F16: 2 | N16: =ISTEXT(D16) -> TRUE | O16: =ISNUMBER(D16) -> FALSE | P16: =OR(N16=TRUE,O16=TRUE) -> TRUE
C17: =IF(P17=TRUE,C16+1,) -> 0 | E17: =IF(P17=TRUE,E16+F16,) -> 0 | N17: =ISTEXT(D17) -> FALSE | O17: =ISNUMBER(D17) -> FALSE | P17: =OR(N17=TRUE,O17=TRUE) -> FALSE
C18: =IF(P18=TRUE,C17+1,) -> 0 | E18: =IF(P18=TRUE,E17+F17,) -> 0 | N18: =ISTEXT(D18) -> FALSE | O18: =ISNUMBER(D18) -> FALSE | P18: =OR(N18=TRUE,O18=TRUE) -> FALSE
C19: =IF(P19=TRUE,C18+1,) -> 0 | E19: =IF(P19=TRUE,E18+F18,) -> 0 | N19: =ISTEXT(D19) -> FALSE | O19: =ISNUMBER(D19) -> FALSE | P19: =OR(N19=TRUE,O19=TRUE) -> FALSE
C20: =IF(P20=TRUE,C19+1,) -> 0 | E20: =IF(P20=TRUE,E19+F19,) -> 0 | N20: =ISTEXT(D20) -> FALSE | O20: =ISNUMBER(D20) -> FALSE | P20: =OR(N20=TRUE,O20=TRUE) -> FALSE
C21: =IF(P21=TRUE,C20+1,) -> 0 | E21: =IF(P21=TRUE,E20+F20,) -> 0 | N21: =ISTEXT(D21) -> FALSE | O21: =ISNUMBER(D21) -> FALSE | P21: =OR(N21=TRUE,O21=TRUE) -> FALSE
C22: =IF(P22=TRUE,C21+1,) -> 0 | E22: =IF(P22=TRUE,E21+F21,) -> 0 | N22: =ISTEXT(D22) -> FALSE | O22: =ISNUMBER(D22) -> FALSE | P22: =OR(N22=TRUE,O22=TRUE) -> FALSE
C23: =IF(P23=TRUE,C22+1,) -> 0 | E23: =IF(P23=TRUE,E22+F22,) -> 0 | N23: =ISTEXT(D23) -> FALSE | O23: =ISNUMBER(D23) -> FALSE | P23: =OR(N23=TRUE,O23=TRUE) -> FALSE
C24: =IF(P24=TRUE,C23+1,) -> 0 | E24: =IF(P24=TRUE,E23+F23,) -> 0 | N24: =ISTEXT(D24) -> FALSE | O24: =ISNUMBER(D24) -> FALSE | P24: =OR(N24=TRUE,O24=TRUE) -> FALSE
C25: =IF(P25=TRUE,C24+1,) -> 0 | E25: =IF(P25=TRUE,E24+F24,) -> 0 | N25: =ISTEXT(D25) -> FALSE | O25: =ISNUMBER(D25) -> FALSE | P25: =OR(N25=TRUE,O25=TRUE) -> FALSE
C26: =IF(P26=TRUE,C25+1,) -> 0 | E26: =IF(P26=TRUE,E25+F25,) -> 0 | N26: =ISTEXT(D26) -> FALSE | O26: =ISNUMBER(D26) -> FALSE | P26: =OR(N26=TRUE,O26=TRUE) -> FALSE
C27: =IF(P27=TRUE,C26+1,) -> 0 | E27: =IF(P27=TRUE,E26+F26,) -> 0 | N27: =ISTEXT(D27) -> FALSE | O27: =ISNUMBER(D27) -> FALSE | P27: =OR(N27=TRUE,O27=TRUE) -> FALSE
C28: =IF(P28=TRUE,C27+1,) -> 0 | E28: =IF(P28=TRUE,E27+F27,) -> 0 | N28: =ISTEXT(D28) -> FALSE | O28: =ISNUMBER(D28) -> FALSE | P28: =OR(N28=TRUE,O28=TRUE) -> FALSE
... C99: =IF(P99=TRUE,C98+1,) -> 0 | E99: =IF(P99=TRUE,E98+F98,) -> 0 | N99: =ISTEXT(D99) -> FALSE | O99: =ISNUMBER(D99) -> FALSE | P99: =OR(N99=TRUE,O99=TRUE) -> FALSE

Sheet DI - Discapacidad
D2: Diseño de registro de datos fiscales y personales
D3: ='CONTROL DE VERSIONES'!G68 -> IRPF 2025
D4: Discapacidad
C5: =IF(P5=TRUE,C4+1,) -> 0
C6: =IF(P6=TRUE,C5+1,) -> 0
C7: Este concepto de datos fiscales incluye los datos por discapacidad con origen en el Modelo 990
C9: Nº | D9: Nombre | E9: Posición | F9: Longitud | G9: Descripción
C10: =IF(P10=TRUE,1,) -> 1 | D10: Tipo | E10: =IF(P10=TRUE,1,) -> 1 | F10: 1 | G10: Tipo de registro = '2' | N10: =ISTEXT(D10) -> TRUE | O10: =ISNUMBER(D10) -> FALSE | P10: =OR(N10=TRUE,O10=TRUE) -> TRUE
C11: =IF(P11=TRUE,C10+1,) -> 2 | D11: Código | E11: =IF(P11=TRUE,E10+F10,) -> 2 | F11: 7 | G11: 'DInnnnn' Donde 'DInnnnn' será siempre igual a 'DI00001' | N11: =ISTEXT(D11) -> TRUE | O11: =ISNUMBER(D11) -> FALSE | P11: =OR(N11=TRUE,O11=TRUE) -> TRUE
C12: =IF(P12=TRUE,C11+1,) -> 3 | D12: NIF del declarante | E12: =IF(P12=TRUE,E11+F11,) -> 9 | F12: 9 | N12: =ISTEXT(D12) -> TRUE | O12: =ISNUMBER(D12) -> FALSE | P12: =OR(N12=TRUE,O12=TRUE) -> TRUE
C13: =IF(P13=TRUE,C12+1,) -> 4 | D13: Nombre del declarante | E13: =IF(P13=TRUE,E12+F12,) -> 18 | F13: 40 | N13: =ISTEXT(D13) -> TRUE | O13: =ISNUMBER(D13) -> FALSE | P13: =OR(N13=TRUE,O13=TRUE) -> TRUE
C14: =IF(P14=TRUE,C13+1,) -> 5 | D14: Grado de discapacidad | E14: =IF(P14=TRUE,E13+F13,) -> 58 | F14: 3 | N14: =ISTEXT(D14) -> TRUE | O14: =ISNUMBER(D14) -> FALSE | P14: =OR(N14=TRUE,O14=TRUE) -> TRUE
C15: =IF(P15=TRUE,C14+1,) -> 6 | D15: Necesidad de ayuda de terceras personas | E15: =IF(P15=TRUE,E14+F14,) -> 61 | F15: 1 | G15: " " - NO "S" - SI | N15: =ISTEXT(D15) -> TRUE | O15: =ISNUMBER(D15) -> FALSE | P15: =OR(N15=TRUE,O15=TRUE) -> TRUE
C16: =IF(P16=TRUE,C15+1,) -> 7 | D16: Movilidad reducida | E16: =IF(P16=TRUE,E15+F15,) -> 62 | F16: 1 | G16: " " - NO "S" - SI | N16: =ISTEXT(D16) -> TRUE | O16: =ISNUMBER(D16) -> FALSE | P16: =OR(N16=TRUE,O16=TRUE) -> TRUE
C17: =IF(P17=TRUE,C16+1,) -> 0 | E17: =IF(P17=TRUE,E16+F16,) -> 0 | N17: =ISTEXT(D17) -> FALSE | O17: =ISNUMBER(D17) -> FALSE | P17: =OR(N17=TRUE,O17=TRUE) -> FALSE
C18: =IF(P18=TRUE,C17+1,) -> 0 | E18: =IF(P18=TRUE,E17+F17,) -> 0 | N18: =ISTEXT(D18) -> FALSE | O18: =ISNUMBER(D18) -> FALSE | P18: =OR(N18=TRUE,O18=TRUE) -> FALSE
C19: =IF(P19=TRUE,C18+1,) -> 0 | E19: =IF(P19=TRUE,E18+F18,) -> 0 | N19: =ISTEXT(D19) -> FALSE | O19: =ISNUMBER(D19) -> FALSE | P19: =OR(N19=TRUE,O19=TRUE) -> FALSE
C20: =IF(P20=TRUE,C19+1,) -> 0 | E20: =IF(P20=TRUE,E19+F19,) -> 0 | N20: =ISTEXT(D20) -> FALSE | O20: =ISNUMBER(D20) -> FALSE | P20: =OR(N20=TRUE,O20=TRUE) -> FALSE
C21: =IF(P21=TRUE,C20+1,) -> 0 | E21: =IF(P21=TRUE,E20+F20,) -> 0 | N21: =ISTEXT(D21) -> FALSE | O21: =ISNUMBER(D21) -> FALSE | P21: =OR(N21=TRUE,O21=TRUE) -> FALSE
C22: =IF(P22=TRUE,C21+1,) -> 0 | E22: =IF(P22=TRUE,E21+F21,) -> 0 | N22: =ISTEXT(D22) -> FALSE | O22: =ISNUMBER(D22) -> FALSE | P22: =OR(N22=TRUE,O22=TRUE) -> FALSE
C23: =IF(P23=TRUE,C22+1,) -> 0 | E23: =IF(P23=TRUE,E22+F22,) -> 0 | N23: =ISTEXT(D23) -> FALSE | O23: =ISNUMBER(D23) -> FALSE | P23: =OR(N23=TRUE,O23=TRUE) -> FALSE
C24: =IF(P24=TRUE,C23+1,) -> 0 | E24: =IF(P24=TRUE,E23+F23,) -> 0 | N24: =ISTEXT(D24) -> FALSE | O24: =ISNUMBER(D24) -> FALSE | P24: =OR(N24=TRUE,O24=TRUE) -> FALSE
C25: =IF(P25=TRUE,C24+1,) -> 0 | E25: =IF(P25=TRUE,E24+F24,) -> 0 | N25: =ISTEXT(D25) -> FALSE | O25: =ISNUMBER(D25) -> FALSE | P25: =OR(N25=TRUE,O25=TRUE) -> FALSE
C26: =IF(P26=TRUE,C25+1,) -> 0 | E26: =IF(P26=TRUE,E25+F25,) -> 0 | N26: =ISTEXT(D26) -> FALSE | O26: =ISNUMBER(D26) -> FALSE | P26: =OR(N26=TRUE,O26=TRUE) -> FALSE
C27: =IF(P27=TRUE,C26+1,) -> 0 | E27: =IF(P27=TRUE,E26+F26,) -> 0 | N27: =ISTEXT(D27) -> FALSE | O27: =ISNUMBER(D27) -> FALSE | P27: =OR(N27=TRUE,O27=TRUE) -> FALSE
C28: =IF(P28=TRUE,C27+1,) -> 0 | E28: =IF(P28=TRUE,E27+F27,) -> 0 | N28: =ISTEXT(D28) -> FALSE | O28: =ISNUMBER(D28) -> FALSE | P28: =OR(N28=TRUE,O28=TRUE) -> FALSE
... C99: =IF(P99=TRUE,C98+1,) -> 0 | E99: =IF(P99=TRUE,E98+F98,) -> 0 | N99: =ISTEXT(D99) -> FALSE | O99: =ISNUMBER(D99) -> FALSE | P99: =OR(N99=TRUE,O99=TRUE) -> FALSE

Sheet RTA - Rdto. trabajo mod 190
D2: Diseño de registro de datos fiscales y personales
D3: ='CONTROL DE VERSIONES'!G68 -> IRPF 2025
D4: Rendimientos del trabajo del modelo 190
C5: =IF(P5=TRUE,C4+1,) -> 0
C6: =IF(P6=TRUE,C5+1,) -> 0
C7: Este concepto de datos fiscales incluye los rendimientos del trabajo del Modelo 190
C9: Nº | D9: Nombre | E9: Posición | F9: Longitud | G9: Descripción
C10: =IF(P10=TRUE,1,) -> 1 | D10: Tipo | E10: =IF(P10=TRUE,1,) -> 1 | F10: 1 | G10: Tipo de registro = '2' | N10: =ISTEXT(D10) -> TRUE | O10: =ISNUMBER(D10) -> FALSE | P10: =OR(N10=TRUE,O10=TRUE) -> TRUE
C11: =IF(P11=TRUE,C10+1,) -> 2 | D11: Código concepto | E11: =IF(P11=TRUE,E10+F10,) -> 2 | F11: 7 | G11: RTAnnnn' Donde nnnn es el número del registro de este tipo contenido en el fichero de datos fiscales. | N11: =ISTEXT(D11) -> TRUE | O11: =ISNUMBER(D11) -> FALSE | P11: =OR(N11=TRUE,O11=TRUE) -> TRUE
C12: =IF(P12=TRUE,C11+1,) -> 3 | D12: NIF pagador | E12: =IF(P12=TRUE,E11+F11,) -> 9 | F12: 9 | G12: NIF declarante | N12: =ISTEXT(D12) -> TRUE | O12: =ISNUMBER(D12) -> FALSE | P12: =OR(N12=TRUE,O12=TRUE) -> TRUE
C13: =IF(P13=TRUE,C12+1,) -> 4 | D13: Nombre del pagador | E13: =IF(P13=TRUE,E12+F12,) -> 18 | F13: 40 | G13: Razón Social / Apellidos y nombre del declarante | N13: =ISTEXT(D13) -> TRUE | O13: =ISNUMBER(D13) -> FALSE | P13: =OR(N13=TRUE,O13=TRUE) -> TRUE
C14: =IF(P14=TRUE,C13+1,) -> 5 | D14: Clave y Subclave de percepcion | E14: =IF(P14=TRUE,E13+F13,) -> 58 | F14: 3 | G14: Se entregará en cada registro una de las siguientes combinaciones de las claves y subclaves de percepción del modelo 190: ‘A ‘ - Empleados ‘B1‘ - Prestación ‘B2‘ - Prestación ‘B3‘ - Prestación ‘B4‘ - Prestación ‘B99‘ - Prestación ‘C1 ‘ - Desempleo ‘C2 ‘ - Prestación ERE ‘C3 ‘ - Prestación ERTE ‘C4 ‘ - Prestación autónomos ‘C5 ‘ - Subsidio desempleo ‘C6 ‘ - Renta activa inserción ‘C7 ‘ - Otras prestaciones contributivas ‘C8 ‘ - Otras prestaciones no contributivas ‘C9 ‘ - Prestaciones de varios tipos ‘E1‘ - Consejero ‘E2‘ - Consejero ‘E3‘ - Consejero ‘E4‘ - Consejero ‘F1‘ - Cursos, conf. ‘F2‘ - Cursos, conf. ‘F3‘ - Obras lit., art., cient. ‘F4‘ - Obras lit., art., cient. ‘F5‘ - Propiedad intelectual ‘F6‘ - Propiedad intelectual ‘F7‘ - Derechos de autor | N14: =ISTEXT(D14) -> TRUE | O14: =ISNUMBER(D14) -> FALSE | P14: =OR(N14=TRUE,O14=TRUE) -> TRUE
C15: =IF(P15=TRUE,C14+1,) -> 6 | D15: Percepciones dinerarias | E15: =IF(P15=TRUE,E14+F14,) -> 61 | F15: 13 | N15: =ISTEXT(D15) -> TRUE | O15: =ISNUMBER(D15) -> FALSE | P15: =OR(N15=TRUE,O15=TRUE) -> TRUE
C16: =IF(P16=TRUE,C15+1,) -> 7 | D16: Retenciones | E16: =IF(P16=TRUE,E15+F15,) -> 74 | F16: 13 | N16: =ISTEXT(D16) -> TRUE | O16: =ISNUMBER(D16) -> FALSE | P16: =OR(N16=TRUE,O16=TRUE) -> TRUE
C17: =IF(P17=TRUE,C16+1,) -> 8 | D17: Retribuciones en especie | E17: =IF(P17=TRUE,E16+F16,) -> 87 | F17: 13 | G17: Campo calculado de acuerdo a la siguiente fórmula: Retribuciones en Especie = Valoración (de la percepción en especie) declarada en el modelo + Ingresos a cuenta efectuados – Ingresos a cuenta repercutidos. | N17: =ISTEXT(D17) -> TRUE | O17: =ISNUMBER(D17) -> FALSE | P17: =OR(N17=TRUE,O17=TRUE) -> TRUE
C18: =IF(P18=TRUE,C17+1,) -> 9 | D18: Valoración | E18: =IF(P18=TRUE,E17+F17,) -> 100 | F18: 13 | N18: =ISTEXT(D18) -> TRUE | O18: =ISNUMBER(D18) -> FALSE | P18: =OR(N18=TRUE,O18=TRUE) -> TRUE
C19: =IF(P19=TRUE,C18+1,) -> 10 | D19: Ingresos a cuenta efectuados | E19: =IF(P19=TRUE,E18+F18,) -> 113 | F19: 13 | G19: Ingresos a cuenta efectuados de las percepciones en especie | N19: =ISTEXT(D19) -> TRUE | O19: =ISNUMBER(D19) -> FALSE | P19: =OR(N19=TRUE,O19=TRUE) -> TRUE
C20: =IF(P20=TRUE,C19+1,) -> 11 | D20: Ingresos a cuenta repercutidos | E20: =IF(P20=TRUE,E19+F19,) -> 126 | F20: 13 | G20: Ingresos a cuenta repercutidos de las percepciones en especie | N20: =ISTEXT(D20) -> TRUE | O20: =ISNUMBER(D20) -> FALSE | P20: =OR(N20=TRUE,O20=TRUE) -> TRUE
C21: =IF(P21=TRUE,C20+1,) -> 12 | D21: Gastos deducibles | E21: =IF(P21=TRUE,E20+F20,) -> 139 | F21: 13 | N21: =ISTEXT(D21) -> TRUE | O21: =ISNUMBER(D21) -> FALSE | P21: =OR(N21=TRUE,O21=TRUE) -> TRUE
C22: =IF(P22=TRUE,C21+1,) -> 13 | D22: Reducciones aplicables | E22: =IF(P22=TRUE,E21+F21,) -> 152 | F22: 13 | N22: =ISTEXT(D22) -> TRUE | O22: =ISNUMBER(D22) -> FALSE | P22: =OR(N22=TRUE,O22=TRUE) -> TRUE
C23: =IF(P23=TRUE,C22+1,) -> 14 | D23: Retribucion dineraria por Incapacidad Laboral | E23: =IF(P23=TRUE,E22+F22,) -> 165 | F23: 13 | N23: =ISTEXT(D23) -> TRUE | O23: =ISNUMBER(D23) -> FALSE | P23: =OR(N23=TRUE,O23=TRUE) -> TRUE
C24: =IF(P24=TRUE,C23+1,) -> 15 | D24: Retencion Incapacidad Laboral | E24: =IF(P24=TRUE,E23+F23,) -> 178 | F24: 13 | N24: =ISTEXT(D24) -> TRUE | O24: =ISNUMBER(D24) -> FALSE | P24: =OR(N24=TRUE,O24=TRUE) -> TRUE
C25: =IF(P25=TRUE,C24+1,) -> 16 | D25: Retribucion en especie Incapacidad Laboral | E25: =IF(P25=TRUE,E24+F24,) -> 191 | F25: 13 | G25: Campo calculado de acuerdo a la siguiente fórmula: Retribuciones en Especie = Valoración (de la percepción en especie) declarada IL en el modelo + Ingresos a cuenta efectuados IL – Ingresos a cuenta repercutidos IL. | N25: =ISTEXT(D25) -> TRUE | O25: =ISNUMBER(D25) -> FALSE | P25: =OR(N25=TRUE,O25=TRUE) -> TRUE
C26: =IF(P26=TRUE,C25+1,) -> 17 | D26: Valoracion Incapacidad Laboral | E26: =IF(P26=TRUE,E25+F25,) -> 204 | F26: 13 | N26: =ISTEXT(D26) -> TRUE | O26: =ISNUMBER(D26) -> FALSE | P26: =OR(N26=TRUE,O26=TRUE) -> TRUE
C27: =IF(P27=TRUE,C26+1,) -> 18 | D27: Ingreso a cuenta Incapacidad Laboral | E27: =IF(P27=TRUE,E26+F26,) -> 217 | F27: 13 | N27: =ISTEXT(D27) -> TRUE | O27: =ISNUMBER(D27) -> FALSE | P27: =OR(N27=TRUE,O27=TRUE) -> TRUE
C28: =IF(P28=TRUE,C27+1,) -> 19 | D28: Ingresos a cuenta repercutidos por Incapacidad Laboral | E28: =IF(P28=TRUE,E27+F27,) -> 230 | F28: 13 | N28: =ISTEXT(D28) -> TRUE | O28: =ISNUMBER(D28) -> FALSE | P28: =OR(N28=TRUE,O28=TRUE) -> TRUE
C29: =IF(P29=TRUE,C28+1,) -> 20 | D29: Movilidad geografica | E29: =IF(P29=TRUE,E28+F28,) -> 243 | F29: 1 | G29: Valores posibles: '0' - NO '1' - SI | N29: =ISTEXT(D29) -> TRUE | O29: =ISNUMBER(D29) -> FALSE | P29: =OR(N29=TRUE,O29=TRUE) -> TRUE
C30: =IF(P30=TRUE,C29+1,) -> 21 | D30: Discapacidad | E30: =IF(P30=TRUE,E29+F29,) -> 244 | F30: 1 | G30: Valores posibles: ‘0’ - No padece discapacidad o discapacidad < 33%, ‘1’ - Discapacidad ≥ 33% o < 65%. ‘2’ - Discapacidad ≥ 33% o < 65% y necesita ayuda 3ª persona. ‘3’ - Discapacidad ≥ 65%. | N30: =ISTEXT(D30) -> TRUE | O30: =ISNUMBER(D30) -> FALSE | P30: =OR(N30=TRUE,O30=TRUE) -> TRUE
C31: =IF(P31=TRUE,C30+1,) -> 22 | D31: Marca percepciones FOGASA | E31: =IF(P31=TRUE,E30+F30,) -> 245 | F31: 1 | G31: Pago efectuado por el Fondo de Garantía Salarial (FOGASA) Valores posibles: 'S' - SI 'N' - NO | N31: =ISTEXT(D31) -> TRUE | O31: =ISNUMBER(D31) -> FALSE | P31: =OR(N31=TRUE,O31=TRUE) -> TRUE
C32: =IF(P32=TRUE,C31+1,) -> 23 | D32: Marca especie | E32: =IF(P32=TRUE,E31+F31,) -> 246 | F32: 1 | G32: Valores posibles: '1' - SI '0' - NO | N32: =ISTEXT(D32) -> TRUE | O32: =ISNUMBER(D32) -> FALSE | P32: =OR(N32=TRUE,O32=TRUE) -> TRUE
C33: =IF(P33=TRUE,C32+1,) -> 24 | D33: Subtipos B01 | E33: =IF(P33=TRUE,E32+F32,) -> 247 | F33: 5 | N33: =ISTEXT(D33) -> TRUE | O33: =ISNUMBER(D33) -> FALSE | P33: =OR(N33=TRUE,O33=TRUE) -> TRUE
C34: =IF(P34=TRUE,C33+1,) -> 25 | D34: Obtenidos Gestión Fondos | E34: =IF(P34=TRUE,E33+F33,) -> 252 | F34: 1 | G34: Valores posibles: '1' - SI '0' - NO | N34: =ISTEXT(D34) -> TRUE | O34: =ISNUMBER(D34) -> FALSE | P34: =OR(N34=TRUE,O34=TRUE) -> TRUE
C35: =IF(P35=TRUE,C34+1,) -> 0 | E35: =IF(P35=TRUE,E34+F34,) -> 0 | N35: =ISTEXT(D35) -> FALSE | O35: =ISNUMBER(D35) -> FALSE | P35: =OR(N35=TRUE,O35=TRUE) -> FALSE
C36: =IF(P36=TRUE,C35+1,) -> 0 | E36: =IF(P36=TRUE,E35+F35,) -> 0 | N36: =ISTEXT(D36) -> FALSE | O36: =ISNUMBER(D36) -> FALSE | P36: =OR(N36=TRUE,O36=TRUE) -> FALSE
C37: =IF(P37=TRUE,C36+1,) -> 0 | E37: =IF(P37=TRUE,E36+F36,) -> 0 | N37: =ISTEXT(D37) -> FALSE | O37: =ISNUMBER(D37) -> FALSE | P37: =OR(N37=TRUE,O37=TRUE) -> FALSE
C38: =IF(P38=TRUE,C37+1,) -> 0 | E38: =IF(P38=TRUE,E37+F37,) -> 0 | N38: =ISTEXT(D38) -> FALSE | O38: =ISNUMBER(D38) -> FALSE | P38: =OR(N38=TRUE,O38=TRUE) -> FALSE
C39: =IF(P39=TRUE,C38+1,) -> 0 | E39: =IF(P39=TRUE,E38+F38,) -> 0 | N39: =ISTEXT(D39) -> FALSE | O39: =ISNUMBER(D39) -> FALSE | P39: =OR(N39=TRUE,O39=TRUE) -> FALSE
C40: =IF(P40=TRUE,C39+1,) -> 0 | E40: =IF(P40=TRUE,E39+F39,) -> 0 | N40: =ISTEXT(D40) -> FALSE | O40: =ISNUMBER(D40) -> FALSE | P40: =OR(N40=TRUE,O40=TRUE) -> FALSE
C41: =IF(P41=TRUE,C40+1,) -> 0 | E41: =IF(P41=TRUE,E40+F40,) -> 0 | N41: =ISTEXT(D41) -> FALSE | O41: =ISNUMBER(D41) -> FALSE | P41: =OR(N41=TRUE,O41=TRUE) -> FALSE
C42: =IF(P42=TRUE,C41+1,) -> 0 | E42: =IF(P42=TRUE,E41+F41,) -> 0 | N42: =ISTEXT(D42) -> FALSE | O42: =ISNUMBER(D42) -> FALSE | P42: =OR(N42=TRUE,O42=TRUE) -> FALSE
C43: =IF(P43=TRUE,C42+1,) -> 0 | E43: =IF(P43=TRUE,E42+F42,) -> 0 | N43: =ISTEXT(D43) -> FALSE | O43: =ISNUMBER(D43) -> FALSE | P43: =OR(N43=TRUE,O43=TRUE) -> FALSE
C44: =IF(P44=TRUE,C43+1,) -> 0 | E44: =IF(P44=TRUE,E43+F43,) -> 0 | N44: =ISTEXT(D44) -> FALSE | O44: =ISNUMBER(D44) -> FALSE | P44: =OR(N44=TRUE,O44=TRUE) -> FALSE
C45: =IF(P45=TRUE,C44+1,) -> 0 | E45: =IF(P45=TRUE,E44+F44,) -> 0 | N45: =ISTEXT(D45) -> FALSE | O45: =ISNUMBER(D45) -> FALSE | P45: =OR(N45=TRUE,O45=TRUE) -> FALSE
C46: =IF(P46=TRUE,C45+1,) -> 0 | E46: =IF(P46=TRUE,E45+F45,) -> 0 | N46: =ISTEXT(D46) -> FALSE | O46: =ISNUMBER(D46) -> FALSE | P46: =OR(N46=TRUE,O46=TRUE) -> FALSE
... C99: =IF(P99=TRUE,C98+1,) -> 0 | E99: =IF(P99=TRUE,E98+F98,) -> 0 | N99: =ISTEXT(D99) -> FALSE | O99: =ISNUMBER(D99) -> FALSE | P99: =OR(N99=TRUE,O99=TRUE) -> FALSE

Sheet RTD - Rentas exentas
D2: Diseño de registro de datos fiscales y personales
D3: ='CONTROL DE VERSIONES'!G68 -> IRPF 2025
D4: Rentas exentas
C5: =IF(P5=TRUE,C4+1,) -> 0
C6: =IF(P6=TRUE,C5+1,) -> 0
C7: Este concepto de datos fiscales incluye las rentas exentas con origen en el Modelo 190. - La subclave L29 (Prestaciones económicas en concepto de ingreso mínimo vital - IMV) se remite siempre. Dichas cantidades están exentas de tributación en IRPF. No obstante, el artículo 33 del RDLey 20/2020 establece la obligación de presentar anualmente declaración de IRPF para todos los beneficiarios del IMV integrantes de la unidad de convivencia. - Las subclaves L22 y L28 solo se remiten si el importe conjunto percibido de las subclave L22, L28 y/o L29 supera el límite máximo anual que establece el artículo 7. letra y) de la LIRPF como cuantía exenta de tributación, fijada en 1,5 veces el IPREM (12.159,42 € para 2022) (indicador público de rentas de efectos múltiples), el exceso deberá consignarse en la declaración de IRPF, teniendo la consideración de rendimiento de trabajo personal.
C9: Nº | D9: Nombre | E9: Posición | F9: Longitud | G9: Descripción
C10: =IF(P10=TRUE,1,) -> 1 | D10: Tipo | E10: =IF(P10=TRUE,1,) -> 1 | F10: 1 | G10: Tipo de registro = '2' | N10: =ISTEXT(D10) -> TRUE | O10: =ISNUMBER(D10) -> FALSE | P10: =OR(N10=TRUE,O10=TRUE) -> TRUE
C11: =IF(P11=TRUE,C10+1,) -> 2 | D11: Código | E11: =IF(P11=TRUE,E10+F10,) -> 2 | F11: 7 | G11: 'RTDnnnn' Donde nnnn es el número del registro de este tipo contenido en el fichero de datos fiscales. | N11: =ISTEXT(D11) -> TRUE | O11: =ISNUMBER(D11) -> FALSE | P11: =OR(N11=TRUE,O11=TRUE) -> TRUE
C12: =IF(P12=TRUE,C11+1,) -> 3 | D12: NIF del pagador | E12: =IF(P12=TRUE,E11+F11,) -> 9 | F12: 9 | N12: =ISTEXT(D12) -> TRUE | O12: =ISNUMBER(D12) -> FALSE | P12: =OR(N12=TRUE,O12=TRUE) -> TRUE
C13: =IF(P13=TRUE,C12+1,) -> 4 | D13: Nombre del pagador | E13: =IF(P13=TRUE,E12+F12,) -> 18 | F13: 40 | N13: =ISTEXT(D13) -> TRUE | O13: =ISNUMBER(D13) -> FALSE | P13: =OR(N13=TRUE,O13=TRUE) -> TRUE
C14: =IF(P14=TRUE,C13+1,) -> 5 | D14: Clave y subclave | E14: =IF(P14=TRUE,E13+F13,) -> 58 | F14: 3 | G14: Clave(1) + Subclave (2) Claves: 'L05' - Indemnizaciones 'L10' - Becas 'L22' - Otras ayudas de CCAA y EELL de carácter social 'L25' - Ayuda empresas para guarderías 'L26' - Ayuda guarderías a sus empleados 'L27' - Prestaciones maternidad o paternidad 'L28' - Renta mínima de inserción 'L29' - Ingreso mínimo vital | N14: =ISTEXT(D14) -> TRUE | O14: =ISNUMBER(D14) -> FALSE | P14: =OR(N14=TRUE,O14=TRUE) -> TRUE
C15: =IF(P16=TRUE,C14+1,) -> 6 | D15: Retribución dineraria | E15: =IF(P16=TRUE,E14+F14,) -> 61 | F15: 13
C16: =IF(P16=TRUE,C15+1,) -> 7 | D16: Retribución en especie | E16: 74 | F16: 13 | G16: (Valoración dda. + Ing cat efec. - ing.cta repercutido) Campo calculado de acuerdo a la siguiente fórmula: Retribuciones en Especie = Valoración (de la percepción en especie) declarada en el modelo + Ingresos a cuenta efectuados – Ingresos a cuenta repercutidos. | N16: =ISTEXT(D15) -> TRUE | O16: =ISNUMBER(D15) -> FALSE | P16: =OR(N16=TRUE,O16=TRUE) -> TRUE
C17: 8 | D17: Gastos deducibles | E17: 87 | F17: 13 | N17: =ISTEXT(D17) -> TRUE | O17: =ISNUMBER(D17) -> FALSE | P17: =OR(N17=TRUE,O17=TRUE) -> TRUE
C18: =IF(P18=TRUE,C17+1,) -> 0 | E18: =IF(P18=TRUE,E17+F17,) -> 0 | N18: =ISTEXT(D18) -> FALSE | O18: =ISNUMBER(D18) -> FALSE | P18: =OR(N18=TRUE,O18=TRUE) -> FALSE
C19: =IF(P19=TRUE,C18+1,) -> 0 | E19: =IF(P19=TRUE,E18+F18,) -> 0 | N19: =ISTEXT(D19) -> FALSE | O19: =ISNUMBER(D19) -> FALSE | P19: =OR(N19=TRUE,O19=TRUE) -> FALSE
C20: =IF(P20=TRUE,C19+1,) -> 0 | E20: =IF(P20=TRUE,E19+F19,) -> 0 | N20: =ISTEXT(D20) -> FALSE | O20: =ISNUMBER(D20) -> FALSE | P20: =OR(N20=TRUE,O20=TRUE) -> FALSE
C21: =IF(P21=TRUE,C20+1,) -> 0 | E21: =IF(P21=TRUE,E20+F20,) -> 0 | N21: =ISTEXT(D21) -> FALSE | O21: =ISNUMBER(D21) -> FALSE | P21: =OR(N21=TRUE,O21=TRUE) -> FALSE
C22: =IF(P22=TRUE,C21+1,) -> 0 | E22: =IF(P22=TRUE,E21+F21,) -> 0 | N22: =ISTEXT(D22) -> FALSE | O22: =ISNUMBER(D22) -> FALSE | P22: =OR(N22=TRUE,O22=TRUE) -> FALSE
C23: =IF(P23=TRUE,C22+1,) -> 0 | E23: =IF(P23=TRUE,E22+F22,) -> 0 | N23: =ISTEXT(D23) -> FALSE | O23: =ISNUMBER(D23) -> FALSE | P23: =OR(N23=TRUE,O23=TRUE) -> FALSE
C24: =IF(P24=TRUE,C23+1,) -> 0 | E24: =IF(P24=TRUE,E23+F23,) -> 0 | N24: =ISTEXT(D24) -> FALSE | O24: =ISNUMBER(D24) -> FALSE | P24: =OR(N24=TRUE,O24=TRUE) -> FALSE
C25: =IF(P25=TRUE,C24+1,) -> 0 | E25: =IF(P25=TRUE,E24+F24,) -> 0 | N25: =ISTEXT(D25) -> FALSE | O25: =ISNUMBER(D25) -> FALSE | P25: =OR(N25=TRUE,O25=TRUE) -> FALSE
C26: =IF(P26=TRUE,C25+1,) -> 0 | E26: =IF(P26=TRUE,E25+F25,) -> 0 | N26: =ISTEXT(D26) -> FALSE | O26: =ISNUMBER(D26) -> FALSE | P26: =OR(N26=TRUE,O26=TRUE) -> FALSE
C27: =IF(P27=TRUE,C26+1,) -> 0 | E27: =IF(P27=TRUE,E26+F26,) -> 0 | N27: =ISTEXT(D27) -> FALSE | O27: =ISNUMBER(D27) -> FALSE | P27: =OR(N27=TRUE,O27=TRUE) -> FALSE
C28: =IF(P28=TRUE,C27+1,) -> 0 | E28: =IF(P28=TRUE,E27+F27,) -> 0 | N28: =ISTEXT(D28) -> FALSE | O28: =ISNUMBER(D28) -> FALSE | P28: =OR(N28=TRUE,O28=TRUE) -> FALSE
C29: =IF(P29=TRUE,C28+1,) -> 0 | E29: =IF(P29=TRUE,E28+F28,) -> 0 | N29: =ISTEXT(D29) -> FALSE | O29: =ISNUMBER(D29) -> FALSE | P29: =OR(N29=TRUE,O29=TRUE) -> FALSE
... C100: =IF(P100=TRUE,C99+1,) -> 0 | E100: =IF(P100=TRUE,E99+F99,) -> 0 | N100: =ISTEXT(D100) -> FALSE | O100: =ISNUMBER(D100) -> FALSE | P100: =OR(N100=TRUE,O100=TRUE) -> FALSE

Sheet RTB - Premios y Ganancias Patr.
D2: Diseño de registro de datos fiscales y personales
D3: ='CONTROL DE VERSIONES'!G68 -> IRPF 2025
D4: Premios y ganancias patrimoniales
C5: =IF(P5=TRUE,C4+1,) -> 0
C6: =IF(P6=TRUE,C5+1,) -> 0
C7: Este concepto de datos fiscales incluye los premios y ganancias patrimoniales con origen en el Modelo 190
C9: Nº | D9: Nombre | E9: Posición | F9: Longitud | G9: Descripción
C10: =IF(P10=TRUE,1,) -> 1 | D10: Tipo | E10: =IF(P10=TRUE,1,) -> 1 | F10: 1 | G10: Tipo de registro = '2' | N10: =ISTEXT(D10) -> TRUE | O10: =ISNUMBER(D10) -> FALSE | P10: =OR(N10=TRUE,O10=TRUE) -> TRUE
C11: =IF(P11=TRUE,C10+1,) -> 2 | D11: Código | E11: =IF(P11=TRUE,E10+F10,) -> 2 | F11: 7 | G11: 'RTBnnnn' Donde nnnn es el número del registro de este tipo contenido en el fichero de datos fiscales. | N11: =ISTEXT(D11) -> TRUE | O11: =ISNUMBER(D11) -> FALSE | P11: =OR(N11=TRUE,O11=TRUE) -> TRUE
C12: =IF(P12=TRUE,C11+1,) -> 3 | D12: NIF del pagador | E12: =IF(P12=TRUE,E11+F11,) -> 9 | F12: 9 | N12: =ISTEXT(D12) -> TRUE | O12: =ISNUMBER(D12) -> FALSE | P12: =OR(N12=TRUE,O12=TRUE) -> TRUE
C13: =IF(P13=TRUE,C12+1,) -> 4 | D13: Nombre del pagador | E13: =IF(P13=TRUE,E12+F12,) -> 18 | F13: 40 | N13: =ISTEXT(D13) -> TRUE | O13: =ISNUMBER(D13) -> FALSE | P13: =OR(N13=TRUE,O13=TRUE) -> TRUE
C14: =IF(P14=TRUE,C13+1,) -> 5 | D14: Clave y subclave | E14: =IF(P14=TRUE,E13+F13,) -> 58 | F14: 2 | G14: Clave(1) + Subclave (1) Claves: 'K1' - Premios sin fines publicitarios 'K2' - Aprovechamientos forestales 'K3' - Premios con fines publicitarios con retención 'K4' - Premios sin fines publicitarios sin retención 'K5' - Premios con fines publicitarios sin retención | N14: =ISTEXT(D14) -> TRUE | O14: =ISNUMBER(D14) -> FALSE | P14: =OR(N14=TRUE,O14=TRUE) -> TRUE
C15: =IF(P15=TRUE,C14+1,) -> 6 | D15: Retribución dineraria | E15: =IF(P15=TRUE,E14+F14,) -> 60 | F15: 13 | N15: =ISTEXT(D15) -> TRUE | O15: =ISNUMBER(D15) -> FALSE | P15: =OR(N15=TRUE,O15=TRUE) -> TRUE
C16: =IF(P16=TRUE,C15+1,) -> 7 | D16: Retención | E16: =IF(P16=TRUE,E15+F15,) -> 73 | F16: 13 | N16: =ISTEXT(D16) -> TRUE | O16: =ISNUMBER(D16) -> FALSE | P16: =OR(N16=TRUE,O16=TRUE) -> TRUE
C17: =IF(P17=TRUE,C16+1,) -> 8 | D17: Retribución en especie | E17: =IF(P17=TRUE,E16+F16,) -> 86 | F17: 13 | G17: (Valoración dda. + Ing cat efec. - ing.cta repercutido) Campo calculado de acuerdo a la siguiente fórmula: Retribuciones en Especie = Valoración (de la percepción en especie) declarada en el modelo + Ingresos a cuenta efectuados – Ingresos a cuenta repercutidos. | N17: =ISTEXT(D17) -> TRUE | O17: =ISNUMBER(D17) -> FALSE | P17: =OR(N17=TRUE,O17=TRUE) -> TRUE
C18: =IF(P18=TRUE,C17+1,) -> 9 | D18: Valoracion | E18: =IF(P18=TRUE,E17+F17,) -> 99 | F18: 13 | N18: =ISTEXT(D18) -> TRUE | O18: =ISNUMBER(D18) -> FALSE | P18: =OR(N18=TRUE,O18=TRUE) -> TRUE
C19: =IF(P19=TRUE,C18+1,) -> 10 | D19: Ingreso a cta | E19: =IF(P19=TRUE,E18+F18,) -> 112 | F19: 13 | G19: Ingresos a cuenta efectuados de las percepciones en especie | N19: =ISTEXT(D19) -> TRUE | O19: =ISNUMBER(D19) -> FALSE | P19: =OR(N19=TRUE,O19=TRUE) -> TRUE
C20: =IF(P20=TRUE,C19+1,) -> 11 | D20: Ingreso a cta repercutido | E20: =IF(P20=TRUE,E19+F19,) -> 125 | F20: 13 | G20: Ingresos a cuenta repercutidos de las percepciones en especie | N20: =ISTEXT(D20) -> TRUE | O20: =ISNUMBER(D20) -> FALSE | P20: =OR(N20=TRUE,O20=TRUE) -> TRUE
C21: =IF(P21=TRUE,C20+1,) -> 0 | E21: =IF(P21=TRUE,E20+F20,) -> 0 | N21: =ISTEXT(D21) -> FALSE | O21: =ISNUMBER(D21) -> FALSE | P21: =OR(N21=TRUE,O21=TRUE) -> FALSE
C22: =IF(P22=TRUE,C21+1,) -> 0 | E22: =IF(P22=TRUE,E21+F21,) -> 0 | N22: =ISTEXT(D22) -> FALSE | O22: =ISNUMBER(D22) -> FALSE | P22: =OR(N22=TRUE,O22=TRUE) -> FALSE
C23: =IF(P23=TRUE,C22+1,) -> 0 | E23: =IF(P23=TRUE,E22+F22,) -> 0 | N23: =ISTEXT(D23) -> FALSE | O23: =ISNUMBER(D23) -> FALSE | P23: =OR(N23=TRUE,O23=TRUE) -> FALSE
C24: =IF(P24=TRUE,C23+1,) -> 0 | E24: =IF(P24=TRUE,E23+F23,) -> 0 | N24: =ISTEXT(D24) -> FALSE | O24: =ISNUMBER(D24) -> FALSE | P24: =OR(N24=TRUE,O24=TRUE) -> FALSE
C25: =IF(P25=TRUE,C24+1,) -> 0 | E25: =IF(P25=TRUE,E24+F24,) -> 0 | N25: =ISTEXT(D25) -> FALSE | O25: =ISNUMBER(D25) -> FALSE | P25: =OR(N25=TRUE,O25=TRUE) -> FALSE
C26: =IF(P26=TRUE,C25+1,) -> 0 | E26: =IF(P26=TRUE,E25+F25,) -> 0 | N26: =ISTEXT(D26) -> FALSE | O26: =ISNUMBER(D26) -> FALSE | P26: =OR(N26=TRUE,O26=TRUE) -> FALSE
C27: =IF(P27=TRUE,C26+1,) -> 0 | E27: =IF(P27=TRUE,E26+F26,) -> 0 | N27: =ISTEXT(D27) -> FALSE | O27: =ISNUMBER(D27) -> FALSE | P27: =OR(N27=TRUE,O27=TRUE) -> FALSE
C28: =IF(P28=TRUE,C27+1,) -> 0 | E28: =IF(P28=TRUE,E27+F27,) -> 0 | N28: =ISTEXT(D28) -> FALSE | O28: =ISNUMBER(D28) -> FALSE | P28: =OR(N28=TRUE,O28=TRUE) -> FALSE
C29: =IF(P29=TRUE,C28+1,) -> 0 | E29: =IF(P29=TRUE,E28+F28,) -> 0 | N29: =ISTEXT(D29) -> FALSE | O29: =ISNUMBER(D29) -> FALSE | P29: =OR(N29=TRUE,O29=TRUE) -> FALSE
C30: =IF(P30=TRUE,C29+1,) -> 0 | E30: =IF(P30=TRUE,E29+F29,) -> 0 | N30: =ISTEXT(D30) -> FALSE | O30: =ISNUMBER(D30) -> FALSE | P30: =OR(N30=TRUE,O30=TRUE) -> FALSE
C31: =IF(P31=TRUE,C30+1,) -> 0 | E31: =IF(P31=TRUE,E30+F30,) -> 0 | N31: =ISTEXT(D31) -> FALSE | O31: =ISNUMBER(D31) -> FALSE | P31: =OR(N31=TRUE,O31=TRUE) -> FALSE
C32: =IF(P32=TRUE,C31+1,) -> 0 | E32: =IF(P32=TRUE,E31+F31,) -> 0 | N32: =ISTEXT(D32) -> FALSE | O32: =ISNUMBER(D32) -> FALSE | P32: =OR(N32=TRUE,O32=TRUE) -> FALSE
... C99: =IF(P99=TRUE,C98+1,) -> 0 | E99: =IF(P99=TRUE,E98+F98,) -> 0 | N99: =ISTEXT(D99) -> FALSE | O99: =ISNUMBER(D99) -> FALSE | P99: =OR(N99=TRUE,O99=TRUE) -> FALSE

Sheet RTC - Activid. Econom. Mod.190
D2: Diseño de registro de datos fiscales y personales
D3: ='CONTROL DE VERSIONES'!G68 -> IRPF 2025
D4: Actividades Económicas modelo 190
C5: =IF(P5=TRUE,C4+1,) -> 0
C6: =IF(P6=TRUE,C5+1,) -> 0
C7: Este concepto de datos fiscales incluye los datos de Actividades Económicas con origen en el Modelo 190
C9: Nº | D9: Nombre | E9: Posición | F9: Longitud | G9: Descripción
C10: =IF(P10=TRUE,1,) -> 1 | D10: Tipo | E10: =IF(P10=TRUE,1,) -> 1 | F10: 1 | G10: Tipo de registro = '2' | N10: =ISTEXT(D10) -> TRUE | O10: =ISNUMBER(D10) -> FALSE | P10: =OR(N10=TRUE,O10=TRUE) -> TRUE
C11: =IF(P11=TRUE,C10+1,) -> 2 | D11: Código | E11: =IF(P11=TRUE,E10+F10,) -> 2 | F11: 7 | G11: 'RTCnnnn' Donde nnnn es el número del registro de este tipo contenido en el fichero de datos fiscales. | N11: =ISTEXT(D11) -> TRUE | O11: =ISNUMBER(D11) -> FALSE | P11: =OR(N11=TRUE,O11=TRUE) -> TRUE
C12: =IF(P12=TRUE,C11+1,) -> 3 | D12: NIF del pagador | E12: =IF(P12=TRUE,E11+F11,) -> 9 | F12: 9 | N12: =ISTEXT(D12) -> TRUE | O12: =ISNUMBER(D12) -> FALSE | P12: =OR(N12=TRUE,O12=TRUE) -> TRUE
C13: =IF(P13=TRUE,C12+1,) -> 4 | D13: Nombre del pagador | E13: =IF(P13=TRUE,E12+F12,) -> 18 | F13: 40 | N13: =ISTEXT(D13) -> TRUE | O13: =ISNUMBER(D13) -> FALSE | P13: =OR(N13=TRUE,O13=TRUE) -> TRUE
C14: =IF(P14=TRUE,C13+1,) -> 5 | D14: Clave y subclave | E14: =IF(P14=TRUE,E13+F13,) -> 58 | F14: 2 | G14: Clave(1) + Subclave (1) Claves: 'G1' - Activ. Prof. 'G2' - Activ. Prof. 'G3' - Activ. Prof. 'G4' - Activ. Prof. 'G5' - Activ. Prof. 'G6' - Activ. Prof. 'G7' - Activ. Prof. 'G8' - Activ. Prof. 'H1' - Activ. Agric y empresarial en EO 'H2' - Activ. Agric y empresarial en EO 'H3' - Activ. Agric y empresarial en EO 'H4' - Activ. Agric y empresarial en EO 'I1' - Activ. econ. 'I2' - Activ. econ. 'I3' - Activ. econ. 'J' - Der. Imagen | N14: =ISTEXT(D14) -> TRUE | O14: =ISNUMBER(D14) -> FALSE | P14: =OR(N14=TRUE,O14=TRUE) -> TRUE
C15: =IF(P15=TRUE,C14+1,) -> 6 | D15: Retribución dineraria | E15: =IF(P15=TRUE,E14+F14,) -> 60 | F15: 13 | N15: =ISTEXT(D15) -> TRUE | O15: =ISNUMBER(D15) -> FALSE | P15: =OR(N15=TRUE,O15=TRUE) -> TRUE
C16: =IF(P16=TRUE,C15+1,) -> 7 | D16: Retención | E16: =IF(P16=TRUE,E15+F15,) -> 73 | F16: 13 | N16: =ISTEXT(D16) -> TRUE | O16: =ISNUMBER(D16) -> FALSE | P16: =OR(N16=TRUE,O16=TRUE) -> TRUE
C17: =IF(P17=TRUE,C16+1,) -> 8 | D17: Retribución en especie | E17: =IF(P17=TRUE,E16+F16,) -> 86 | F17: 13 | G17: (Valoración dda. + Ing cat efec. - ing.cta repercutido) Campo calculado de acuerdo a la siguiente fórmula: Retribuciones en Especie = Valoración (de la percepción en especie) declarada en el modelo + Ingresos a cuenta efectuados – Ingresos a cuenta repercutidos. | N17: =ISTEXT(D17) -> TRUE | O17: =ISNUMBER(D17) -> FALSE | P17: =OR(N17=TRUE,O17=TRUE) -> TRUE
C18: =IF(P18=TRUE,C17+1,) -> 9 | D18: Valoracion | E18: =IF(P18=TRUE,E17+F17,) -> 99 | F18: 13 | N18: =ISTEXT(D18) -> TRUE | O18: =ISNUMBER(D18) -> FALSE | P18: =OR(N18=TRUE,O18=TRUE) -> TRUE
C19: =IF(P19=TRUE,C18+1,) -> 10 | D19: Ingreso a cta | E19: =IF(P19=TRUE,E18+F18,) -> 112 | F19: 13 | G19: Ingresos a cuenta efectuados de las percepciones en especie | N19: =ISTEXT(D19) -> TRUE | O19: =ISNUMBER(D19) -> FALSE | P19: =OR(N19=TRUE,O19=TRUE) -> TRUE
C20: =IF(P20=TRUE,C19+1,) -> 11 | D20: Ingreso a cta repercutido | E20: =IF(P20=TRUE,E19+F19,) -> 125 | F20: 13 | G20: Ingresos a cuenta repercutidos de las percepciones en especie | N20: =ISTEXT(D20) -> TRUE | O20: =ISNUMBER(D20) -> FALSE | P20: =OR(N20=TRUE,O20=TRUE) -> TRUE
C21: =IF(P21=TRUE,C20+1,) -> 12 | D21: Reducciones aplicables | E21: =IF(P21=TRUE,E20+F20,) -> 138 | F21: 13 | N21: =ISTEXT(D21) -> TRUE | O21: =ISNUMBER(D21) -> FALSE | P21: =OR(N21=TRUE,O21=TRUE) -> TRUE
C22: =IF(P22=TRUE,C21+1,) -> 0 | E22: =IF(P22=TRUE,E21+F21,) -> 0 | N22: =ISTEXT(D22) -> FALSE | O22: =ISNUMBER(D22) -> FALSE | P22: =OR(N22=TRUE,O22=TRUE) -> FALSE
C23: =IF(P23=TRUE,C22+1,) -> 0 | E23: =IF(P23=TRUE,E22+F22,) -> 0 | N23: =ISTEXT(D23) -> FALSE | O23: =ISNUMBER(D23) -> FALSE | P23: =OR(N23=TRUE,O23=TRUE) -> FALSE
C24: =IF(P24=TRUE,C23+1,) -> 0 | E24: =IF(P24=TRUE,E23+F23,) -> 0 | N24: =ISTEXT(D24) -> FALSE | O24: =ISNUMBER(D24) -> FALSE | P24: =OR(N24=TRUE,O24=TRUE) -> FALSE
C25: =IF(P25=TRUE,C24+1,) -> 0 | E25: =IF(P25=TRUE,E24+F24,) -> 0 | N25: =ISTEXT(D25) -> FALSE | O25: =ISNUMBER(D25) -> FALSE | P25: =OR(N25=TRUE,O25=TRUE) -> FALSE
C26: =IF(P26=TRUE,C25+1,) -> 0 | E26: =IF(P26=TRUE,E25+F25,) -> 0 | N26: =ISTEXT(D26) -> FALSE | O26: =ISNUMBER(D26) -> FALSE | P26: =OR(N26=TRUE,O26=TRUE) -> FALSE
C27: =IF(P27=TRUE,C26+1,) -> 0 | E27: =IF(P27=TRUE,E26+F26,) -> 0 | N27: =ISTEXT(D27) -> FALSE | O27: =ISNUMBER(D27) -> FALSE | P27: =OR(N27=TRUE,O27=TRUE) -> FALSE
C28: =IF(P28=TRUE,C27+1,) -> 0 | E28: =IF(P28=TRUE,E27+F27,) -> 0 | N28: =ISTEXT(D28) -> FALSE | O28: =ISNUMBER(D28) -> FALSE | P28: =OR(N28=TRUE,O28=TRUE) -> FALSE
C29: =IF(P29=TRUE,C28+1,) -> 0 | E29: =IF(P29=TRUE,E28+F28,) -> 0 | N29: =ISTEXT(D29) -> FALSE | O29: =ISNUMBER(D29) -> FALSE | P29: =OR(N29=TRUE,O29=TRUE) -> FALSE
C30: =IF(P30=TRUE,C29+1,) -> 0 | E30: =IF(P30=TRUE,E29+F29,) -> 0 | N30: =ISTEXT(D30) -> FALSE | O30: =ISNUMBER(D30) -> FALSE | P30: =OR(N30=TRUE,O30=TRUE) -> FALSE
C31: =IF(P31=TRUE,C30+1,) -> 0 | E31: =IF(P31=TRUE,E30+F30,) -> 0 | N31: =ISTEXT(D31) -> FALSE | O31: =ISNUMBER(D31) -> FALSE | P31: =OR(N31=TRUE,O31=TRUE) -> FALSE
C32: =IF(P32=TRUE,C31+1,) -> 0 | E32: =IF(P32=TRUE,E31+F31,) -> 0 | N32: =ISTEXT(D32) -> FALSE | O32: =ISNUMBER(D32) -> FALSE | P32: =OR(N32=TRUE,O32=TRUE) -> FALSE
C33: =IF(P33=TRUE,C32+1,) -> 0 | E33: =IF(P33=TRUE,E32+F32,) -> 0 | N33: =ISTEXT(D33) -> FALSE | O33: =ISNUMBER(D33) -> FALSE | P33: =OR(N33=TRUE,O33=TRUE) -> FALSE
... C99: =IF(P99=TRUE,C98+1,) -> 0 | E99: =IF(P99=TRUE,E98+F98,) -> 0 | N99: =ISTEXT(D99) -> FALSE | O99: =ISNUMBER(D99) -> FALSE | P99: =OR(N99=TRUE,O99=TRUE) -> FALSE

Sheet AA - Devengo ant. al ejercicio
D2: Diseño de registro de datos fiscales y personales
D3: ='CONTROL DE VERSIONES'!G68 -> IRPF 2025
D4: Rdtos. del trabajo, Act. Económicas, Premios, Ganancias Patrimoniales e Imputaciones de Renta, con ejercicio de devengo anterior a 2025
C5: =IF(P5=TRUE,C4+1,) -> 0
C6: =IF(P6=TRUE,C5+1,) -> 0
C7: Información procedente del modelo de declaración informativa 190: “Retenciones e ingresos a cuenta del Impuesto sobre la Renta de las Personas Físicas. Rendimientos del trabajo y de actividades económicas, premios y determinadas ganancias patrimoniales e imputaciones de renta. Resumen anual”. Con ejercicio de devengo anterior a 2025.
C9: Nº | D9: Nombre | E9: Posición | F9: Longitud | G9: Descripción
C10: =IF(P10=TRUE,1,) -> 1 | D10: Tipo | E10: =IF(P10=TRUE,1,) -> 1 | F10: 1 | G10: Tipo de registro = '2' | N10: =ISTEXT(D10) -> TRUE | O10: =ISNUMBER(D10) -> FALSE | P10: =OR(N10=TRUE,O10=TRUE) -> TRUE
C11: =IF(P11=TRUE,C10+1,) -> 2 | D11: Código | E11: =IF(P11=TRUE,E10+F10,) -> 2 | F11: 7 | G11: 'AAnnnnn' Donde nnnn es el número del registro de este tipo contenido en el fichero de datos fiscales. | N11: =ISTEXT(D11) -> TRUE | O11: =ISNUMBER(D11) -> FALSE | P11: =OR(N11=TRUE,O11=TRUE) -> TRUE
C12: =IF(P12=TRUE,C11+1,) -> 3 | D12: NIF del Pagador | E12: =IF(P12=TRUE,E11+F11,) -> 9 | F12: 9 | N12: =ISTEXT(D12) -> TRUE | O12: =ISNUMBER(D12) -> FALSE | P12: =OR(N12=TRUE,O12=TRUE) -> TRUE
C13: =IF(P13=TRUE,C12+1,) -> 4 | D13: Nombre del Pagador | E13: =IF(P13=TRUE,E12+F12,) -> 18 | F13: 40 | N13: =ISTEXT(D13) -> TRUE | O13: =ISNUMBER(D13) -> FALSE | P13: =OR(N13=TRUE,O13=TRUE) -> TRUE
C14: =IF(P14=TRUE,C13+1,) -> 5 | D14: Ejercicio del devengo | E14: =IF(P14=TRUE,E13+F13,) -> 58 | F14: 4 | N14: =ISTEXT(D14) -> TRUE | O14: =ISNUMBER(D14) -> FALSE | P14: =OR(N14=TRUE,O14=TRUE) -> TRUE
C15: =IF(P15=TRUE,C14+1,) -> 6 | D15: Clave | E15: =IF(P15=TRUE,E14+F14,) -> 62 | F15: 3 | G15: Clave (1) + Sub clave (2) Claves: ‘A‘ - Empleado ‘B2‘ - Prestación ‘B*‘ - Pensionista ‘C‘ - Desempleado ‘D‘ - Desemp. P. U. ‘E*‘ - Consejero ‘F*‘ - Cursos,conf. ‘G*‘ - Activ. prof. ‘H*‘ - Activ. Agric. y empresariales en EO ‘I*‘ - Activ. econ. ‘J‘ - Der. De imagen ‘K1‘ - Premios ‘K2‘ - Aprovechamientos forestales ‘K3‘ - Premios ‘L05‘ - Indemnizaciones ‘L10’ - Becas ‘L25’ - Ayuda empresas para guarderías ‘L26’ - Ayuda guarderías a sus empleados ‘L27’ - Prestaciones maternidad | N15: =ISTEXT(D15) -> TRUE | O15: =ISNUMBER(D15) -> FALSE | P15: =OR(N15=TRUE,O15=TRUE) -> TRUE
C16: =IF(P16=TRUE,C15+1,) -> 7 | D16: Retribuciones Dineraria | E16: =IF(P16=TRUE,E15+F15,) -> 65 | F16: 13 | N16: =ISTEXT(D16) -> TRUE | O16: =ISNUMBER(D16) -> FALSE | P16: =OR(N16=TRUE,O16=TRUE) -> TRUE
C17: =IF(P17=TRUE,C16+1,) -> 8 | D17: Retención | E17: =IF(P17=TRUE,E16+F16,) -> 78 | F17: 13 | N17: =ISTEXT(D17) -> TRUE | O17: =ISNUMBER(D17) -> FALSE | P17: =OR(N17=TRUE,O17=TRUE) -> TRUE
C18: =IF(P18=TRUE,C17+1,) -> 9 | D18: Retribución en especie | E18: =IF(P18=TRUE,E17+F17,) -> 91 | F18: 13 | G18: (Valoración dda. + ing.cta efec. – ing.cta repercutido) | N18: =ISTEXT(D18) -> TRUE | O18: =ISNUMBER(D18) -> FALSE | P18: =OR(N18=TRUE,O18=TRUE) -> TRUE
C19: =IF(P19=TRUE,C18+1,) -> 10 | D19: Valoración | E19: =IF(P19=TRUE,E18+F18,) -> 104 | F19: 13 | N19: =ISTEXT(D19) -> TRUE | O19: =ISNUMBER(D19) -> FALSE | P19: =OR(N19=TRUE,O19=TRUE) -> TRUE
C20: =IF(P20=TRUE,C19+1,) -> 11 | D20: Ingresos a cuenta | E20: =IF(P20=TRUE,E19+F19,) -> 117 | F20: 13 | N20: =ISTEXT(D20) -> TRUE | O20: =ISNUMBER(D20) -> FALSE | P20: =OR(N20=TRUE,O20=TRUE) -> TRUE
C21: =IF(P21=TRUE,C20+1,) -> 12 | D21: Ingresos a cuenta repercutido | E21: =IF(P21=TRUE,E20+F20,) -> 130 | F21: 13 | N21: =ISTEXT(D21) -> TRUE | O21: =ISNUMBER(D21) -> FALSE | P21: =OR(N21=TRUE,O21=TRUE) -> TRUE
C22: =IF(P22=TRUE,C21+1,) -> 13 | D22: Gastos deducibles | E22: =IF(P22=TRUE,E21+F21,) -> 143 | F22: 13 | N22: =ISTEXT(D22) -> TRUE | O22: =ISNUMBER(D22) -> FALSE | P22: =OR(N22=TRUE,O22=TRUE) -> TRUE
C23: =IF(P23=TRUE,C22+1,) -> 14 | D23: Reducciones | E23: =IF(P23=TRUE,E22+F22,) -> 156 | F23: 13 | N23: =ISTEXT(D23) -> TRUE | O23: =ISNUMBER(D23) -> FALSE | P23: =OR(N23=TRUE,O23=TRUE) -> TRUE
C24: =IF(P24=TRUE,C23+1,) -> 15 | D24: Retribuciones Dineraria Incapacidad Laboral | E24: =IF(P24=TRUE,E23+F23,) -> 169 | F24: 13 | N24: =ISTEXT(D24) -> TRUE | O24: =ISNUMBER(D24) -> FALSE | P24: =OR(N24=TRUE,O24=TRUE) -> TRUE
C25: =IF(P25=TRUE,C24+1,) -> 16 | D25: Retención Incapacidad Laboral | E25: =IF(P25=TRUE,E24+F24,) -> 182 | F25: 13 | N25: =ISTEXT(D25) -> TRUE | O25: =ISNUMBER(D25) -> FALSE | P25: =OR(N25=TRUE,O25=TRUE) -> TRUE
C26: =IF(P26=TRUE,C25+1,) -> 17 | D26: Retribución en Especie Incapacidad Laboral | E26: =IF(P26=TRUE,E25+F25,) -> 195 | F26: 13 | G26: (Valoración dda. IL. + ing.cta efec.IL – ing.cta repercutido IL) | N26: =ISTEXT(D26) -> TRUE | O26: =ISNUMBER(D26) -> FALSE | P26: =OR(N26=TRUE,O26=TRUE) -> TRUE
C27: =IF(P27=TRUE,C26+1,) -> 18 | D27: Valoración Incapacidad Laboral | E27: =IF(P27=TRUE,E26+F26,) -> 208 | F27: 13 | N27: =ISTEXT(D27) -> TRUE | O27: =ISNUMBER(D27) -> FALSE | P27: =OR(N27=TRUE,O27=TRUE) -> TRUE
C28: =IF(P28=TRUE,C27+1,) -> 19 | D28: Ingresos a cuenta Incapacidad Laboral | E28: =IF(P28=TRUE,E27+F27,) -> 221 | F28: 13 | N28: =ISTEXT(D28) -> TRUE | O28: =ISNUMBER(D28) -> FALSE | P28: =OR(N28=TRUE,O28=TRUE) -> TRUE
C29: =IF(P29=TRUE,C28+1,) -> 20 | D29: Ingresos a cuenta repercutido Incapacidad Laboral | E29: =IF(P29=TRUE,E28+F28,) -> 234 | F29: 13 | N29: =ISTEXT(D29) -> TRUE | O29: =ISNUMBER(D29) -> FALSE | P29: =OR(N29=TRUE,O29=TRUE) -> TRUE
C30: =IF(P30=TRUE,C29+1,) -> 0 | E30: =IF(P30=TRUE,E29+F29,) -> 0 | N30: =ISTEXT(D30) -> FALSE | O30: =ISNUMBER(D30) -> FALSE | P30: =OR(N30=TRUE,O30=TRUE) -> FALSE
C31: =IF(P31=TRUE,C30+1,) -> 0 | E31: =IF(P31=TRUE,E30+F30,) -> 0 | N31: =ISTEXT(D31) -> FALSE | O31: =ISNUMBER(D31) -> FALSE | P31: =OR(N31=TRUE,O31=TRUE) -> FALSE
C32: =IF(P32=TRUE,C31+1,) -> 0 | E32: =IF(P32=TRUE,E31+F31,) -> 0 | N32: =ISTEXT(D32) -> FALSE | O32: =ISNUMBER(D32) -> FALSE | P32: =OR(N32=TRUE,O32=TRUE) -> FALSE
C33: =IF(P33=TRUE,C32+1,) -> 0 | E33: =IF(P33=TRUE,E32+F32,) -> 0 | N33: =ISTEXT(D33) -> FALSE | O33: =ISNUMBER(D33) -> FALSE | P33: =OR(N33=TRUE,O33=TRUE) -> FALSE
C34: =IF(P34=TRUE,C33+1,) -> 0 | E34: =IF(P34=TRUE,E33+F33,) -> 0 | N34: =ISTEXT(D34) -> FALSE | O34: =ISNUMBER(D34) -> FALSE | P34: =OR(N34=TRUE,O34=TRUE) -> FALSE
C35: =IF(P35=TRUE,C34+1,) -> 0 | E35: =IF(P35=TRUE,E34+F34,) -> 0 | N35: =ISTEXT(D35) -> FALSE | O35: =ISNUMBER(D35) -> FALSE | P35: =OR(N35=TRUE,O35=TRUE) -> FALSE
C36: =IF(P36=TRUE,C35+1,) -> 0 | E36: =IF(P36=TRUE,E35+F35,) -> 0 | N36: =ISTEXT(D36) -> FALSE | O36: =ISNUMBER(D36) -> FALSE | P36: =OR(N36=TRUE,O36=TRUE) -> FALSE
C37: =IF(P37=TRUE,C36+1,) -> 0 | E37: =IF(P37=TRUE,E36+F36,) -> 0 | N37: =ISTEXT(D37) -> FALSE | O37: =ISNUMBER(D37) -> FALSE | P37: =OR(N37=TRUE,O37=TRUE) -> FALSE
C38: =IF(P38=TRUE,C37+1,) -> 0 | E38: =IF(P38=TRUE,E37+F37,) -> 0 | N38: =ISTEXT(D38) -> FALSE | O38: =ISNUMBER(D38) -> FALSE | P38: =OR(N38=TRUE,O38=TRUE) -> FALSE
C39: =IF(P39=TRUE,C38+1,) -> 0 | E39: =IF(P39=TRUE,E38+F38,) -> 0 | N39: =ISTEXT(D39) -> FALSE | O39: =ISNUMBER(D39) -> FALSE | P39: =OR(N39=TRUE,O39=TRUE) -> FALSE
C40: =IF(P40=TRUE,C39+1,) -> 0 | E40: =IF(P40=TRUE,E39+F39,) -> 0 | N40: =ISTEXT(D40) -> FALSE | O40: =ISNUMBER(D40) -> FALSE | P40: =OR(N40=TRUE,O40=TRUE) -> FALSE
C41: =IF(P41=TRUE,C40+1,) -> 0 | E41: =IF(P41=TRUE,E40+F40,) -> 0 | N41: =ISTEXT(D41) -> FALSE | O41: =ISNUMBER(D41) -> FALSE | P41: =OR(N41=TRUE,O41=TRUE) -> FALSE
... C99: =IF(P99=TRUE,C98+1,) -> 0 | E99: =IF(P99=TRUE,E98+F98,) -> 0 | N99: =ISTEXT(D99) -> FALSE | O99: =ISNUMBER(D99) -> FALSE | P99: =OR(N99=TRUE,O99=TRUE) -> FALSE

Sheet PP - Planes de Pensiones
D2: Diseño de registro de datos fiscales y personales
D3: ='CONTROL DE VERSIONES'!G68 -> IRPF 2025
D4: Planes de Pensiones
C5: =IF(P5=TRUE,C4+1,) -> 0
C6: =IF(P6=TRUE,C5+1,) -> 0
C7: Este concepto de datos fiscales incluye los datos por Planes de Pensiones con origen en el Modelo 345
C9: Nº | D9: Nombre | E9: Posición | F9: Longitud | G9: Descripción
C10: =IF(P10=TRUE,1,) -> 1 | D10: Tipo | E10: =IF(P10=TRUE,1,) -> 1 | F10: 1 | G10: Tipo de registro = '2' | N10: =ISTEXT(D10) -> TRUE | O10: =ISNUMBER(D10) -> FALSE | P10: =OR(N10=TRUE,O10=TRUE) -> TRUE
C11: =IF(P11=TRUE,C10+1,) -> 2 | D11: Código | E11: =IF(P11=TRUE,E10+F10,) -> 2 | F11: 7 | G11: 'PPnnnnn' Donde nnnn es el número del registro de este tipo contenido en el fichero de datos fiscales. | N11: =ISTEXT(D11) -> TRUE | O11: =ISNUMBER(D11) -> FALSE | P11: =OR(N11=TRUE,O11=TRUE) -> TRUE
C12: =IF(P12=TRUE,C11+1,) -> 3 | D12: NIF del Gestor/Promotor | E12: =IF(P12=TRUE,E11+F11,) -> 9 | F12: 9 | N12: =ISTEXT(D12) -> TRUE | O12: =ISNUMBER(D12) -> FALSE | P12: =OR(N12=TRUE,O12=TRUE) -> TRUE
C13: =IF(P13=TRUE,C12+1,) -> 4 | D13: Nombre del Gestor/Promotor | E13: =IF(P13=TRUE,E12+F12,) -> 18 | F13: 40 | N13: =ISTEXT(D13) -> TRUE | O13: =ISNUMBER(D13) -> FALSE | P13: =OR(N13=TRUE,O13=TRUE) -> TRUE
C14: =IF(P14=TRUE,C13+1,) -> 5 | D14: Clave | E14: =IF(P14=TRUE,E13+F13,) -> 58 | F14: 1 | G14: Claves: 'A' - Aportaciones de los partícipes 'C' - Contrib. deduc. del promotor 'E' - Profesionales o empresarios 'F' - Trabajad. por cuenta ajena o socios trabajadores 'G' - Cobertura de contigencias 'H' - Primas satisfechas a planes de previsión asegurados 'J' - Primas a planes de previsión social empresarial 'K' - Primas a seguros privados de dependencia 'L' - Primas a seguros colectivos dependencia 'M' - Aportaciones a productos paneuropeos de pensiones indiv. (PEPP) | N14: =ISTEXT(D14) -> TRUE | O14: =ISNUMBER(D14) -> FALSE | P14: =OR(N14=TRUE,O14=TRUE) -> TRUE
C15: =IF(P15=TRUE,C14+1,) -> 6 | D15: Subclave | E15: =IF(P15=TRUE,E14+F14,) -> 59 | F15: 2 | G15: Subclave: '00’; excepto en los siguientes casos: ‘01’ – para la clave A, aportaciones de los partícipes ‘02’ – para la clave A, aportaciones de los trabajadores ‘03’ – para la clave A, aportaciones de los trabajadores ‘01’ – para la clave C, contribuciones de los promotores. ‘02’ – para la clave C, aportaciones del empresario/profesional ‘03’ – para la clave C, aportaciones decisión del trabajador ‘01’ – para la clave E, aportaciones del empresario ‘02’ – para la clave E, profesionales o empresarios ‘01’ – para la clave F, cobertura de contingencias ‘02’ – para la clave F, aportaciones de los trabajadores ‘01’ – para la clave G, contribuciones del promotor ‘02’ – para la clave G, aportaciones decisión del trabajador ‘01’ – para la clave J, aportaciones de los asegurados ‘02’ – para la clave J, aportaciones decisión del trabajador ‘03’ – para la clave J, contribuciones de los tomadores. ’04’ – para la clave J, aportaciones del empresario/profesional ‘01’ – para la clave L, primas satisfechas por la empresa ‘02’ – para la clave L, aportaciones del empresario/profesional ‘03’ – para la clave L, primas decisión del trabajador | N15: =ISTEXT(D15) -> TRUE | O15: =ISNUMBER(D15) -> FALSE | P15: =OR(N15=TRUE,O15=TRUE) -> TRUE
C16: =IF(P16=TRUE,C15+1,) -> 7 | D16: Aportación | E16: =IF(P16=TRUE,E15+F15,) -> 61 | F16: 13 | G16: Este importe aparecerá siempre (Aportación del empleado) | N16: =ISTEXT(D16) -> TRUE | O16: =ISNUMBER(D16) -> FALSE | P16: =OR(N16=TRUE,O16=TRUE) -> TRUE
C17: =IF(P17=TRUE,C16+1,) -> 8 | D17: Aport. | E17: =IF(P17=TRUE,E16+F16,) -> 74 | F17: 13 | G17: Coincide con el anterior, sólo aparecerá para las claves y subclaves: C01, G01, J03, L01 y C03, G02, J02 y L03 | N17: =ISTEXT(D17) -> TRUE | O17: =ISNUMBER(D17) -> FALSE | P17: =OR(N17=TRUE,O17=TRUE) -> TRUE
C18: =IF(P18=TRUE,C17+1,) -> 9 | D18: NIF persona con discapacidad | E18: =IF(P18=TRUE,E17+F17,) -> 87 | F18: 9 | N18: =ISTEXT(D18) -> TRUE | O18: =ISNUMBER(D18) -> FALSE | P18: =OR(N18=TRUE,O18=TRUE) -> TRUE
C19: =IF(P19=TRUE,C18+1,) -> 10 | D19: Rendimientos íntegros del trabajo | E19: =IF(P19=TRUE,E18+F18,) -> 96 | F19: 1 | G19: Superiores a 60.000 euros Valores.: 'S' o 'N' | N19: =ISTEXT(D19) -> TRUE | O19: =ISNUMBER(D19) -> FALSE | P19: =OR(N19=TRUE,O19=TRUE) -> TRUE
C20: =IF(P20=TRUE,C19+1,) -> 11 | D20: NIF empleador | E20: =IF(P20=TRUE,E19+F19,) -> 97 | F20: 9 | G20: Promotor o tomador del sistema de previsión social | N20: =ISTEXT(D20) -> TRUE | O20: =ISNUMBER(D20) -> FALSE | P20: =OR(N20=TRUE,O20=TRUE) -> TRUE
C21: =IF(P21=TRUE,C20+1,) -> 12 | D21: Apellidos y nombre del empleador | E21: =IF(P21=TRUE,E20+F20,) -> 106 | F21: 40 | G21: Promotor o tomador del sistema de previsión social | N21: =ISTEXT(D21) -> TRUE | O21: =ISNUMBER(D21) -> FALSE | P21: =OR(N21=TRUE,O21=TRUE) -> TRUE
C22: =IF(P22=TRUE,C21+1,) -> 13 | D22: RTP > 60.000 € | E22: =IF(P22=TRUE,E21+F21,) -> 146 | F22: 1 | G22: RTP > 60.000 € (calculado) Valores.: 'S' o 'N' | N22: =ISTEXT(D22) -> TRUE | O22: =ISNUMBER(D22) -> FALSE | P22: =OR(N22=TRUE,O22=TRUE) -> TRUE
C23: =IF(P23=TRUE,C22+1,) -> 0 | E23: =IF(P23=TRUE,E22+F22,) -> 0 | N23: =ISTEXT(D23) -> FALSE | O23: =ISNUMBER(D23) -> FALSE | P23: =OR(N23=TRUE,O23=TRUE) -> FALSE
C24: =IF(P24=TRUE,C23+1,) -> 0 | E24: =IF(P24=TRUE,E23+F23,) -> 0 | N24: =ISTEXT(D24) -> FALSE | O24: =ISNUMBER(D24) -> FALSE | P24: =OR(N24=TRUE,O24=TRUE) -> FALSE
C25: =IF(P25=TRUE,C24+1,) -> 0 | E25: =IF(P25=TRUE,E24+F24,) -> 0 | N25: =ISTEXT(D25) -> FALSE | O25: =ISNUMBER(D25) -> FALSE | P25: =OR(N25=TRUE,O25=TRUE) -> FALSE
C26: =IF(P26=TRUE,C25+1,) -> 0 | E26: =IF(P26=TRUE,E25+F25,) -> 0 | N26: =ISTEXT(D26) -> FALSE | O26: =ISNUMBER(D26) -> FALSE | P26: =OR(N26=TRUE,O26=TRUE) -> FALSE
C27: =IF(P27=TRUE,C26+1,) -> 0 | E27: =IF(P27=TRUE,E26+F26,) -> 0 | N27: =ISTEXT(D27) -> FALSE | O27: =ISNUMBER(D27) -> FALSE | P27: =OR(N27=TRUE,O27=TRUE) -> FALSE
C28: =IF(P28=TRUE,C27+1,) -> 0 | E28: =IF(P28=TRUE,E27+F27,) -> 0 | N28: =ISTEXT(D28) -> FALSE | O28: =ISNUMBER(D28) -> FALSE | P28: =OR(N28=TRUE,O28=TRUE) -> FALSE
C29: =IF(P29=TRUE,C28+1,) -> 0 | E29: =IF(P29=TRUE,E28+F28,) -> 0 | N29: =ISTEXT(D29) -> FALSE | O29: =ISNUMBER(D29) -> FALSE | P29: =OR(N29=TRUE,O29=TRUE) -> FALSE
C30: =IF(P30=TRUE,C29+1,) -> 0 | E30: =IF(P30=TRUE,E29+F29,) -> 0 | N30: =ISTEXT(D30) -> FALSE | O30: =ISNUMBER(D30) -> FALSE | P30: =OR(N30=TRUE,O30=TRUE) -> FALSE
C31: =IF(P31=TRUE,C30+1,) -> 0 | E31: =IF(P31=TRUE,E30+F30,) -> 0 | N31: =ISTEXT(D31) -> FALSE | O31: =ISNUMBER(D31) -> FALSE | P31: =OR(N31=TRUE,O31=TRUE) -> FALSE
C32: =IF(P32=TRUE,C31+1,) -> 0 | E32: =IF(P32=TRUE,E31+F31,) -> 0 | N32: =ISTEXT(D32) -> FALSE | O32: =ISNUMBER(D32) -> FALSE | P32: =OR(N32=TRUE,O32=TRUE) -> FALSE
C33: =IF(P33=TRUE,C32+1,) -> 0 | E33: =IF(P33=TRUE,E32+F32,) -> 0 | N33: =ISTEXT(D33) -> FALSE | O33: =ISNUMBER(D33) -> FALSE | P33: =OR(N33=TRUE,O33=TRUE) -> FALSE
C34: =IF(P34=TRUE,C33+1,) -> 0 | E34: =IF(P34=TRUE,E33+F33,) -> 0 | N34: =ISTEXT(D34) -> FALSE | O34: =ISNUMBER(D34) -> FALSE | P34: =OR(N34=TRUE,O34=TRUE) -> FALSE
... C99: =IF(P99=TRUE,C98+1,) -> 0 | E99: =IF(P99=TRUE,E98+F98,) -> 0 | N99: =ISTEXT(D99) -> FALSE | O99: =ISNUMBER(D99) -> FALSE | P99: =OR(N99=TRUE,O99=TRUE) -> FALSE

Sheet CB - Rdto. cuentas bancarias
D2: Diseño de registro de datos fiscales y personales
D3: ='CONTROL DE VERSIONES'!G68 -> IRPF 2025
D4: Rendimientos de cuentas bancarias
C5: =IF(P5=TRUE,C4+1,) -> 0
C6: =IF(P6=TRUE,C5+1,) -> 0
C7: Este concepto de datos fiscales incluye los datos de los rendimientos por cuentas bancarias con origen en el Modelo 196
C9: Nº | D9: Nombre | E9: Posición | F9: Longitud | G9: Descripción
C10: =IF(P10=TRUE,1,) -> 1 | D10: Tipo | E10: =IF(P10=TRUE,1,) -> 1 | F10: 1 | G10: Tipo de registro = '2' | N10: =ISTEXT(D10) -> TRUE | O10: =ISNUMBER(D10) -> FALSE | P10: =OR(N10=TRUE,O10=TRUE) -> TRUE
C11: =IF(P11=TRUE,C10+1,) -> 2 | D11: Código | E11: =IF(P11=TRUE,E10+F10,) -> 2 | F11: 7 | G11: 'CBnnnnn' Donde nnnn es el número del registro de este tipo contenido en el fichero de datos fiscales. | N11: =ISTEXT(D11) -> TRUE | O11: =ISNUMBER(D11) -> FALSE | P11: =OR(N11=TRUE,O11=TRUE) -> TRUE
C12: =IF(P12=TRUE,C11+1,) -> 3 | D12: NIF del Pagador | E12: =IF(P12=TRUE,E11+F11,) -> 9 | F12: 9 | N12: =ISTEXT(D12) -> TRUE | O12: =ISNUMBER(D12) -> FALSE | P12: =OR(N12=TRUE,O12=TRUE) -> TRUE
C13: =IF(P13=TRUE,C12+1,) -> 4 | D13: Nombre del Pagador | E13: =IF(P13=TRUE,E12+F12,) -> 18 | F13: 40 | G13: Nombre de la Entidad | N13: =ISTEXT(D13) -> TRUE | O13: =ISNUMBER(D13) -> FALSE | P13: =OR(N13=TRUE,O13=TRUE) -> TRUE
C14: =IF(P14=TRUE,C13+1,) -> 5 | D14: Cuenta | E14: =IF(P14=TRUE,E13+F13,) -> 58 | F14: 10 | G14: Últimos 10 dígitos del Código de Cuenta Cliente (CCC) | N14: =ISTEXT(D14) -> TRUE | O14: =ISNUMBER(D14) -> FALSE | P14: =OR(N14=TRUE,O14=TRUE) -> TRUE
C15: =IF(P15=TRUE,C14+1,) -> 6 | D15: Tipo | E15: =IF(P15=TRUE,E14+F14,) -> 68 | F15: 1 | G15: Tipos: '1’ - Cuenta corriente ‘2‘ - Cuenta ahorro ‘3‘ - Impos. A plazo ‘4‘ - Cuenta financ. ‘5‘ - Cuenta crédito ‘6’ - Contr. Financ. Atip | N15: =ISTEXT(D15) -> TRUE | O15: =ISNUMBER(D15) -> FALSE | P15: =OR(N15=TRUE,O15=TRUE) -> TRUE
C16: =IF(P16=TRUE,C15+1,) -> 7 | D16: Número de titulares | E16: =IF(P16=TRUE,E15+F15,) -> 69 | F16: 3 | N16: =ISTEXT(D16) -> TRUE | O16: =ISNUMBER(D16) -> FALSE | P16: =OR(N16=TRUE,O16=TRUE) -> TRUE
C17: =IF(P17=TRUE,C16+1,) -> 8 | D17: Rendimientos dinerarios | E17: =IF(P17=TRUE,E16+F16,) -> 72 | F17: 13 | N17: =ISTEXT(D17) -> TRUE | O17: =ISNUMBER(D17) -> FALSE | P17: =OR(N17=TRUE,O17=TRUE) -> TRUE
C18: =IF(P18=TRUE,C17+1,) -> 9 | D18: Retenciones | E18: =IF(P18=TRUE,E17+F17,) -> 85 | F18: 13 | N18: =ISTEXT(D18) -> TRUE | O18: =ISNUMBER(D18) -> FALSE | P18: =OR(N18=TRUE,O18=TRUE) -> TRUE
C19: =IF(P19=TRUE,C18+1,) -> 10 | D19: Rend. Especie | E19: =IF(P19=TRUE,E18+F18,) -> 98 | F19: 13 | G19: Retribución declarada | N19: =ISTEXT(D19) -> TRUE | O19: =ISNUMBER(D19) -> FALSE | P19: =OR(N19=TRUE,O19=TRUE) -> TRUE
C20: =IF(P20=TRUE,C19+1,) -> 11 | D20: Ingreso a Cta. | E20: =IF(P20=TRUE,E19+F19,) -> 111 | F20: 13 | G20: Ingresos a cuenta efectuados de las percepciones en especie | N20: =ISTEXT(D20) -> TRUE | O20: =ISNUMBER(D20) -> FALSE | P20: =OR(N20=TRUE,O20=TRUE) -> TRUE
C21: =IF(P21=TRUE,C20+1,) -> 0 | E21: =IF(P21=TRUE,E20+F20,) -> 0 | N21: =ISTEXT(D21) -> FALSE | O21: =ISNUMBER(D21) -> FALSE | P21: =OR(N21=TRUE,O21=TRUE) -> FALSE
C22: =IF(P22=TRUE,C21+1,) -> 0 | E22: =IF(P22=TRUE,E21+F21,) -> 0 | N22: =ISTEXT(D22) -> FALSE | O22: =ISNUMBER(D22) -> FALSE | P22: =OR(N22=TRUE,O22=TRUE) -> FALSE
C23: =IF(P23=TRUE,C22+1,) -> 0 | E23: =IF(P23=TRUE,E22+F22,) -> 0 | N23: =ISTEXT(D23) -> FALSE | O23: =ISNUMBER(D23) -> FALSE | P23: =OR(N23=TRUE,O23=TRUE) -> FALSE
C24: =IF(P24=TRUE,C23+1,) -> 0 | E24: =IF(P24=TRUE,E23+F23,) -> 0 | N24: =ISTEXT(D24) -> FALSE | O24: =ISNUMBER(D24) -> FALSE | P24: =OR(N24=TRUE,O24=TRUE) -> FALSE
C25: =IF(P25=TRUE,C24+1,) -> 0 | E25: =IF(P25=TRUE,E24+F24,) -> 0 | N25: =ISTEXT(D25) -> FALSE | O25: =ISNUMBER(D25) -> FALSE | P25: =OR(N25=TRUE,O25=TRUE) -> FALSE
C26: =IF(P26=TRUE,C25+1,) -> 0 | E26: =IF(P26=TRUE,E25+F25,) -> 0 | N26: =ISTEXT(D26) -> FALSE | O26: =ISNUMBER(D26) -> FALSE | P26: =OR(N26=TRUE,O26=TRUE) -> FALSE
C27: =IF(P27=TRUE,C26+1,) -> 0 | E27: =IF(P27=TRUE,E26+F26,) -> 0 | N27: =ISTEXT(D27) -> FALSE | O27: =ISNUMBER(D27) -> FALSE | P27: =OR(N27=TRUE,O27=TRUE) -> FALSE
C28: =IF(P28=TRUE,C27+1,) -> 0 | E28: =IF(P28=TRUE,E27+F27,) -> 0 | N28: =ISTEXT(D28) -> FALSE | O28: =ISNUMBER(D28) -> FALSE | P28: =OR(N28=TRUE,O28=TRUE) -> FALSE
C29: =IF(P29=TRUE,C28+1,) -> 0 | E29: =IF(P29=TRUE,E28+F28,) -> 0 | N29: =ISTEXT(D29) -> FALSE | O29: =ISNUMBER(D29) -> FALSE | P29: =OR(N29=TRUE,O29=TRUE) -> FALSE
C30: =IF(P30=TRUE,C29+1,) -> 0 | E30: =IF(P30=TRUE,E29+F29,) -> 0 | N30: =ISTEXT(D30) -> FALSE | O30: =ISNUMBER(D30) -> FALSE | P30: =OR(N30=TRUE,O30=TRUE) -> FALSE
C31: =IF(P31=TRUE,C30+1,) -> 0 | E31: =IF(P31=TRUE,E30+F30,) -> 0 | N31: =ISTEXT(D31) -> FALSE | O31: =ISNUMBER(D31) -> FALSE | P31: =OR(N31=TRUE,O31=TRUE) -> FALSE
C32: =IF(P32=TRUE,C31+1,) -> 0 | E32: =IF(P32=TRUE,E31+F31,) -> 0 | N32: =ISTEXT(D32) -> FALSE | O32: =ISNUMBER(D32) -> FALSE | P32: =OR(N32=TRUE,O32=TRUE) -> FALSE
... C99: =IF(P99=TRUE,C98+1,) -> 0 | E99: =IF(P99=TRUE,E98+F98,) -> 0 | N99: =ISTEXT(D99) -> FALSE | O99: =ISNUMBER(D99) -> FALSE | P99: =OR(N99=TRUE,O99=TRUE) -> FALSE

Sheet LT - Rdto. Letras del Tesoro
D2: Diseño de registro de datos fiscales y personales
D3: ='CONTROL DE VERSIONES'!G68 -> IRPF 2025
D4: Rendimientos de Letras del Tesoro
C5: =IF(P5=TRUE,C4+1,) -> 0
C6: =IF(P6=TRUE,C5+1,) -> 0
C7: Este concepto de datos fiscales incluye los datos de los rendimientos de Letras del Tesoro con origen en el Modelo 192
C9: Nº | D9: Nombre | E9: Posición | F9: Longitud | G9: Descripción
C10: =IF(P10=TRUE,1,) -> 1 | D10: Tipo | E10: =IF(P10=TRUE,1,) -> 1 | F10: 1 | G10: Tipo de registro = '2' | N10: =ISTEXT(D10) -> TRUE | O10: =ISNUMBER(D10) -> FALSE | P10: =OR(N10=TRUE,O10=TRUE) -> TRUE
C11: =IF(P11=TRUE,C10+1,) -> 2 | D11: Código | E11: =IF(P11=TRUE,E10+F10,) -> 2 | F11: 7 | G11: 'LTnnnnn' Donde nnnn es el número del registro de este tipo contenido en el fichero de datos fiscales. | N11: =ISTEXT(D11) -> TRUE | O11: =ISNUMBER(D11) -> FALSE | P11: =OR(N11=TRUE,O11=TRUE) -> TRUE
C12: =IF(P12=TRUE,C11+1,) -> 3 | D12: NIF del Declarante | E12: =IF(P12=TRUE,E11+F11,) -> 9 | F12: 9 | N12: =ISTEXT(D12) -> TRUE | O12: =ISNUMBER(D12) -> FALSE | P12: =OR(N12=TRUE,O12=TRUE) -> TRUE
C13: =IF(P13=TRUE,C12+1,) -> 4 | D13: Nombre del Declarante | E13: =IF(P13=TRUE,E12+F12,) -> 18 | F13: 40 | G13: Nombre de la Entidad | N13: =ISTEXT(D13) -> TRUE | O13: =ISNUMBER(D13) -> FALSE | P13: =OR(N13=TRUE,O13=TRUE) -> TRUE
C14: =IF(P14=TRUE,C13+1,) -> 5 | D14: Importe de la compra | E14: =IF(P14=TRUE,E13+F13,) -> 58 | F14: 15 | N14: =ISTEXT(D14) -> TRUE | O14: =ISNUMBER(D14) -> FALSE | P14: =OR(N14=TRUE,O14=TRUE) -> TRUE
C15: =IF(P15=TRUE,C14+1,) -> 6 | D15: Fecha de la compra | E15: =IF(P15=TRUE,E14+F14,) -> 73 | F15: 8 | G15: AAAAMMDD (Formato de la fecha) | N15: =ISTEXT(D15) -> TRUE | O15: =ISNUMBER(D15) -> FALSE | P15: =OR(N15=TRUE,O15=TRUE) -> TRUE
C16: =IF(P16=TRUE,C15+1,) -> 7 | D16: Importe de la venta | E16: =IF(P16=TRUE,E15+F15,) -> 81 | F16: 15 | N16: =ISTEXT(D16) -> TRUE | O16: =ISNUMBER(D16) -> FALSE | P16: =OR(N16=TRUE,O16=TRUE) -> TRUE
C17: =IF(P17=TRUE,C16+1,) -> 8 | D17: Fecha de la venta | E17: =IF(P17=TRUE,E16+F16,) -> 96 | F17: 8 | G17: AAAAMMDD (Formato de la fecha) | N17: =ISTEXT(D17) -> TRUE | O17: =ISNUMBER(D17) -> FALSE | P17: =OR(N17=TRUE,O17=TRUE) -> TRUE
C18: =IF(P18=TRUE,C17+1,) -> 9 | D18: Número de titulares | E18: =IF(P18=TRUE,E17+F17,) -> 104 | F18: 3 | N18: =ISTEXT(D18) -> TRUE | O18: =ISNUMBER(D18) -> FALSE | P18: =OR(N18=TRUE,O18=TRUE) -> TRUE
C19: =IF(P19=TRUE,C18+1,) -> 10 | D19: Rendimiento | E19: =IF(P19=TRUE,E18+F18,) -> 107 | F19: 15 | N19: =ISTEXT(D19) -> TRUE | O19: =ISNUMBER(D19) -> FALSE | P19: =OR(N19=TRUE,O19=TRUE) -> TRUE
C20: =IF(P20=TRUE,C19+1,) -> 11 | D20: Gastos de la operación | E20: =IF(P20=TRUE,E19+F19,) -> 122 | F20: 15 | N20: =ISTEXT(D20) -> TRUE | O20: =ISNUMBER(D20) -> FALSE | P20: =OR(N20=TRUE,O20=TRUE) -> TRUE
C21: =IF(P21=TRUE,C20+1,) -> 12 | D21: Clave de traspaso | E21: =IF(P21=TRUE,E20+F20,) -> 137 | F21: 1 | G21: Valores.: 'T' o ' ' | N21: =ISTEXT(D21) -> TRUE | O21: =ISNUMBER(D21) -> FALSE | P21: =OR(N21=TRUE,O21=TRUE) -> TRUE
C22: =IF(P22=TRUE,C21+1,) -> 0 | E22: =IF(P22=TRUE,E21+F21,) -> 0 | N22: =ISTEXT(D22) -> FALSE | O22: =ISNUMBER(D22) -> FALSE | P22: =OR(N22=TRUE,O22=TRUE) -> FALSE
C23: =IF(P23=TRUE,C22+1,) -> 0 | E23: =IF(P23=TRUE,E22+F22,) -> 0 | N23: =ISTEXT(D23) -> FALSE | O23: =ISNUMBER(D23) -> FALSE | P23: =OR(N23=TRUE,O23=TRUE) -> FALSE
C24: =IF(P24=TRUE,C23+1,) -> 0 | E24: =IF(P24=TRUE,E23+F23,) -> 0 | N24: =ISTEXT(D24) -> FALSE | O24: =ISNUMBER(D24) -> FALSE | P24: =OR(N24=TRUE,O24=TRUE) -> FALSE
C25: =IF(P25=TRUE,C24+1,) -> 0 | E25: =IF(P25=TRUE,E24+F24,) -> 0 | N25: =ISTEXT(D25) -> FALSE | O25: =ISNUMBER(D25) -> FALSE | P25: =OR(N25=TRUE,O25=TRUE) -> FALSE
C26: =IF(P26=TRUE,C25+1,) -> 0 | E26: =IF(P26=TRUE,E25+F25,) -> 0 | N26: =ISTEXT(D26) -> FALSE | O26: =ISNUMBER(D26) -> FALSE | P26: =OR(N26=TRUE,O26=TRUE) -> FALSE
C27: =IF(P27=TRUE,C26+1,) -> 0 | E27: =IF(P27=TRUE,E26+F26,) -> 0 | N27: =ISTEXT(D27) -> FALSE | O27: =ISNUMBER(D27) -> FALSE | P27: =OR(N27=TRUE,O27=TRUE) -> FALSE
C28: =IF(P28=TRUE,C27+1,) -> 0 | E28: =IF(P28=TRUE,E27+F27,) -> 0 | N28: =ISTEXT(D28) -> FALSE | O28: =ISNUMBER(D28) -> FALSE | P28: =OR(N28=TRUE,O28=TRUE) -> FALSE
C29: =IF(P29=TRUE,C28+1,) -> 0 | E29: =IF(P29=TRUE,E28+F28,) -> 0 | N29: =ISTEXT(D29) -> FALSE | O29: =ISNUMBER(D29) -> FALSE | P29: =OR(N29=TRUE,O29=TRUE) -> FALSE
C30: =IF(P30=TRUE,C29+1,) -> 0 | E30: =IF(P30=TRUE,E29+F29,) -> 0 | N30: =ISTEXT(D30) -> FALSE | O30: =ISNUMBER(D30) -> FALSE | P30: =OR(N30=TRUE,O30=TRUE) -> FALSE
C31: =IF(P31=TRUE,C30+1,) -> 0 | E31: =IF(P31=TRUE,E30+F30,) -> 0 | N31: =ISTEXT(D31) -> FALSE | O31: =ISNUMBER(D31) -> FALSE | P31: =OR(N31=TRUE,O31=TRUE) -> FALSE
C32: =IF(P32=TRUE,C31+1,) -> 0 | E32: =IF(P32=TRUE,E31+F31,) -> 0 | N32: =ISTEXT(D32) -> FALSE | O32: =ISNUMBER(D32) -> FALSE | P32: =OR(N32=TRUE,O32=TRUE) -> FALSE
C33: =IF(P33=TRUE,C32+1,) -> 0 | E33: =IF(P33=TRUE,E32+F32,) -> 0 | N33: =ISTEXT(D33) -> FALSE | O33: =ISNUMBER(D33) -> FALSE | P33: =OR(N33=TRUE,O33=TRUE) -> FALSE
... C99: =IF(P99=TRUE,C98+1,) -> 0 | E99: =IF(P99=TRUE,E98+F98,) -> 0 | N99: =ISTEXT(D99) -> FALSE | O99: =ISNUMBER(D99) -> FALSE | P99: =OR(N99=TRUE,O99=TRUE) -> FALSE

Sheet REA - Rdtos. Explícito B.Imp A
D2: Diseño de registro de datos fiscales y personales
D3: ='CONTROL DE VERSIONES'!G68 -> IRPF 2025
D4: Rendimientos explícitos del capital mobiliario, base imponible del ahorro
C5: =IF(P5=TRUE,C4+1,) -> 0
C6: =IF(P6=TRUE,C5+1,) -> 0
C7: Este concepto de datos fiscales incluye los datos de los rendimientos explícitos de capital mobiliario dentro de la base imponible del ahorro con origen en el Modelo 193
C9: Nº | D9: Nombre | E9: Posición | F9: Longitud | G9: Descripción
C10: =IF(P10=TRUE,1,) -> 1 | D10: Tipo | E10: =IF(P10=TRUE,1,) -> 1 | F10: 1 | G10: Tipo de registro = '2' | N10: =ISTEXT(D10) -> TRUE | O10: =ISNUMBER(D10) -> FALSE | P10: =OR(N10=TRUE,O10=TRUE) -> TRUE
C11: =IF(P11=TRUE,C10+1,) -> 2 | D11: Código | E11: =IF(P11=TRUE,E10+F10,) -> 2 | F11: 7 | G11: 'REAnnnn' Donde nnnn es el número del registro de este tipo contenido en el fichero de datos fiscales. | N11: =ISTEXT(D11) -> TRUE | O11: =ISNUMBER(D11) -> FALSE | P11: =OR(N11=TRUE,O11=TRUE) -> TRUE
C12: =IF(P12=TRUE,C11+1,) -> 3 | D12: NIF del Emisor | E12: =IF(P12=TRUE,E11+F11,) -> 9 | F12: 9 | N12: =ISTEXT(D12) -> TRUE | O12: =ISNUMBER(D12) -> FALSE | P12: =OR(N12=TRUE,O12=TRUE) -> TRUE
C13: =IF(P13=TRUE,C12+1,) -> 4 | D13: Nombre del Emisor | E13: =IF(P13=TRUE,E12+F12,) -> 18 | F13: 40 | G13: Nombre de la Entidad | N13: =ISTEXT(D13) -> TRUE | O13: =ISNUMBER(D13) -> FALSE | P13: =OR(N13=TRUE,O13=TRUE) -> TRUE
C14: =IF(P14=TRUE,C13+1,) -> 5 | D14: NIF del Declarante | E14: =IF(P14=TRUE,E13+F13,) -> 58 | F14: 9 | N14: =ISTEXT(D14) -> TRUE | O14: =ISNUMBER(D14) -> FALSE | P14: =OR(N14=TRUE,O14=TRUE) -> TRUE
C15: =IF(P15=TRUE,C14+1,) -> 6 | D15: Nombre del Declarante | E15: =IF(P15=TRUE,E14+F14,) -> 67 | F15: 40 | N15: =ISTEXT(D15) -> TRUE | O15: =ISNUMBER(D15) -> FALSE | P15: =OR(N15=TRUE,O15=TRUE) -> TRUE
C16: =IF(P16=TRUE,C15+1,) -> 7 | D16: Clave y subclave | E16: =IF(P16=TRUE,E15+F15,) -> 107 | F16: 3 | G16: Claves: ‘A01’ - Prima A. J. ‘A02’ - Dividendo ‘A03’ - Dividendo ‘A04’ - Dividendo ‘A05’ - Otros ‘A07’ - Dividendo ‘A08’ - Dividendo ‘B01’ - Intereses ‘B02’ - Intereses ‘B03’ - Intereses ‘B04’ - I. Bonific. ‘B05’ - I.Cesión c. ‘B06’ - ‘Otros’ ‘C05’ - Rentas vit. 'C13' - Otros rendimientos BIA ‘GAS’ - Gastos | N16: =ISTEXT(D16) -> TRUE | O16: =ISNUMBER(D16) -> FALSE | P16: =OR(N16=TRUE,O16=TRUE) -> TRUE
C17: =IF(P17=TRUE,C16+1,) -> 8 | D17: Tipo | E17: =IF(P17=TRUE,E16+F16,) -> 110 | F17: 1 | G17: Valores: '1' Dinerarias '2' En especie | N17: =ISTEXT(D17) -> TRUE | O17: =ISNUMBER(D17) -> FALSE | P17: =OR(N17=TRUE,O17=TRUE) -> TRUE
C18: =IF(P18=TRUE,C17+1,) -> 9 | D18: Importe Integro | E18: =IF(P18=TRUE,E17+F17,) -> 111 | F18: 15 | G18: Importe declarado + Compensación Nota: Importe de la percepción declarada más la compensación. Si la percepción es cero y la base de retención distinta de cero y la retención distinta de cero se toma la base de retención como percepción, excepto cuando la base de retención es igual a la compensación en cuyo caso se deja como está (percepción igual a cero). | N18: =ISTEXT(D18) -> TRUE | O18: =ISNUMBER(D18) -> FALSE | P18: =OR(N18=TRUE,O18=TRUE) -> TRUE
C19: =IF(P19=TRUE,C18+1,) -> 10 | D19: Retención | E19: =IF(P19=TRUE,E18+F18,) -> 126 | F19: 13 | N19: =ISTEXT(D19) -> TRUE | O19: =ISNUMBER(D19) -> FALSE | P19: =OR(N19=TRUE,O19=TRUE) -> TRUE
C20: =IF(P20=TRUE,C19+1,) -> 11 | D20: Gastos deducibles | E20: =IF(P20=TRUE,E19+F19,) -> 139 | F20: 13 | G20: Este importe sólo en clave ‘GAS’ | N20: =ISTEXT(D20) -> TRUE | O20: =ISNUMBER(D20) -> FALSE | P20: =OR(N20=TRUE,O20=TRUE) -> TRUE
C21: =IF(P21=TRUE,C20+1,) -> 12 | D21: Penalización | E21: =IF(P21=TRUE,E20+F20,) -> 152 | F21: 11 | N21: =ISTEXT(D21) -> TRUE | O21: =ISNUMBER(D21) -> FALSE | P21: =OR(N21=TRUE,O21=TRUE) -> TRUE
C22: =IF(P22=TRUE,C21+1,) -> 0 | E22: =IF(P22=TRUE,E21+F21,) -> 0 | N22: =ISTEXT(D22) -> FALSE | O22: =ISNUMBER(D22) -> FALSE | P22: =OR(N22=TRUE,O22=TRUE) -> FALSE
C23: =IF(P23=TRUE,C22+1,) -> 0 | E23: =IF(P23=TRUE,E22+F22,) -> 0 | N23: =ISTEXT(D23) -> FALSE | O23: =ISNUMBER(D23) -> FALSE | P23: =OR(N23=TRUE,O23=TRUE) -> FALSE
C24: =IF(P24=TRUE,C23+1,) -> 0 | E24: =IF(P24=TRUE,E23+F23,) -> 0 | N24: =ISTEXT(D24) -> FALSE | O24: =ISNUMBER(D24) -> FALSE | P24: =OR(N24=TRUE,O24=TRUE) -> FALSE
C25: =IF(P25=TRUE,C24+1,) -> 0 | E25: =IF(P25=TRUE,E24+F24,) -> 0 | N25: =ISTEXT(D25) -> FALSE | O25: =ISNUMBER(D25) -> FALSE | P25: =OR(N25=TRUE,O25=TRUE) -> FALSE
C26: =IF(P26=TRUE,C25+1,) -> 0 | E26: =IF(P26=TRUE,E25+F25,) -> 0 | N26: =ISTEXT(D26) -> FALSE | O26: =ISNUMBER(D26) -> FALSE | P26: =OR(N26=TRUE,O26=TRUE) -> FALSE
C27: =IF(P27=TRUE,C26+1,) -> 0 | E27: =IF(P27=TRUE,E26+F26,) -> 0 | N27: =ISTEXT(D27) -> FALSE | O27: =ISNUMBER(D27) -> FALSE | P27: =OR(N27=TRUE,O27=TRUE) -> FALSE
C28: =IF(P28=TRUE,C27+1,) -> 0 | E28: =IF(P28=TRUE,E27+F27,) -> 0 | N28: =ISTEXT(D28) -> FALSE | O28: =ISNUMBER(D28) -> FALSE | P28: =OR(N28=TRUE,O28=TRUE) -> FALSE
C29: =IF(P29=TRUE,C28+1,) -> 0 | E29: =IF(P29=TRUE,E28+F28,) -> 0 | N29: =ISTEXT(D29) -> FALSE | O29: =ISNUMBER(D29) -> FALSE | P29: =OR(N29=TRUE,O29=TRUE) -> FALSE
C30: =IF(P30=TRUE,C29+1,) -> 0 | E30: =IF(P30=TRUE,E29+F29,) -> 0 | N30: =ISTEXT(D30) -> FALSE | O30: =ISNUMBER(D30) -> FALSE | P30: =OR(N30=TRUE,O30=TRUE) -> FALSE
C31: =IF(P31=TRUE,C30+1,) -> 0 | E31: =IF(P31=TRUE,E30+F30,) -> 0 | N31: =ISTEXT(D31) -> FALSE | O31: =ISNUMBER(D31) -> FALSE | P31: =OR(N31=TRUE,O31=TRUE) -> FALSE
C32: =IF(P32=TRUE,C31+1,) -> 0 | E32: =IF(P32=TRUE,E31+F31,) -> 0 | N32: =ISTEXT(D32) -> FALSE | O32: =ISNUMBER(D32) -> FALSE | P32: =OR(N32=TRUE,O32=TRUE) -> FALSE
C33: =IF(P33=TRUE,C32+1,) -> 0 | E33: =IF(P33=TRUE,E32+F32,) -> 0 | N33: =ISTEXT(D33) -> FALSE | O33: =ISNUMBER(D33) -> FALSE | P33: =OR(N33=TRUE,O33=TRUE) -> FALSE
... C99: =IF(P99=TRUE,C98+1,) -> 0 | E99: =IF(P99=TRUE,E98+F98,) -> 0 | N99: =ISTEXT(D99) -> FALSE | O99: =ISNUMBER(D99) -> FALSE | P99: =OR(N99=TRUE,O99=TRUE) -> FALSE

Sheet REG - Rdtos. Explícito B.Imp G
D2: Diseño de registro de datos fiscales y personales
D3: ='CONTROL DE VERSIONES'!G68 -> IRPF 2025
D4: Rendimientos explícitos del capital mobiliario, base imponible general
C5: =IF(P5=TRUE,C4+1,) -> 0
C6: =IF(P6=TRUE,C5+1,) -> 0
C7: Este concepto de datos fiscales incluye los datos de los rendimientos explícitos de capital mobiliario dentro de la base imponible general con origen en el Modelo 193
C9: Nº | D9: Nombre | E9: Posición | F9: Longitud | G9: Descripción
C10: =IF(P10=TRUE,1,) -> 1 | D10: Tipo | E10: =IF(P10=TRUE,1,) -> 1 | F10: 1 | G10: Tipo de registro = '2' | N10: =ISTEXT(D10) -> TRUE | O10: =ISNUMBER(D10) -> FALSE | P10: =OR(N10=TRUE,O10=TRUE) -> TRUE
C11: =IF(P11=TRUE,C10+1,) -> 2 | D11: Código | E11: =IF(P11=TRUE,E10+F10,) -> 2 | F11: 7 | G11: 'REGnnnn' Donde nnnn es el número del registro de este tipo contenido en el fichero de datos fiscales. | N11: =ISTEXT(D11) -> TRUE | O11: =ISNUMBER(D11) -> FALSE | P11: =OR(N11=TRUE,O11=TRUE) -> TRUE
C12: =IF(P12=TRUE,C11+1,) -> 3 | D12: NIF del Emisor | E12: =IF(P12=TRUE,E11+F11,) -> 9 | F12: 9 | N12: =ISTEXT(D12) -> TRUE | O12: =ISNUMBER(D12) -> FALSE | P12: =OR(N12=TRUE,O12=TRUE) -> TRUE
C13: =IF(P13=TRUE,C12+1,) -> 4 | D13: Nombre del Emisor | E13: =IF(P13=TRUE,E12+F12,) -> 18 | F13: 40 | G13: Nombre de la Entidad | N13: =ISTEXT(D13) -> TRUE | O13: =ISNUMBER(D13) -> FALSE | P13: =OR(N13=TRUE,O13=TRUE) -> TRUE
C14: =IF(P14=TRUE,C13+1,) -> 5 | D14: NIF del Declarante | E14: =IF(P14=TRUE,E13+F13,) -> 58 | F14: 9 | N14: =ISTEXT(D14) -> TRUE | O14: =ISNUMBER(D14) -> FALSE | P14: =OR(N14=TRUE,O14=TRUE) -> TRUE
C15: =IF(P15=TRUE,C14+1,) -> 6 | D15: Nombre del Declarante | E15: =IF(P15=TRUE,E14+F14,) -> 67 | F15: 40 | N15: =ISTEXT(D15) -> TRUE | O15: =ISNUMBER(D15) -> FALSE | P15: =OR(N15=TRUE,O15=TRUE) -> TRUE
C16: =IF(P16=TRUE,C15+1,) -> 7 | D16: Clave y subclave | E16: =IF(P16=TRUE,E15+F15,) -> 107 | F16: 3 | G16: Claves: ‘C01’ - Prop. Intel. ‘C02’ - Prop. Indus. ‘C03’ - Asistenc. T. ‘C04’ - Arrend. M. ‘C06’ - Rdto. Imag. ‘C07’ - Arrend. Im ‘C12’ - Otros rendimientos BIG ‘C15’ - Cesiones derechos de autor ‘D01’ - Intereses ‘D02’ - Intereses ‘D03’ - Intereses ‘D04’ - I. Bonific. ‘D05’ - I.Cesión c. ‘D06’ - ‘Otros’ | N16: =ISTEXT(D16) -> TRUE | O16: =ISNUMBER(D16) -> FALSE | P16: =OR(N16=TRUE,O16=TRUE) -> TRUE
C17: =IF(P17=TRUE,C16+1,) -> 8 | D17: Tipo | E17: =IF(P17=TRUE,E16+F16,) -> 110 | F17: 1 | G17: Valores: '1' Dinerarias '2' En especie | N17: =ISTEXT(D17) -> TRUE | O17: =ISNUMBER(D17) -> FALSE | P17: =OR(N17=TRUE,O17=TRUE) -> TRUE
C18: =IF(P18=TRUE,C17+1,) -> 9 | D18: Importe Integro | E18: =IF(P18=TRUE,E17+F17,) -> 111 | F18: 15 | G18: Importe declarado + Compensación Nota: Importe de la percepción declarada más la compensación. Si la percepción es cero y la base de retención distinta de cero y la retención distinta de cero se toma la base de retención como percepción, excepto cuando la base de retención es igual a la compensación en cuyo caso se deja como está (percepción igual a cero). | N18: =ISTEXT(D18) -> TRUE | O18: =ISNUMBER(D18) -> FALSE | P18: =OR(N18=TRUE,O18=TRUE) -> TRUE
C19: =IF(P19=TRUE,C18+1,) -> 10 | D19: Retención | E19: =IF(P19=TRUE,E18+F18,) -> 126 | F19: 13 | N19: =ISTEXT(D19) -> TRUE | O19: =ISNUMBER(D19) -> FALSE | P19: =OR(N19=TRUE,O19=TRUE) -> TRUE
C20: =IF(P20=TRUE,C19+1,) -> 11 | D20: Reducción | E20: =IF(P20=TRUE,E19+F19,) -> 139 | F20: 13 | N20: =ISTEXT(D20) -> TRUE | O20: =ISNUMBER(D20) -> FALSE | P20: =OR(N20=TRUE,O20=TRUE) -> TRUE
C21: =IF(P21=TRUE,C20+1,) -> 12 | D21: Penalización | E21: =IF(P21=TRUE,E20+F20,) -> 152 | F21: 11 | N21: =ISTEXT(D21) -> TRUE | O21: =ISNUMBER(D21) -> FALSE | P21: =OR(N21=TRUE,O21=TRUE) -> TRUE
C22: =IF(P22=TRUE,C21+1,) -> 0 | E22: =IF(P22=TRUE,E21+F21,) -> 0 | N22: =ISTEXT(D22) -> FALSE | O22: =ISNUMBER(D22) -> FALSE | P22: =OR(N22=TRUE,O22=TRUE) -> FALSE
C23: =IF(P23=TRUE,C22+1,) -> 0 | E23: =IF(P23=TRUE,E22+F22,) -> 0 | N23: =ISTEXT(D23) -> FALSE | O23: =ISNUMBER(D23) -> FALSE | P23: =OR(N23=TRUE,O23=TRUE) -> FALSE
C24: =IF(P24=TRUE,C23+1,) -> 0 | E24: =IF(P24=TRUE,E23+F23,) -> 0 | N24: =ISTEXT(D24) -> FALSE | O24: =ISNUMBER(D24) -> FALSE | P24: =OR(N24=TRUE,O24=TRUE) -> FALSE
C25: =IF(P25=TRUE,C24+1,) -> 0 | E25: =IF(P25=TRUE,E24+F24,) -> 0 | N25: =ISTEXT(D25) -> FALSE | O25: =ISNUMBER(D25) -> FALSE | P25: =OR(N25=TRUE,O25=TRUE) -> FALSE
C26: =IF(P26=TRUE,C25+1,) -> 0 | E26: =IF(P26=TRUE,E25+F25,) -> 0 | N26: =ISTEXT(D26) -> FALSE | O26: =ISNUMBER(D26) -> FALSE | P26: =OR(N26=TRUE,O26=TRUE) -> FALSE
C27: =IF(P27=TRUE,C26+1,) -> 0 | E27: =IF(P27=TRUE,E26+F26,) -> 0 | N27: =ISTEXT(D27) -> FALSE | O27: =ISNUMBER(D27) -> FALSE | P27: =OR(N27=TRUE,O27=TRUE) -> FALSE
C28: =IF(P28=TRUE,C27+1,) -> 0 | E28: =IF(P28=TRUE,E27+F27,) -> 0 | N28: =ISTEXT(D28) -> FALSE | O28: =ISNUMBER(D28) -> FALSE | P28: =OR(N28=TRUE,O28=TRUE) -> FALSE
C29: =IF(P29=TRUE,C28+1,) -> 0 | E29: =IF(P29=TRUE,E28+F28,) -> 0 | N29: =ISTEXT(D29) -> FALSE | O29: =ISNUMBER(D29) -> FALSE | P29: =OR(N29=TRUE,O29=TRUE) -> FALSE
C30: =IF(P30=TRUE,C29+1,) -> 0 | E30: =IF(P30=TRUE,E29+F29,) -> 0 | N30: =ISTEXT(D30) -> FALSE | O30: =ISNUMBER(D30) -> FALSE | P30: =OR(N30=TRUE,O30=TRUE) -> FALSE
C31: =IF(P31=TRUE,C30+1,) -> 0 | E31: =IF(P31=TRUE,E30+F30,) -> 0 | N31: =ISTEXT(D31) -> FALSE | O31: =ISNUMBER(D31) -> FALSE | P31: =OR(N31=TRUE,O31=TRUE) -> FALSE
C32: =IF(P32=TRUE,C31+1,) -> 0 | E32: =IF(P32=TRUE,E31+F31,) -> 0 | N32: =ISTEXT(D32) -> FALSE | O32: =ISNUMBER(D32) -> FALSE | P32: =OR(N32=TRUE,O32=TRUE) -> FALSE
C33: =IF(P33=TRUE,C32+1,) -> 0 | E33: =IF(P33=TRUE,E32+F32,) -> 0 | N33: =ISTEXT(D33) -> FALSE | O33: =ISNUMBER(D33) -> FALSE | P33: =OR(N33=TRUE,O33=TRUE) -> FALSE
... C99: =IF(P99=TRUE,C98+1,) -> 0 | E99: =IF(P99=TRUE,E98+F98,) -> 0 | N99: =ISTEXT(D99) -> FALSE | O99: =ISNUMBER(D99) -> FALSE | P99: =OR(N99=TRUE,O99=TRUE) -> FALSE

Sheet RI - Rdtos. Implícito
D2: Diseño de registro de datos fiscales y personales
D3: ='CONTROL DE VERSIONES'!G68 -> IRPF 2025
D4: Rendimientos implícitos del capital mobiliario
C5: =IF(P5=TRUE,C4+1,) -> 0
C6: =IF(P6=TRUE,C5+1,) -> 0
C7: Este concepto de datos fiscales incluye los datos de los rendimientos implícitos de capital mobiliario con origen en el Modelo 194
C9: Nº | D9: Nombre | E9: Posición | F9: Longitud | G9: Descripción
C10: =IF(P10=TRUE,1,) -> 1 | D10: Tipo | E10: =IF(P10=TRUE,1,) -> 1 | F10: 1 | G10: Tipo de registro = '2' | N10: =ISTEXT(D10) -> TRUE | O10: =ISNUMBER(D10) -> FALSE | P10: =OR(N10=TRUE,O10=TRUE) -> TRUE
C11: =IF(P11=TRUE,C10+1,) -> 2 | D11: Código | E11: =IF(P11=TRUE,E10+F10,) -> 2 | F11: 7 | G11: 'RInnnnn' Donde nnnn es el número del registro de este tipo contenido en el fichero de datos fiscales. | N11: =ISTEXT(D11) -> TRUE | O11: =ISNUMBER(D11) -> FALSE | P11: =OR(N11=TRUE,O11=TRUE) -> TRUE
C12: =IF(P12=TRUE,C11+1,) -> 3 | D12: NIF del Emisor | E12: =IF(P12=TRUE,E11+F11,) -> 9 | F12: 9 | N12: =ISTEXT(D12) -> TRUE | O12: =ISNUMBER(D12) -> FALSE | P12: =OR(N12=TRUE,O12=TRUE) -> TRUE
C13: =IF(P13=TRUE,C12+1,) -> 4 | D13: Nombre del Emisor | E13: =IF(P13=TRUE,E12+F12,) -> 18 | F13: 40 | G13: Nombre de la Entidad | N13: =ISTEXT(D13) -> TRUE | O13: =ISNUMBER(D13) -> FALSE | P13: =OR(N13=TRUE,O13=TRUE) -> TRUE
C14: =IF(P14=TRUE,C13+1,) -> 5 | D14: NIF del Declarante | E14: =IF(P14=TRUE,E13+F13,) -> 58 | F14: 9 | N14: =ISTEXT(D14) -> TRUE | O14: =ISNUMBER(D14) -> FALSE | P14: =OR(N14=TRUE,O14=TRUE) -> TRUE
C15: =IF(P15=TRUE,C14+1,) -> 6 | D15: Nombre del Declarante | E15: =IF(P15=TRUE,E14+F14,) -> 67 | F15: 40 | N15: =ISTEXT(D15) -> TRUE | O15: =ISNUMBER(D15) -> FALSE | P15: =OR(N15=TRUE,O15=TRUE) -> TRUE
C16: =IF(P16=TRUE,C15+1,) -> 7 | D16: Origen | E16: =IF(P16=TRUE,E15+F15,) -> 107 | F16: 1 | G16: Orígenes: ‘A’ - Transmisión ‘B’ - Amortización o reembolso ‘C’ - Canje o conversión ‘D’ - Transm de AF antes de los 30 anteriores al vencimiento del cupón. ‘E’ - Cesión Temp de AF con pacto de recompra. | N16: =ISTEXT(D16) -> TRUE | O16: =ISNUMBER(D16) -> FALSE | P16: =OR(N16=TRUE,O16=TRUE) -> TRUE
C17: =IF(P17=TRUE,C16+1,) -> 8 | D17: Rendimiento | E17: =IF(P17=TRUE,E16+F16,) -> 108 | F17: 13 | G17: Base de retención | N17: =ISTEXT(D17) -> TRUE | O17: =ISNUMBER(D17) -> FALSE | P17: =OR(N17=TRUE,O17=TRUE) -> TRUE
C18: =IF(P18=TRUE,C17+1,) -> 9 | D18: Retención | E18: =IF(P18=TRUE,E17+F17,) -> 121 | F18: 13 | N18: =ISTEXT(D18) -> TRUE | O18: =ISNUMBER(D18) -> FALSE | P18: =OR(N18=TRUE,O18=TRUE) -> TRUE
C19: =IF(P19=TRUE,C18+1,) -> 10 | D19: Vinculación | E19: =IF(P19=TRUE,E18+F18,) -> 134 | F19: 1 | G19: Valores posibles: 'V' - Rendimientos de entidades vinculadas. ' ' - No son rendimientos de entidades vinculadas. | N19: =ISTEXT(D19) -> TRUE | O19: =ISNUMBER(D19) -> FALSE | P19: =OR(N19=TRUE,O19=TRUE) -> TRUE
C20: =IF(P20=TRUE,C19+1,) -> 0 | E20: =IF(P20=TRUE,E19+F19,) -> 0 | N20: =ISTEXT(D20) -> FALSE | O20: =ISNUMBER(D20) -> FALSE | P20: =OR(N20=TRUE,O20=TRUE) -> FALSE
C21: =IF(P21=TRUE,C20+1,) -> 0 | E21: =IF(P21=TRUE,E20+F20,) -> 0 | N21: =ISTEXT(D21) -> FALSE | O21: =ISNUMBER(D21) -> FALSE | P21: =OR(N21=TRUE,O21=TRUE) -> FALSE
C22: =IF(P22=TRUE,C21+1,) -> 0 | E22: =IF(P22=TRUE,E21+F21,) -> 0 | N22: =ISTEXT(D22) -> FALSE | O22: =ISNUMBER(D22) -> FALSE | P22: =OR(N22=TRUE,O22=TRUE) -> FALSE
C23: =IF(P23=TRUE,C22+1,) -> 0 | E23: =IF(P23=TRUE,E22+F22,) -> 0 | N23: =ISTEXT(D23) -> FALSE | O23: =ISNUMBER(D23) -> FALSE | P23: =OR(N23=TRUE,O23=TRUE) -> FALSE
C24: =IF(P24=TRUE,C23+1,) -> 0 | E24: =IF(P24=TRUE,E23+F23,) -> 0 | N24: =ISTEXT(D24) -> FALSE | O24: =ISNUMBER(D24) -> FALSE | P24: =OR(N24=TRUE,O24=TRUE) -> FALSE
C25: =IF(P25=TRUE,C24+1,) -> 0 | E25: =IF(P25=TRUE,E24+F24,) -> 0 | N25: =ISTEXT(D25) -> FALSE | O25: =ISNUMBER(D25) -> FALSE | P25: =OR(N25=TRUE,O25=TRUE) -> FALSE
C26: =IF(P26=TRUE,C25+1,) -> 0 | E26: =IF(P26=TRUE,E25+F25,) -> 0 | N26: =ISTEXT(D26) -> FALSE | O26: =ISNUMBER(D26) -> FALSE | P26: =OR(N26=TRUE,O26=TRUE) -> FALSE
C27: =IF(P27=TRUE,C26+1,) -> 0 | E27: =IF(P27=TRUE,E26+F26,) -> 0 | N27: =ISTEXT(D27) -> FALSE | O27: =ISNUMBER(D27) -> FALSE | P27: =OR(N27=TRUE,O27=TRUE) -> FALSE
C28: =IF(P28=TRUE,C27+1,) -> 0 | E28: =IF(P28=TRUE,E27+F27,) -> 0 | N28: =ISTEXT(D28) -> FALSE | O28: =ISNUMBER(D28) -> FALSE | P28: =OR(N28=TRUE,O28=TRUE) -> FALSE
C29: =IF(P29=TRUE,C28+1,) -> 0 | E29: =IF(P29=TRUE,E28+F28,) -> 0 | N29: =ISTEXT(D29) -> FALSE | O29: =ISNUMBER(D29) -> FALSE | P29: =OR(N29=TRUE,O29=TRUE) -> FALSE
C30: =IF(P30=TRUE,C29+1,) -> 0 | E30: =IF(P30=TRUE,E29+F29,) -> 0 | N30: =ISTEXT(D30) -> FALSE | O30: =ISNUMBER(D30) -> FALSE | P30: =OR(N30=TRUE,O30=TRUE) -> FALSE
C31: =IF(P31=TRUE,C30+1,) -> 0 | E31: =IF(P31=TRUE,E30+F30,) -> 0 | N31: =ISTEXT(D31) -> FALSE | O31: =ISNUMBER(D31) -> FALSE | P31: =OR(N31=TRUE,O31=TRUE) -> FALSE
... C99: =IF(P99=TRUE,C98+1,) -> 0 | E99: =IF(P99=TRUE,E98+F98,) -> 0 | N99: =ISTEXT(D99) -> FALSE | O99: =ISNUMBER(D99) -> FALSE | P99: =OR(N99=TRUE,O99=TRUE) -> FALSE

Sheet SG - Rdtos. Operac. de Seguros
D2: Diseño de registro de datos fiscales y personales
D3: ='CONTROL DE VERSIONES'!G68 -> IRPF 2025
D4: Rendimientos de operaciones de seguros
C5: =IF(P5=TRUE,C4+1,) -> 0
C6: =IF(P6=TRUE,C5+1,) -> 0
C7: Este concepto de datos fiscales incluye los datos de los rendimientos obtenidos por operaciones de seguros con origen en el Modelo 188
C9: Nº | D9: Nombre | E9: Posición | F9: Longitud | G9: Descripción
C10: =IF(P10=TRUE,1,) -> 1 | D10: Tipo | E10: =IF(P10=TRUE,1,) -> 1 | F10: 1 | G10: Tipo de registro = '2' | N10: =ISTEXT(D10) -> TRUE | O10: =ISNUMBER(D10) -> FALSE | P10: =OR(N10=TRUE,O10=TRUE) -> TRUE
C11: =IF(P11=TRUE,C10+1,) -> 2 | D11: Código | E11: =IF(P11=TRUE,E10+F10,) -> 2 | F11: 7 | G11: 'SGnnnnn' Donde nnnn es el número del registro de este tipo contenido en el fichero de datos fiscales. | N11: =ISTEXT(D11) -> TRUE | O11: =ISNUMBER(D11) -> FALSE | P11: =OR(N11=TRUE,O11=TRUE) -> TRUE
C12: =IF(P12=TRUE,C11+1,) -> 3 | D12: NIF del Declarante | E12: =IF(P12=TRUE,E11+F11,) -> 9 | F12: 9 | N12: =ISTEXT(D12) -> TRUE | O12: =ISNUMBER(D12) -> FALSE | P12: =OR(N12=TRUE,O12=TRUE) -> TRUE
C13: =IF(P13=TRUE,C12+1,) -> 4 | D13: Nombre del Declarante | E13: =IF(P13=TRUE,E12+F12,) -> 18 | F13: 40 | N13: =ISTEXT(D13) -> TRUE | O13: =ISNUMBER(D13) -> FALSE | P13: =OR(N13=TRUE,O13=TRUE) -> TRUE
C14: =IF(P14=TRUE,C13+1,) -> 5 | D14: Modalidad | E14: =IF(P14=TRUE,E13+F13,) -> 58 | F14: 1 | G14: Valores: '1' Dinerarias '2' En especie | N14: =ISTEXT(D14) -> TRUE | O14: =ISNUMBER(D14) -> FALSE | P14: =OR(N14=TRUE,O14=TRUE) -> TRUE
C15: =IF(P15=TRUE,C14+1,) -> 6 | D15: Rendimiento | E15: =IF(P15=TRUE,E14+F14,) -> 59 | F15: 13 | G15: Rendimiento declarado + ing.cta (si es en especie) | N15: =ISTEXT(D15) -> TRUE | O15: =ISNUMBER(D15) -> FALSE | P15: =OR(N15=TRUE,O15=TRUE) -> TRUE
C16: =IF(P16=TRUE,C15+1,) -> 7 | D16: Retención e Ingreso a cuenta | E16: =IF(P16=TRUE,E15+F15,) -> 72 | F16: 13 | N16: =ISTEXT(D16) -> TRUE | O16: =ISNUMBER(D16) -> FALSE | P16: =OR(N16=TRUE,O16=TRUE) -> TRUE
C17: =IF(P17=TRUE,C16+1,) -> 8 | D17: Reduccción DT.4ª | E17: =IF(P17=TRUE,E16+F16,) -> 85 | F17: 13 | N17: =ISTEXT(D17) -> TRUE | O17: =ISNUMBER(D17) -> FALSE | P17: =OR(N17=TRUE,O17=TRUE) -> TRUE
C18: =IF(P18=TRUE,C17+1,) -> 9 | D18: Base de retención e ingreso a cuenta | E18: =IF(P18=TRUE,E17+F17,) -> 98 | F18: 13 | N18: =ISTEXT(D18) -> TRUE | O18: =ISNUMBER(D18) -> FALSE | P18: =OR(N18=TRUE,O18=TRUE) -> TRUE
C19: =IF(P19=TRUE,C18+1,) -> 0 | E19: =IF(P19=TRUE,E18+F18,) -> 0 | N19: =ISTEXT(D19) -> FALSE | O19: =ISNUMBER(D19) -> FALSE | P19: =OR(N19=TRUE,O19=TRUE) -> FALSE
C20: =IF(P20=TRUE,C19+1,) -> 0 | E20: =IF(P20=TRUE,E19+F19,) -> 0 | N20: =ISTEXT(D20) -> FALSE | O20: =ISNUMBER(D20) -> FALSE | P20: =OR(N20=TRUE,O20=TRUE) -> FALSE
C21: =IF(P21=TRUE,C20+1,) -> 0 | E21: =IF(P21=TRUE,E20+F20,) -> 0 | N21: =ISTEXT(D21) -> FALSE | O21: =ISNUMBER(D21) -> FALSE | P21: =OR(N21=TRUE,O21=TRUE) -> FALSE
C22: =IF(P22=TRUE,C21+1,) -> 0 | E22: =IF(P22=TRUE,E21+F21,) -> 0 | N22: =ISTEXT(D22) -> FALSE | O22: =ISNUMBER(D22) -> FALSE | P22: =OR(N22=TRUE,O22=TRUE) -> FALSE
C23: =IF(P23=TRUE,C22+1,) -> 0 | E23: =IF(P23=TRUE,E22+F22,) -> 0 | N23: =ISTEXT(D23) -> FALSE | O23: =ISNUMBER(D23) -> FALSE | P23: =OR(N23=TRUE,O23=TRUE) -> FALSE
C24: =IF(P24=TRUE,C23+1,) -> 0 | E24: =IF(P24=TRUE,E23+F23,) -> 0 | N24: =ISTEXT(D24) -> FALSE | O24: =ISNUMBER(D24) -> FALSE | P24: =OR(N24=TRUE,O24=TRUE) -> FALSE
C25: =IF(P25=TRUE,C24+1,) -> 0 | E25: =IF(P25=TRUE,E24+F24,) -> 0 | N25: =ISTEXT(D25) -> FALSE | O25: =ISNUMBER(D25) -> FALSE | P25: =OR(N25=TRUE,O25=TRUE) -> FALSE
C26: =IF(P26=TRUE,C25+1,) -> 0 | E26: =IF(P26=TRUE,E25+F25,) -> 0 | N26: =ISTEXT(D26) -> FALSE | O26: =ISNUMBER(D26) -> FALSE | P26: =OR(N26=TRUE,O26=TRUE) -> FALSE
C27: =IF(P27=TRUE,C26+1,) -> 0 | E27: =IF(P27=TRUE,E26+F26,) -> 0 | N27: =ISTEXT(D27) -> FALSE | O27: =ISNUMBER(D27) -> FALSE | P27: =OR(N27=TRUE,O27=TRUE) -> FALSE
C28: =IF(P28=TRUE,C27+1,) -> 0 | E28: =IF(P28=TRUE,E27+F27,) -> 0 | N28: =ISTEXT(D28) -> FALSE | O28: =ISNUMBER(D28) -> FALSE | P28: =OR(N28=TRUE,O28=TRUE) -> FALSE
C29: =IF(P29=TRUE,C28+1,) -> 0 | E29: =IF(P29=TRUE,E28+F28,) -> 0 | N29: =ISTEXT(D29) -> FALSE | O29: =ISNUMBER(D29) -> FALSE | P29: =OR(N29=TRUE,O29=TRUE) -> FALSE
C30: =IF(P30=TRUE,C29+1,) -> 0 | E30: =IF(P30=TRUE,E29+F29,) -> 0 | N30: =ISTEXT(D30) -> FALSE | O30: =ISNUMBER(D30) -> FALSE | P30: =OR(N30=TRUE,O30=TRUE) -> FALSE
... C99: =IF(P99=TRUE,C98+1,) -> 0 | E99: =IF(P99=TRUE,E98+F98,) -> 0 | N99: =ISTEXT(D99) -> FALSE | O99: =ISNUMBER(D99) -> FALSE | P99: =OR(N99=TRUE,O99=TRUE) -> FALSE

Sheet CD - Capitales Seguros de Vida
D2: Diseño de registro de datos fiscales y personales
D3: ='CONTROL DE VERSIONES'!G68 -> IRPF 2025
D4: Capitales diferidos de seguros de vida a cuyo rendimiento le sea aplicable la D.T. 4ª
C5: =IF(P5=TRUE,C4+1,) -> 0
C6: =IF(P6=TRUE,C5+1,) -> 0
C7: Este concepto de datos fiscales incluye los datos de los capitales diferidos de los seguros de vida a cuyo rendimiento le sea aplicable la D.T.4ª
C9: Nº | D9: Nombre | E9: Posición | F9: Longitud | G9: Descripción
C10: =IF(P10=TRUE,1,) -> 1 | D10: Tipo | E10: =IF(P10=TRUE,1,) -> 1 | F10: 1 | G10: Tipo de registro = '2' | N10: =ISTEXT(D10) -> TRUE | O10: =ISNUMBER(D10) -> FALSE | P10: =OR(N10=TRUE,O10=TRUE) -> TRUE
C11: =IF(P11=TRUE,C10+1,) -> 2 | D11: Código | E11: =IF(P11=TRUE,E10+F10,) -> 2 | F11: 7 | G11: 'CDnnnnn' Donde nnnn es el número del registro de este tipo contenido en el fichero de datos fiscales. | N11: =ISTEXT(D11) -> TRUE | O11: =ISNUMBER(D11) -> FALSE | P11: =OR(N11=TRUE,O11=TRUE) -> TRUE
C12: =IF(P12=TRUE,C11+1,) -> 3 | D12: Importe | E12: =IF(P12=TRUE,E11+F11,) -> 9 | F12: 13 | G12: Sumatorio de la casilla 44 de la declaración IRPF 2024 + casilla 44 de la declaración IRPF 2023 + casilla 44 de la declaración IRPF 2022 + casilla 44 de la declaración IRPF 2021 + casilla 44 de la declaración IRPF 2020 + casilla 44 de la declaración IRPF 2019 + casilla 44 de la declaración IRPF 2018 + casilla 42 de la declaración IRPF 2017 + casilla 38 de la declaración IRPF 2016 + casilla 29 de la declaración el IRPF 2015 que tenga tributación individual. | N12: =ISTEXT(D12) -> TRUE | O12: =ISNUMBER(D12) -> FALSE | P12: =OR(N12=TRUE,O12=TRUE) -> TRUE
C13: =IF(P13=TRUE,C12+1,) -> 4 | D13: Importe 2015 conjunta | E13: =IF(P13=TRUE,E12+F12,) -> 22 | F13: 13 | G13: Se obtiene de la casilla 29 de la declaración el IRPF 2015 que tenga tributación conjunta; no se puede identificar en este caso la proporción que corresponde a cada contribuyente y se indica de forma separada para que el contribuyente se aplique lo que corresponda. | N13: =ISTEXT(D13) -> TRUE | O13: =ISNUMBER(D13) -> FALSE | P13: =OR(N13=TRUE,O13=TRUE) -> TRUE
C14: =IF(P14=TRUE,C13+1,) -> 5 | D14: Tipo de tributación 2015 | E14: =IF(P14=TRUE,E13+F13,) -> 35 | F14: 1 | G14: Valores: 'I' Individual 'C' Conjunta | N14: =ISTEXT(D14) -> TRUE | O14: =ISNUMBER(D14) -> FALSE | P14: =OR(N14=TRUE,O14=TRUE) -> TRUE
C15: =IF(P15=TRUE,C14+1,) -> 0 | E15: =IF(P15=TRUE,E14+F14,) -> 0 | N15: =ISTEXT(D15) -> FALSE | O15: =ISNUMBER(D15) -> FALSE | P15: =OR(N15=TRUE,O15=TRUE) -> FALSE
C16: =IF(P16=TRUE,C15+1,) -> 0 | E16: =IF(P16=TRUE,E15+F15,) -> 0 | N16: =ISTEXT(D16) -> FALSE | O16: =ISNUMBER(D16) -> FALSE | P16: =OR(N16=TRUE,O16=TRUE) -> FALSE
C17: =IF(P17=TRUE,C16+1,) -> 0 | E17: =IF(P17=TRUE,E16+F16,) -> 0 | N17: =ISTEXT(D17) -> FALSE | O17: =ISNUMBER(D17) -> FALSE | P17: =OR(N17=TRUE,O17=TRUE) -> FALSE
C18: =IF(P18=TRUE,C17+1,) -> 0 | E18: =IF(P18=TRUE,E17+F17,) -> 0 | N18: =ISTEXT(D18) -> FALSE | O18: =ISNUMBER(D18) -> FALSE | P18: =OR(N18=TRUE,O18=TRUE) -> FALSE
C19: =IF(P19=TRUE,C18+1,) -> 0 | E19: =IF(P19=TRUE,E18+F18,) -> 0 | N19: =ISTEXT(D19) -> FALSE | O19: =ISNUMBER(D19) -> FALSE | P19: =OR(N19=TRUE,O19=TRUE) -> FALSE
C20: =IF(P20=TRUE,C19+1,) -> 0 | E20: =IF(P20=TRUE,E19+F19,) -> 0 | N20: =ISTEXT(D20) -> FALSE | O20: =ISNUMBER(D20) -> FALSE | P20: =OR(N20=TRUE,O20=TRUE) -> FALSE
C21: =IF(P21=TRUE,C20+1,) -> 0 | E21: =IF(P21=TRUE,E20+F20,) -> 0 | N21: =ISTEXT(D21) -> FALSE | O21: =ISNUMBER(D21) -> FALSE | P21: =OR(N21=TRUE,O21=TRUE) -> FALSE
C22: =IF(P22=TRUE,C21+1,) -> 0 | E22: =IF(P22=TRUE,E21+F21,) -> 0 | N22: =ISTEXT(D22) -> FALSE | O22: =ISNUMBER(D22) -> FALSE | P22: =OR(N22=TRUE,O22=TRUE) -> FALSE
C23: =IF(P23=TRUE,C22+1,) -> 0 | E23: =IF(P23=TRUE,E22+F22,) -> 0 | N23: =ISTEXT(D23) -> FALSE | O23: =ISNUMBER(D23) -> FALSE | P23: =OR(N23=TRUE,O23=TRUE) -> FALSE
C24: =IF(P24=TRUE,C23+1,) -> 0 | E24: =IF(P24=TRUE,E23+F23,) -> 0 | N24: =ISTEXT(D24) -> FALSE | O24: =ISNUMBER(D24) -> FALSE | P24: =OR(N24=TRUE,O24=TRUE) -> FALSE
C25: =IF(P25=TRUE,C24+1,) -> 0 | E25: =IF(P25=TRUE,E24+F24,) -> 0 | N25: =ISTEXT(D25) -> FALSE | O25: =ISNUMBER(D25) -> FALSE | P25: =OR(N25=TRUE,O25=TRUE) -> FALSE
C26: =IF(P26=TRUE,C25+1,) -> 0 | E26: =IF(P26=TRUE,E25+F25,) -> 0 | N26: =ISTEXT(D26) -> FALSE | O26: =ISNUMBER(D26) -> FALSE | P26: =OR(N26=TRUE,O26=TRUE) -> FALSE
... C99: =IF(P99=TRUE,C98+1,) -> 0 | E99: =IF(P99=TRUE,E98+F98,) -> 0 | N99: =ISTEXT(D99) -> FALSE | O99: =ISNUMBER(D99) -> FALSE | P99: =OR(N99=TRUE,O99=TRUE) -> FALSE

Sheet TV - Venta activos financieros
D2: Diseño de registro de datos fiscales y personales
D3: ='CONTROL DE VERSIONES'!G68 -> IRPF 2025
D4: Ventas de activos financieros y otros valores mobiliarios
C5: =IF(P5=TRUE,C4+1,) -> 0
C6: =IF(P6=TRUE,C5+1,) -> 0
C7: Este concepto de datos fiscales incluye los datos de las ventas de activos financieros y otros valores mobiliarios con origen en el Modelo 198
C9: Nº | D9: Nombre | E9: Posición | F9: Longitud | G9: Descripción
C10: =IF(P10=TRUE,1,) -> 1 | D10: Tipo | E10: =IF(P10=TRUE,1,) -> 1 | F10: 1 | G10: Tipo de registro = '2' | N10: =ISTEXT(D10) -> TRUE | O10: =ISNUMBER(D10) -> FALSE | P10: =OR(N10=TRUE,O10=TRUE) -> TRUE
C11: =IF(P11=TRUE,C10+1,) -> 2 | D11: Código | E11: =IF(P11=TRUE,E10+F10,) -> 2 | F11: 7 | G11: 'TVnnnnn' Donde nnnn es el número del registro de este tipo contenido en el fichero de datos fiscales. | N11: =ISTEXT(D11) -> TRUE | O11: =ISNUMBER(D11) -> FALSE | P11: =OR(N11=TRUE,O11=TRUE) -> TRUE
C12: =IF(P12=TRUE,C11+1,) -> 3 | D12: NIF del Emisor | E12: =IF(P12=TRUE,E11+F11,) -> 9 | F12: 9 | N12: =ISTEXT(D12) -> TRUE | O12: =ISNUMBER(D12) -> FALSE | P12: =OR(N12=TRUE,O12=TRUE) -> TRUE
C13: =IF(P13=TRUE,C12+1,) -> 4 | D13: Nombre del Emisor | E13: =IF(P13=TRUE,E12+F12,) -> 18 | F13: 40 | G13: Nombre de la Entidad | N13: =ISTEXT(D13) -> TRUE | O13: =ISNUMBER(D13) -> FALSE | P13: =OR(N13=TRUE,O13=TRUE) -> TRUE
C14: =IF(P14=TRUE,C13+1,) -> 5 | D14: NIF del Declarante | E14: =IF(P14=TRUE,E13+F13,) -> 58 | F14: 9 | N14: =ISTEXT(D14) -> TRUE | O14: =ISNUMBER(D14) -> FALSE | P14: =OR(N14=TRUE,O14=TRUE) -> TRUE
C15: =IF(P15=TRUE,C14+1,) -> 6 | D15: Nombre del Declarante | E15: =IF(P15=TRUE,E14+F14,) -> 67 | F15: 40 | N15: =ISTEXT(D15) -> TRUE | O15: =ISNUMBER(D15) -> FALSE | P15: =OR(N15=TRUE,O15=TRUE) -> TRUE
C16: =IF(P16=TRUE,C15+1,) -> 7 | D16: Fecha de la operación | E16: =IF(P16=TRUE,E15+F15,) -> 107 | F16: 8 | G16: AAAAMMDD (Formato de la fecha) | N16: =ISTEXT(D16) -> TRUE | O16: =ISNUMBER(D16) -> FALSE | P16: =OR(N16=TRUE,O16=TRUE) -> TRUE
C17: =IF(P17=TRUE,C16+1,) -> 8 | D17: Clave Mercado | E17: =IF(P17=TRUE,E16+F16,) -> 115 | F17: 1 | G17: Valor: ‘A’ - Mercado secundario oficial de valores español ‘B’ - Mercado secundario oficial de valores extranjeros de la UE ‘C’ - Otros mercados nacionales ‘D’ - Otros mercados extranjeros ‘F’ - Operaciones intervenidas por fedatarios públicos ‘O’ - Operaciones realizadas fuera de mercado (O.T.C.) ‘P’ - Mercado secundario de valores extranjeros (excluidos los de la UE) | N17: =ISTEXT(D17) -> TRUE | O17: =ISNUMBER(D17) -> FALSE | P17: =OR(N17=TRUE,O17=TRUE) -> TRUE
C18: =IF(P18=TRUE,C17+1,) -> 9 | D18: Valor | E18: =IF(P18=TRUE,E17+F17,) -> 116 | F18: 1 | G18: Valor: ‘A’ - Acciones ‘B’ - Rdtos. Explicitos ‘C’ - Rdtos. Implicitos ‘D’ - Ppal.Segreg. ‘E’ - Cupones ‘F’ - Der. Garantía ‘G’ - Der. Disfrute ‘I’ - Otros ‘J’ - CuponesRtos.E.Terr ‘K’ - Part. Prefer. ‘L’ - Contratos por diferencias ‘M’ - Part. I.I.C | N18: =ISTEXT(D18) -> TRUE | O18: =ISNUMBER(D18) -> FALSE | P18: =OR(N18=TRUE,O18=TRUE) -> TRUE
C19: =IF(P19=TRUE,C18+1,) -> 10 | D19: Número de titulares | E19: =IF(P19=TRUE,E18+F18,) -> 117 | F19: 3 | N19: =ISTEXT(D19) -> TRUE | O19: =ISNUMBER(D19) -> FALSE | P19: =OR(N19=TRUE,O19=TRUE) -> TRUE
C20: =IF(P20=TRUE,C19+1,) -> 11 | D20: Importe de la venta | E20: =IF(P20=TRUE,E19+F19,) -> 120 | F20: 15 | N20: =ISTEXT(D20) -> TRUE | O20: =ISNUMBER(D20) -> FALSE | P20: =OR(N20=TRUE,O20=TRUE) -> TRUE
C21: =IF(P21=TRUE,C20+1,) -> 12 | D21: Rendimientos | E21: =IF(P21=TRUE,E20+F20,) -> 135 | F21: 12 | G21: (Rendimiento + Compensación) | N21: =ISTEXT(D21) -> TRUE | O21: =ISNUMBER(D21) -> FALSE | P21: =OR(N21=TRUE,O21=TRUE) -> TRUE
C22: =IF(P22=TRUE,C21+1,) -> 13 | D22: Declarado | E22: =IF(P22=TRUE,E21+F21,) -> 147 | F22: 1 | G22: Valor: ‘B’ - Perceptor Part. Prefe. ‘C’ - Tercero ‘E’ - Entidad Central de Contrapartida ‘N’ - Nudo Propietario ‘P’ - Prestamista ‘Q’ - Prestatario ‘T’ - Titular ‘U’ - Usufructuario | N22: =ISTEXT(D22) -> TRUE | O22: =ISNUMBER(D22) -> FALSE | P22: =OR(N22=TRUE,O22=TRUE) -> TRUE
C23: =IF(P23=TRUE,C22+1,) -> 14 | D23: Gastos de la operación | E23: =IF(P23=TRUE,E22+F22,) -> 148 | F23: 12 | N23: =ISTEXT(D23) -> TRUE | O23: =ISNUMBER(D23) -> FALSE | P23: =OR(N23=TRUE,O23=TRUE) -> TRUE
C24: =IF(P24=TRUE,C23+1,) -> 0 | E24: =IF(P24=TRUE,E23+F23,) -> 0 | N24: =ISTEXT(D24) -> FALSE | O24: =ISNUMBER(D24) -> FALSE | P24: =OR(N24=TRUE,O24=TRUE) -> FALSE
C25: =IF(P25=TRUE,C24+1,) -> 0 | E25: =IF(P25=TRUE,E24+F24,) -> 0 | N25: =ISTEXT(D25) -> FALSE | O25: =ISNUMBER(D25) -> FALSE | P25: =OR(N25=TRUE,O25=TRUE) -> FALSE
C26: =IF(P26=TRUE,C25+1,) -> 0 | E26: =IF(P26=TRUE,E25+F25,) -> 0 | N26: =ISTEXT(D26) -> FALSE | O26: =ISNUMBER(D26) -> FALSE | P26: =OR(N26=TRUE,O26=TRUE) -> FALSE
C27: =IF(P27=TRUE,C26+1,) -> 0 | E27: =IF(P27=TRUE,E26+F26,) -> 0 | N27: =ISTEXT(D27) -> FALSE | O27: =ISNUMBER(D27) -> FALSE | P27: =OR(N27=TRUE,O27=TRUE) -> FALSE
C28: =IF(P28=TRUE,C27+1,) -> 0 | E28: =IF(P28=TRUE,E27+F27,) -> 0 | N28: =ISTEXT(D28) -> FALSE | O28: =ISNUMBER(D28) -> FALSE | P28: =OR(N28=TRUE,O28=TRUE) -> FALSE
C29: =IF(P29=TRUE,C28+1,) -> 0 | E29: =IF(P29=TRUE,E28+F28,) -> 0 | N29: =ISTEXT(D29) -> FALSE | O29: =ISNUMBER(D29) -> FALSE | P29: =OR(N29=TRUE,O29=TRUE) -> FALSE
C30: =IF(P30=TRUE,C29+1,) -> 0 | E30: =IF(P30=TRUE,E29+F29,) -> 0 | N30: =ISTEXT(D30) -> FALSE | O30: =ISNUMBER(D30) -> FALSE | P30: =OR(N30=TRUE,O30=TRUE) -> FALSE
C31: =IF(P31=TRUE,C30+1,) -> 0 | E31: =IF(P31=TRUE,E30+F30,) -> 0 | N31: =ISTEXT(D31) -> FALSE | O31: =ISNUMBER(D31) -> FALSE | P31: =OR(N31=TRUE,O31=TRUE) -> FALSE
C32: =IF(P32=TRUE,C31+1,) -> 0 | E32: =IF(P32=TRUE,E31+F31,) -> 0 | N32: =ISTEXT(D32) -> FALSE | O32: =ISNUMBER(D32) -> FALSE | P32: =OR(N32=TRUE,O32=TRUE) -> FALSE
C33: =IF(P33=TRUE,C32+1,) -> 0 | E33: =IF(P33=TRUE,E32+F32,) -> 0 | N33: =ISTEXT(D33) -> FALSE | O33: =ISNUMBER(D33) -> FALSE | P33: =OR(N33=TRUE,O33=TRUE) -> FALSE
C34: =IF(P34=TRUE,C33+1,) -> 0 | E34: =IF(P34=TRUE,E33+F33,) -> 0 | N34: =ISTEXT(D34) -> FALSE | O34: =ISNUMBER(D34) -> FALSE | P34: =OR(N34=TRUE,O34=TRUE) -> FALSE
C35: =IF(P35=TRUE,C34+1,) -> 0 | E35: =IF(P35=TRUE,E34+F34,) -> 0 | N35: =ISTEXT(D35) -> FALSE | O35: =ISNUMBER(D35) -> FALSE | P35: =OR(N35=TRUE,O35=TRUE) -> FALSE
... C99: =IF(P99=TRUE,C98+1,) -> 0 | E99: =IF(P99=TRUE,E98+F98,) -> 0 | N99: =ISTEXT(D99) -> FALSE | O99: =ISNUMBER(D99) -> FALSE | P99: =OR(N99=TRUE,O99=TRUE) -> FALSE

Sheet AR - Arrendamientos de locales
D2: Diseño de registro de datos fiscales y personales
D3: ='CONTROL DE VERSIONES'!G68 -> IRPF 2025
D4: Arrendamientos de locales
C5: =IF(P5=TRUE,C4+1,) -> 0
C6: =IF(P6=TRUE,C5+1,) -> 0
C7: Este concepto de datos fiscales incluye los arrendamientos de locales con origen en el Modelo 180
C9: Nº | D9: Nombre | E9: Posición | F9: Longitud | G9: Descripción
C10: =IF(P10=TRUE,1,) -> 1 | D10: Tipo | E10: =IF(P10=TRUE,1,) -> 1 | F10: 1 | G10: Tipo de registro = '2' | N10: =ISTEXT(D10) -> TRUE | O10: =ISNUMBER(D10) -> FALSE | P10: =OR(N10=TRUE,O10=TRUE) -> TRUE
C11: =IF(P11=TRUE,C10+1,) -> 2 | D11: Código | E11: =IF(P11=TRUE,E10+F10,) -> 2 | F11: 7 | G11: 'ARnnnnn' Donde nnnn es el número del registro de este tipo contenido en el fichero de datos fiscales. | N11: =ISTEXT(D11) -> TRUE | O11: =ISNUMBER(D11) -> FALSE | P11: =OR(N11=TRUE,O11=TRUE) -> TRUE
C12: =IF(P12=TRUE,C11+1,) -> 3 | D12: NIF del Pagador | E12: =IF(P12=TRUE,E11+F11,) -> 9 | F12: 9 | N12: =ISTEXT(D12) -> TRUE | O12: =ISNUMBER(D12) -> FALSE | P12: =OR(N12=TRUE,O12=TRUE) -> TRUE
C13: =IF(P13=TRUE,C12+1,) -> 4 | D13: Nombre del Pagador | E13: =IF(P13=TRUE,E12+F12,) -> 18 | F13: 40 | N13: =ISTEXT(D13) -> TRUE | O13: =ISNUMBER(D13) -> FALSE | P13: =OR(N13=TRUE,O13=TRUE) -> TRUE
C14: =IF(P14=TRUE,C13+1,) -> 5 | D14: Ref. Catastral | E14: =IF(P14=TRUE,E13+F13,) -> 58 | F14: 20 | N14: =ISTEXT(D14) -> TRUE | O14: =ISNUMBER(D14) -> FALSE | P14: =OR(N14=TRUE,O14=TRUE) -> TRUE
C15: =IF(P15=TRUE,C14+1,) -> 6 | D15: Clave | E15: =IF(P15=TRUE,E14+F14,) -> 78 | F15: 1 | G15: Claves: '1' - Dineraria '2' - En especie | N15: =ISTEXT(D15) -> TRUE | O15: =ISNUMBER(D15) -> FALSE | P15: =OR(N15=TRUE,O15=TRUE) -> TRUE
C16: =IF(P16=TRUE,C15+1,) -> 7 | D16: Ingresos | E16: =IF(P16=TRUE,E15+F15,) -> 79 | F16: 13 | G16: Si es En Especie: Retribución + ingreso a Cuenta | N16: =ISTEXT(D16) -> TRUE | O16: =ISNUMBER(D16) -> FALSE | P16: =OR(N16=TRUE,O16=TRUE) -> TRUE
C17: =IF(P17=TRUE,C16+1,) -> 8 | D17: Retención | E17: =IF(P17=TRUE,E16+F16,) -> 92 | F17: 13 | N17: =ISTEXT(D17) -> TRUE | O17: =ISNUMBER(D17) -> FALSE | P17: =OR(N17=TRUE,O17=TRUE) -> TRUE
C18: =IF(P18=TRUE,C17+1,) -> 0 | E18: =IF(P18=TRUE,E17+F17,) -> 0 | N18: =ISTEXT(D18) -> FALSE | O18: =ISNUMBER(D18) -> FALSE | P18: =OR(N18=TRUE,O18=TRUE) -> FALSE
C19: =IF(P19=TRUE,C18+1,) -> 0 | E19: =IF(P19=TRUE,E18+F18,) -> 0 | N19: =ISTEXT(D19) -> FALSE | O19: =ISNUMBER(D19) -> FALSE | P19: =OR(N19=TRUE,O19=TRUE) -> FALSE
C20: =IF(P20=TRUE,C19+1,) -> 0 | E20: =IF(P20=TRUE,E19+F19,) -> 0 | N20: =ISTEXT(D20) -> FALSE | O20: =ISNUMBER(D20) -> FALSE | P20: =OR(N20=TRUE,O20=TRUE) -> FALSE
C21: =IF(P21=TRUE,C20+1,) -> 0 | E21: =IF(P21=TRUE,E20+F20,) -> 0 | N21: =ISTEXT(D21) -> FALSE | O21: =ISNUMBER(D21) -> FALSE | P21: =OR(N21=TRUE,O21=TRUE) -> FALSE
C22: =IF(P22=TRUE,C21+1,) -> 0 | E22: =IF(P22=TRUE,E21+F21,) -> 0 | N22: =ISTEXT(D22) -> FALSE | O22: =ISNUMBER(D22) -> FALSE | P22: =OR(N22=TRUE,O22=TRUE) -> FALSE
C23: =IF(P23=TRUE,C22+1,) -> 0 | E23: =IF(P23=TRUE,E22+F22,) -> 0 | N23: =ISTEXT(D23) -> FALSE | O23: =ISNUMBER(D23) -> FALSE | P23: =OR(N23=TRUE,O23=TRUE) -> FALSE
C24: =IF(P24=TRUE,C23+1,) -> 0 | E24: =IF(P24=TRUE,E23+F23,) -> 0 | N24: =ISTEXT(D24) -> FALSE | O24: =ISNUMBER(D24) -> FALSE | P24: =OR(N24=TRUE,O24=TRUE) -> FALSE
C25: =IF(P25=TRUE,C24+1,) -> 0 | E25: =IF(P25=TRUE,E24+F24,) -> 0 | N25: =ISTEXT(D25) -> FALSE | O25: =ISNUMBER(D25) -> FALSE | P25: =OR(N25=TRUE,O25=TRUE) -> FALSE
C26: =IF(P26=TRUE,C25+1,) -> 0 | E26: =IF(P26=TRUE,E25+F25,) -> 0 | N26: =ISTEXT(D26) -> FALSE | O26: =ISNUMBER(D26) -> FALSE | P26: =OR(N26=TRUE,O26=TRUE) -> FALSE
C27: =IF(P27=TRUE,C26+1,) -> 0 | E27: =IF(P27=TRUE,E26+F26,) -> 0 | N27: =ISTEXT(D27) -> FALSE | O27: =ISNUMBER(D27) -> FALSE | P27: =OR(N27=TRUE,O27=TRUE) -> FALSE
C28: =IF(P28=TRUE,C27+1,) -> 0 | E28: =IF(P28=TRUE,E27+F27,) -> 0 | N28: =ISTEXT(D28) -> FALSE | O28: =ISNUMBER(D28) -> FALSE | P28: =OR(N28=TRUE,O28=TRUE) -> FALSE
C29: =IF(P29=TRUE,C28+1,) -> 0 | E29: =IF(P29=TRUE,E28+F28,) -> 0 | N29: =ISTEXT(D29) -> FALSE | O29: =ISNUMBER(D29) -> FALSE | P29: =OR(N29=TRUE,O29=TRUE) -> FALSE
... C99: =IF(P99=TRUE,C98+1,) -> 0 | E99: =IF(P99=TRUE,E98+F98,) -> 0 | N99: =ISTEXT(D99) -> FALSE | O99: =ISNUMBER(D99) -> FALSE | P99: =OR(N99=TRUE,O99=TRUE) -> FALSE

Sheet CT - Cotizaciones Autonomos
D2: Diseño de registro de datos fiscales y personales
D3: ='CONTROL DE VERSIONES'!G68 -> IRPF 2025
D4: Cotizaciones de autónomos
C5: =IF(P5=TRUE,C4+1,) -> 0
C6: =IF(P6=TRUE,C5+1,) -> 0
C7: Este concepto de datos fiscales incluye las cotizaciones del régimen especial de autónomos. Siempre hay que comprobar que las cotizaciones a la Seguridad Social como autónomo no se han duplicado, incluyéndose como gastos de Seguridad Social de los rendimientos del trabajo del Modelo 190.
C9: Nº | D9: Nombre | E9: Posición | F9: Longitud | G9: Descripción
C10: =IF(P10=TRUE,1,) -> 1 | D10: Tipo | E10: =IF(P10=TRUE,1,) -> 1 | F10: 1 | G10: Tipo de registro = '2' | N10: =ISTEXT(D10) -> TRUE | O10: =ISNUMBER(D10) -> FALSE | P10: =OR(N10=TRUE,O10=TRUE) -> TRUE
C11: =IF(P11=TRUE,C10+1,) -> 2 | D11: Código | E11: =IF(P11=TRUE,E10+F10,) -> 2 | F11: 7 | G11: 'CTnnnnn' Donde nnnn es el número del registro de este tipo contenido en el fichero de datos fiscales. | N11: =ISTEXT(D11) -> TRUE | O11: =ISNUMBER(D11) -> FALSE | P11: =OR(N11=TRUE,O11=TRUE) -> TRUE
C12: =IF(P12=TRUE,C11+1,) -> 3 | D12: Número de afiliación | E12: =IF(P12=TRUE,E11+F11,) -> 9 | F12: 12 | N12: =ISTEXT(D12) -> TRUE | O12: =ISNUMBER(D12) -> FALSE | P12: =OR(N12=TRUE,O12=TRUE) -> TRUE
C13: =IF(P13=TRUE,C12+1,) -> 4 | D13: Reg de cotización | E13: =IF(P13=TRUE,E12+F12,) -> 21 | F13: 4 | G13: Regímenes: 0138 - Régimen General de Empleados del Hogar 0140 - Régimen General (Conv. Esp.) 0161 - Régimen General Agrario 0521 - Reg. Esp. Trabajadores Autónomos 0540 - Reg.Espe Autónomos (Conv.Esp.) 0825 - Reg. Especial del Mar (Autónomos) 0840 - Reg. Especial del Mar (Conv.Esp.) 0940 - Reg. Esp. Minería del Carbón (Conv. Esp.) 1211 - Reg. Esp. de empleados del hogar (Fijos) | N13: =ISTEXT(D13) -> TRUE | O13: =ISNUMBER(D13) -> FALSE | P13: =OR(N13=TRUE,O13=TRUE) -> TRUE
C14: =IF(P14=TRUE,C13+1,) -> 5 | D14: Importe | E14: =IF(P14=TRUE,E13+F13,) -> 25 | F14: 17 | N14: =ISTEXT(D14) -> TRUE | O14: =ISNUMBER(D14) -> FALSE | P14: =OR(N14=TRUE,O14=TRUE) -> TRUE
C15: =IF(P15=TRUE,C14+1,) -> 0 | E15: =IF(P15=TRUE,E14+F14,) -> 0 | N15: =ISTEXT(D15) -> FALSE | O15: =ISNUMBER(D15) -> FALSE | P15: =OR(N15=TRUE,O15=TRUE) -> FALSE
C16: =IF(P16=TRUE,C15+1,) -> 0 | E16: =IF(P16=TRUE,E15+F15,) -> 0 | N16: =ISTEXT(D16) -> FALSE | O16: =ISNUMBER(D16) -> FALSE | P16: =OR(N16=TRUE,O16=TRUE) -> FALSE
C17: =IF(P17=TRUE,C16+1,) -> 0 | E17: =IF(P17=TRUE,E16+F16,) -> 0 | N17: =ISTEXT(D17) -> FALSE | O17: =ISNUMBER(D17) -> FALSE | P17: =OR(N17=TRUE,O17=TRUE) -> FALSE
C18: =IF(P18=TRUE,C17+1,) -> 0 | E18: =IF(P18=TRUE,E17+F17,) -> 0 | N18: =ISTEXT(D18) -> FALSE | O18: =ISNUMBER(D18) -> FALSE | P18: =OR(N18=TRUE,O18=TRUE) -> FALSE
C19: =IF(P19=TRUE,C18+1,) -> 0 | E19: =IF(P19=TRUE,E18+F18,) -> 0 | N19: =ISTEXT(D19) -> FALSE | O19: =ISNUMBER(D19) -> FALSE | P19: =OR(N19=TRUE,O19=TRUE) -> FALSE
C20: =IF(P20=TRUE,C19+1,) -> 0 | E20: =IF(P20=TRUE,E19+F19,) -> 0 | N20: =ISTEXT(D20) -> FALSE | O20: =ISNUMBER(D20) -> FALSE | P20: =OR(N20=TRUE,O20=TRUE) -> FALSE
C21: =IF(P21=TRUE,C20+1,) -> 0 | E21: =IF(P21=TRUE,E20+F20,) -> 0 | N21: =ISTEXT(D21) -> FALSE | O21: =ISNUMBER(D21) -> FALSE | P21: =OR(N21=TRUE,O21=TRUE) -> FALSE
C22: =IF(P22=TRUE,C21+1,) -> 0 | E22: =IF(P22=TRUE,E21+F21,) -> 0 | N22: =ISTEXT(D22) -> FALSE | O22: =ISNUMBER(D22) -> FALSE | P22: =OR(N22=TRUE,O22=TRUE) -> FALSE
C23: =IF(P23=TRUE,C22+1,) -> 0 | E23: =IF(P23=TRUE,E22+F22,) -> 0 | N23: =ISTEXT(D23) -> FALSE | O23: =ISNUMBER(D23) -> FALSE | P23: =OR(N23=TRUE,O23=TRUE) -> FALSE
C24: =IF(P24=TRUE,C23+1,) -> 0 | E24: =IF(P24=TRUE,E23+F23,) -> 0 | N24: =ISTEXT(D24) -> FALSE | O24: =ISNUMBER(D24) -> FALSE | P24: =OR(N24=TRUE,O24=TRUE) -> FALSE
C25: =IF(P25=TRUE,C24+1,) -> 0 | E25: =IF(P25=TRUE,E24+F24,) -> 0 | N25: =ISTEXT(D25) -> FALSE | O25: =ISNUMBER(D25) -> FALSE | P25: =OR(N25=TRUE,O25=TRUE) -> FALSE
C26: =IF(P26=TRUE,C25+1,) -> 0 | E26: =IF(P26=TRUE,E25+F25,) -> 0 | N26: =ISTEXT(D26) -> FALSE | O26: =ISNUMBER(D26) -> FALSE | P26: =OR(N26=TRUE,O26=TRUE) -> FALSE
... C99: =IF(P99=TRUE,C98+1,) -> 0 | E99: =IF(P99=TRUE,E98+F98,) -> 0 | N99: =ISTEXT(D99) -> FALSE | O99: =ISNUMBER(D99) -> FALSE | P99: =OR(N99=TRUE,O99=TRUE) -> FALSE

Sheet AG - Subvenciones agricultores
D2: Diseño de registro de datos fiscales y personales
D3: ='CONTROL DE VERSIONES'!G68 -> IRPF 2025
D4: Subvenciones o indemnizaciones a agricultores, ganaderos o forestales
C5: =IF(P5=TRUE,C4+1,) -> 0
C6: =IF(P6=TRUE,C5+1,) -> 0
C7: Este concepto de datos fiscales incluye las subvenciones o indemnizaciones concedidas a agricultores, ganaderos o forestales con origen en el Modelo 346
C9: Nº | D9: Nombre | E9: Posición | F9: Longitud | G9: Descripción
C10: =IF(P10=TRUE,1,) -> 1 | D10: Tipo | E10: =IF(P10=TRUE,1,) -> 1 | F10: 1 | G10: Tipo de registro = '2' | N10: =ISTEXT(D10) -> TRUE | O10: =ISNUMBER(D10) -> FALSE | P10: =OR(N10=TRUE,O10=TRUE) -> TRUE
C11: =IF(P11=TRUE,C10+1,) -> 2 | D11: Código | E11: =IF(P11=TRUE,E10+F10,) -> 2 | F11: 7 | G11: 'AGnnnnn' Donde nnnn es el número del registro de este tipo contenido en el fichero de datos fiscales. | N11: =ISTEXT(D11) -> TRUE | O11: =ISNUMBER(D11) -> FALSE | P11: =OR(N11=TRUE,O11=TRUE) -> TRUE
C12: =IF(P12=TRUE,C11+1,) -> 3 | D12: NIF del Declarante | E12: =IF(P12=TRUE,E11+F11,) -> 9 | F12: 9 | N12: =ISTEXT(D12) -> TRUE | O12: =ISNUMBER(D12) -> FALSE | P12: =OR(N12=TRUE,O12=TRUE) -> TRUE
C13: =IF(P13=TRUE,C12+1,) -> 4 | D13: Nombre del Declarante | E13: =IF(P13=TRUE,E12+F12,) -> 18 | F13: 40 | N13: =ISTEXT(D13) -> TRUE | O13: =ISNUMBER(D13) -> FALSE | P13: =OR(N13=TRUE,O13=TRUE) -> TRUE
C14: =IF(P14=TRUE,C13+1,) -> 5 | D14: Tipo | E14: =IF(P14=TRUE,E13+F13,) -> 58 | F14: 1 | G14: Tipos: ‘1’ - Corrientes ‘2’ - De capital ‘3’ - Indem. Circ ‘4’ - Indem. Inm. ‘5’ - Cese activ. ‘6’ - Otras | N14: =ISTEXT(D14) -> TRUE | O14: =ISNUMBER(D14) -> FALSE | P14: =OR(N14=TRUE,O14=TRUE) -> TRUE
C15: =IF(P15=TRUE,C14+1,) -> 6 | D15: Concepto | E15: =IF(P15=TRUE,E14+F14,) -> 59 | F15: 50 | N15: =ISTEXT(D15) -> TRUE | O15: =ISNUMBER(D15) -> FALSE | P15: =OR(N15=TRUE,O15=TRUE) -> TRUE
C16: =IF(P16=TRUE,C15+1,) -> 7 | D16: Importe | E16: =IF(P16=TRUE,E15+F15,) -> 109 | F16: 15 | N16: =ISTEXT(D16) -> TRUE | O16: =ISNUMBER(D16) -> FALSE | P16: =OR(N16=TRUE,O16=TRUE) -> TRUE
C17: =IF(P17=TRUE,C16+1,) -> 0 | E17: =IF(P17=TRUE,E16+F16,) -> 0 | N17: =ISTEXT(D17) -> FALSE | O17: =ISNUMBER(D17) -> FALSE | P17: =OR(N17=TRUE,O17=TRUE) -> FALSE
C18: =IF(P18=TRUE,C17+1,) -> 0 | E18: =IF(P18=TRUE,E17+F17,) -> 0 | N18: =ISTEXT(D18) -> FALSE | O18: =ISNUMBER(D18) -> FALSE | P18: =OR(N18=TRUE,O18=TRUE) -> FALSE
C19: =IF(P19=TRUE,C18+1,) -> 0 | E19: =IF(P19=TRUE,E18+F18,) -> 0 | N19: =ISTEXT(D19) -> FALSE | O19: =ISNUMBER(D19) -> FALSE | P19: =OR(N19=TRUE,O19=TRUE) -> FALSE
C20: =IF(P20=TRUE,C19+1,) -> 0 | E20: =IF(P20=TRUE,E19+F19,) -> 0 | N20: =ISTEXT(D20) -> FALSE | O20: =ISNUMBER(D20) -> FALSE | P20: =OR(N20=TRUE,O20=TRUE) -> FALSE
C21: =IF(P21=TRUE,C20+1,) -> 0 | E21: =IF(P21=TRUE,E20+F20,) -> 0 | N21: =ISTEXT(D21) -> FALSE | O21: =ISNUMBER(D21) -> FALSE | P21: =OR(N21=TRUE,O21=TRUE) -> FALSE
C22: =IF(P22=TRUE,C21+1,) -> 0 | E22: =IF(P22=TRUE,E21+F21,) -> 0 | N22: =ISTEXT(D22) -> FALSE | O22: =ISNUMBER(D22) -> FALSE | P22: =OR(N22=TRUE,O22=TRUE) -> FALSE
C23: =IF(P23=TRUE,C22+1,) -> 0 | E23: =IF(P23=TRUE,E22+F22,) -> 0 | N23: =ISTEXT(D23) -> FALSE | O23: =ISNUMBER(D23) -> FALSE | P23: =OR(N23=TRUE,O23=TRUE) -> FALSE
C24: =IF(P24=TRUE,C23+1,) -> 0 | E24: =IF(P24=TRUE,E23+F23,) -> 0 | N24: =ISTEXT(D24) -> FALSE | O24: =ISNUMBER(D24) -> FALSE | P24: =OR(N24=TRUE,O24=TRUE) -> FALSE
C25: =IF(P25=TRUE,C24+1,) -> 0 | E25: =IF(P25=TRUE,E24+F24,) -> 0 | N25: =ISTEXT(D25) -> FALSE | O25: =ISNUMBER(D25) -> FALSE | P25: =OR(N25=TRUE,O25=TRUE) -> FALSE
C26: =IF(P26=TRUE,C25+1,) -> 0 | E26: =IF(P26=TRUE,E25+F25,) -> 0 | N26: =ISTEXT(D26) -> FALSE | O26: =ISNUMBER(D26) -> FALSE | P26: =OR(N26=TRUE,O26=TRUE) -> FALSE
C27: =IF(P27=TRUE,C26+1,) -> 0 | E27: =IF(P27=TRUE,E26+F26,) -> 0 | N27: =ISTEXT(D27) -> FALSE | O27: =ISNUMBER(D27) -> FALSE | P27: =OR(N27=TRUE,O27=TRUE) -> FALSE
C28: =IF(P28=TRUE,C27+1,) -> 0 | E28: =IF(P28=TRUE,E27+F27,) -> 0 | N28: =ISTEXT(D28) -> FALSE | O28: =ISNUMBER(D28) -> FALSE | P28: =OR(N28=TRUE,O28=TRUE) -> FALSE
... C99: =IF(P99=TRUE,C98+1,) -> 0 | E99: =IF(P99=TRUE,E98+F98,) -> 0 | N99: =ISTEXT(D99) -> FALSE | O99: =ISNUMBER(D99) -> FALSE | P99: =OR(N99=TRUE,O99=TRUE) -> FALSE

Sheet IP - Otras subvenciones
D2: Diseño de registro de datos fiscales y personales
D3: ='CONTROL DE VERSIONES'!G68 -> IRPF 2025
D4: Otras subvenciones y ayudas por las administraciones públicas
C5: =IF(P5=TRUE,C4+1,) -> 0
C6: =IF(P6=TRUE,C5+1,) -> 0
C7: Este concepto de datos fiscales incluye los datos de otras subvenciones y ayudas concedidas por las diferentes administraciones públicas con origen en el Modelo 347
C9: Nº | D9: Nombre | E9: Posición | F9: Longitud | G9: Descripción
C10: =IF(P10=TRUE,1,) -> 1 | D10: Tipo | E10: =IF(P10=TRUE,1,) -> 1 | F10: 1 | G10: Tipo de registro = '2' | N10: =ISTEXT(D10) -> TRUE | O10: =ISNUMBER(D10) -> FALSE | P10: =OR(N10=TRUE,O10=TRUE) -> TRUE
C11: =IF(P11=TRUE,C10+1,) -> 2 | D11: Código | E11: =IF(P11=TRUE,E10+F10,) -> 2 | F11: 7 | G11: 'IPnnnnn' Donde nnnn es el número del registro de este tipo contenido en el fichero de datos fiscales. | N11: =ISTEXT(D11) -> TRUE | O11: =ISNUMBER(D11) -> FALSE | P11: =OR(N11=TRUE,O11=TRUE) -> TRUE
C12: =IF(P12=TRUE,C11+1,) -> 3 | D12: NIF del Declarante | E12: =IF(P12=TRUE,E11+F11,) -> 9 | F12: 9 | N12: =ISTEXT(D12) -> TRUE | O12: =ISNUMBER(D12) -> FALSE | P12: =OR(N12=TRUE,O12=TRUE) -> TRUE
C13: =IF(P13=TRUE,C12+1,) -> 4 | D13: Nombre del Declarante | E13: =IF(P13=TRUE,E12+F12,) -> 18 | F13: 40 | N13: =ISTEXT(D13) -> TRUE | O13: =ISNUMBER(D13) -> FALSE | P13: =OR(N13=TRUE,O13=TRUE) -> TRUE
C14: =IF(P14=TRUE,C13+1,) -> 5 | D14: Importe | E14: =IF(P14=TRUE,E13+F13,) -> 58 | F14: 13 | N14: =ISTEXT(D14) -> TRUE | O14: =ISNUMBER(D14) -> FALSE | P14: =OR(N14=TRUE,O14=TRUE) -> TRUE
C15: =IF(P15=TRUE,C14+1,) -> 6 | D15: Conv. BDNS | E15: =IF(P15=TRUE,E14+F14,) -> 71 | F15: 6 | N15: =ISTEXT(D15) -> TRUE | O15: =ISNUMBER(D15) -> FALSE | P15: =OR(N15=TRUE,O15=TRUE) -> TRUE
C16: =IF(P16=TRUE,C15+1,) -> 0 | E16: =IF(P16=TRUE,E15+F15,) -> 0 | N16: =ISTEXT(D16) -> FALSE | O16: =ISNUMBER(D16) -> FALSE | P16: =OR(N16=TRUE,O16=TRUE) -> FALSE
C17: =IF(P17=TRUE,C16+1,) -> 0 | E17: =IF(P17=TRUE,E16+F16,) -> 0 | N17: =ISTEXT(D17) -> FALSE | O17: =ISNUMBER(D17) -> FALSE | P17: =OR(N17=TRUE,O17=TRUE) -> FALSE
C18: =IF(P18=TRUE,C17+1,) -> 0 | E18: =IF(P18=TRUE,E17+F17,) -> 0 | N18: =ISTEXT(D18) -> FALSE | O18: =ISNUMBER(D18) -> FALSE | P18: =OR(N18=TRUE,O18=TRUE) -> FALSE
C19: =IF(P19=TRUE,C18+1,) -> 0 | E19: =IF(P19=TRUE,E18+F18,) -> 0 | N19: =ISTEXT(D19) -> FALSE | O19: =ISNUMBER(D19) -> FALSE | P19: =OR(N19=TRUE,O19=TRUE) -> FALSE
C20: =IF(P20=TRUE,C19+1,) -> 0 | E20: =IF(P20=TRUE,E19+F19,) -> 0 | N20: =ISTEXT(D20) -> FALSE | O20: =ISNUMBER(D20) -> FALSE | P20: =OR(N20=TRUE,O20=TRUE) -> FALSE
C21: =IF(P21=TRUE,C20+1,) -> 0 | E21: =IF(P21=TRUE,E20+F20,) -> 0 | N21: =ISTEXT(D21) -> FALSE | O21: =ISNUMBER(D21) -> FALSE | P21: =OR(N21=TRUE,O21=TRUE) -> FALSE
C22: =IF(P22=TRUE,C21+1,) -> 0 | E22: =IF(P22=TRUE,E21+F21,) -> 0 | N22: =ISTEXT(D22) -> FALSE | O22: =ISNUMBER(D22) -> FALSE | P22: =OR(N22=TRUE,O22=TRUE) -> FALSE
C23: =IF(P23=TRUE,C22+1,) -> 0 | E23: =IF(P23=TRUE,E22+F22,) -> 0 | N23: =ISTEXT(D23) -> FALSE | O23: =ISNUMBER(D23) -> FALSE | P23: =OR(N23=TRUE,O23=TRUE) -> FALSE
C24: =IF(P24=TRUE,C23+1,) -> 0 | E24: =IF(P24=TRUE,E23+F23,) -> 0 | N24: =ISTEXT(D24) -> FALSE | O24: =ISNUMBER(D24) -> FALSE | P24: =OR(N24=TRUE,O24=TRUE) -> FALSE
C25: =IF(P25=TRUE,C24+1,) -> 0 | E25: =IF(P25=TRUE,E24+F24,) -> 0 | N25: =ISTEXT(D25) -> FALSE | O25: =ISNUMBER(D25) -> FALSE | P25: =OR(N25=TRUE,O25=TRUE) -> FALSE
C26: =IF(P26=TRUE,C25+1,) -> 0 | E26: =IF(P26=TRUE,E25+F25,) -> 0 | N26: =ISTEXT(D26) -> FALSE | O26: =ISNUMBER(D26) -> FALSE | P26: =OR(N26=TRUE,O26=TRUE) -> FALSE
C27: =IF(P27=TRUE,C26+1,) -> 0 | E27: =IF(P27=TRUE,E26+F26,) -> 0 | N27: =ISTEXT(D27) -> FALSE | O27: =ISNUMBER(D27) -> FALSE | P27: =OR(N27=TRUE,O27=TRUE) -> FALSE
... C99: =IF(P99=TRUE,C98+1,) -> 0 | E99: =IF(P99=TRUE,E98+F98,) -> 0 | N99: =ISTEXT(D99) -> FALSE | O99: =ISNUMBER(D99) -> FALSE | P99: =OR(N99=TRUE,O99=TRUE) -> FALSE

Sheet SB - Subvenc. B.Datos Nacional
D2: Diseño de registro de datos fiscales y personales
D3: ='CONTROL DE VERSIONES'!G68 -> IRPF 2025
D4: Subvenciones recogidas en la Base de Datos Nacional de Subvenciones (BDNS)
C5: =IF(P5=TRUE,C4+1,) -> 0
C6: =IF(P6=TRUE,C5+1,) -> 0
C7: Este concepto de datos fiscales incluye los datos recogidos en la Base de Datos Nacional de Subvenciones (BDNS) Importante: Los datos que figuran en este apartado podrían aparecer también en el apartado de “Rendimientos del Trabajo” (información recibida del Modelo 190 presentado por el pagador) o en el de “Otras subvenciones, auxilios y ayudas satisfechos por las Administraciones Públicas” (información recibida del Modelo 347 presentado por el pagador).
C9: Nº | D9: Nombre | E9: Posición | F9: Longitud | G9: Descripción
C10: =IF(P10=TRUE,1,) -> 1 | D10: Tipo | E10: =IF(P10=TRUE,1,) -> 1 | F10: 1 | G10: Tipo de registro = '2' | N10: =ISTEXT(D10) -> TRUE | O10: =ISNUMBER(D10) -> FALSE | P10: =OR(N10=TRUE,O10=TRUE) -> TRUE
C11: =IF(P11=TRUE,C10+1,) -> 2 | D11: Código | E11: =IF(P11=TRUE,E10+F10,) -> 2 | F11: 7 | G11: 'SBnnnnn' Donde nnnn es el número del registro de este tipo contenido en el fichero de datos fiscales. | N11: =ISTEXT(D11) -> TRUE | O11: =ISNUMBER(D11) -> FALSE | P11: =OR(N11=TRUE,O11=TRUE) -> TRUE
C12: =IF(P12=TRUE,C11+1,) -> 3 | D12: Órgano Gestor | E12: =IF(P12=TRUE,E11+F11,) -> 9 | F12: 45 | G12: 45 primeras posiciones de la denominación del organo gestor de la subvención | H12: , | N12: =ISTEXT(D12) -> TRUE | O12: =ISNUMBER(D12) -> FALSE | P12: =OR(N12=TRUE,O12=TRUE) -> TRUE
C13: =IF(P13=TRUE,C12+1,) -> 4 | D13: Tipo de operación | E13: =IF(P13=TRUE,E12+F12,) -> 54 | F13: 2 | G13: Valor: 'PA' - Pago de concesiones a beneficiarios 'DE' - Devoluciones voluntarias 'RE' - Resolución del procedimiento de reintegro procedente | N13: =ISTEXT(D13) -> TRUE | O13: =ISNUMBER(D13) -> FALSE | P13: =OR(N13=TRUE,O13=TRUE) -> TRUE
C14: =IF(P14=TRUE,C13+1,) -> 5 | D14: Importe | E14: =IF(P14=TRUE,E13+F13,) -> 56 | F14: 13 | N14: =ISTEXT(D14) -> TRUE | O14: =ISNUMBER(D14) -> FALSE | P14: =OR(N14=TRUE,O14=TRUE) -> TRUE
C15: =IF(P15=TRUE,C14+1,) -> 6 | D15: Concepto | E15: =IF(P15=TRUE,E14+F14,) -> 69 | F15: 46 | N15: =ISTEXT(D15) -> TRUE | O15: =ISNUMBER(D15) -> FALSE | P15: =OR(N15=TRUE,O15=TRUE) -> TRUE
C16: =IF(P16=TRUE,C15+1,) -> 7 | D16: Posiciones reservadas para la AEAT | E16: =IF(P16=TRUE,E15+F15,) -> 115 | F16: 2 | N16: =ISTEXT(D16) -> TRUE | O16: =ISNUMBER(D16) -> FALSE | P16: =OR(N16=TRUE,O16=TRUE) -> TRUE
C17: =IF(P17=TRUE,C16+1,) -> 8 | D17: Conv. BDNS | E17: =IF(P17=TRUE,E16+F16,) -> 117 | F17: 18 | N17: =ISTEXT(D17) -> TRUE | O17: =ISNUMBER(D17) -> FALSE | P17: =OR(N17=TRUE,O17=TRUE) -> TRUE
C18: =IF(P18=TRUE,C17+1,) -> 0 | E18: =IF(P18=TRUE,E17+F17,) -> 0 | N18: =ISTEXT(D18) -> FALSE | O18: =ISNUMBER(D18) -> FALSE | P18: =OR(N18=TRUE,O18=TRUE) -> FALSE
C19: =IF(P19=TRUE,C18+1,) -> 0 | E19: =IF(P19=TRUE,E18+F18,) -> 0 | N19: =ISTEXT(D19) -> FALSE | O19: =ISNUMBER(D19) -> FALSE | P19: =OR(N19=TRUE,O19=TRUE) -> FALSE
C20: =IF(P20=TRUE,C19+1,) -> 0 | E20: =IF(P20=TRUE,E19+F19,) -> 0 | N20: =ISTEXT(D20) -> FALSE | O20: =ISNUMBER(D20) -> FALSE | P20: =OR(N20=TRUE,O20=TRUE) -> FALSE
C21: =IF(P21=TRUE,C20+1,) -> 0 | E21: =IF(P21=TRUE,E20+F20,) -> 0 | N21: =ISTEXT(D21) -> FALSE | O21: =ISNUMBER(D21) -> FALSE | P21: =OR(N21=TRUE,O21=TRUE) -> FALSE
C22: =IF(P22=TRUE,C21+1,) -> 0 | E22: =IF(P22=TRUE,E21+F21,) -> 0 | N22: =ISTEXT(D22) -> FALSE | O22: =ISNUMBER(D22) -> FALSE | P22: =OR(N22=TRUE,O22=TRUE) -> FALSE
C23: =IF(P23=TRUE,C22+1,) -> 0 | E23: =IF(P23=TRUE,E22+F22,) -> 0 | N23: =ISTEXT(D23) -> FALSE | O23: =ISNUMBER(D23) -> FALSE | P23: =OR(N23=TRUE,O23=TRUE) -> FALSE
C24: =IF(P24=TRUE,C23+1,) -> 0 | E24: =IF(P24=TRUE,E23+F23,) -> 0 | N24: =ISTEXT(D24) -> FALSE | O24: =ISNUMBER(D24) -> FALSE | P24: =OR(N24=TRUE,O24=TRUE) -> FALSE
C25: =IF(P25=TRUE,C24+1,) -> 0 | E25: =IF(P25=TRUE,E24+F24,) -> 0 | N25: =ISTEXT(D25) -> FALSE | O25: =ISNUMBER(D25) -> FALSE | P25: =OR(N25=TRUE,O25=TRUE) -> FALSE
C26: =IF(P26=TRUE,C25+1,) -> 0 | E26: =IF(P26=TRUE,E25+F25,) -> 0 | N26: =ISTEXT(D26) -> FALSE | O26: =ISNUMBER(D26) -> FALSE | P26: =OR(N26=TRUE,O26=TRUE) -> FALSE
C27: =IF(P27=TRUE,C26+1,) -> 0 | E27: =IF(P27=TRUE,E26+F26,) -> 0 | N27: =ISTEXT(D27) -> FALSE | O27: =ISNUMBER(D27) -> FALSE | P27: =OR(N27=TRUE,O27=TRUE) -> FALSE
C28: =IF(P28=TRUE,C27+1,) -> 0 | E28: =IF(P28=TRUE,E27+F27,) -> 0 | N28: =ISTEXT(D28) -> FALSE | O28: =ISNUMBER(D28) -> FALSE | P28: =OR(N28=TRUE,O28=TRUE) -> FALSE
C29: =IF(P29=TRUE,C28+1,) -> 0 | E29: =IF(P29=TRUE,E28+F28,) -> 0 | N29: =ISTEXT(D29) -> FALSE | O29: =ISNUMBER(D29) -> FALSE | P29: =OR(N29=TRUE,O29=TRUE) -> FALSE
... C99: =IF(P99=TRUE,C98+1,) -> 0 | E99: =IF(P99=TRUE,E98+F98,) -> 0 | N99: =ISTEXT(D99) -> FALSE | O99: =ISNUMBER(D99) -> FALSE | P99: =OR(N99=TRUE,O99=TRUE) -> FALSE

Sheet EAA - Atribuc.rdtos cap. mob
D2: Diseño de registro de datos fiscales y personales
D3: ='CONTROL DE VERSIONES'!G68 -> IRPF 2025
D4: Atribución de rendimientos del capital mobiliario
C5: =IF(P5=TRUE,C4+1,) -> 0
C6: =IF(P6=TRUE,C5+1,) -> 0
C7: Este concepto de datos fiscales incluye la atribución de rendimientos de capital mobiliario con origen en el Modelo 184
C9: Nº | D9: Nombre | E9: Posición | F9: Longitud | G9: Descripción
C10: =IF(P10=TRUE,1,) -> 1 | D10: Tipo | E10: =IF(P10=TRUE,1,) -> 1 | F10: 1 | G10: Tipo de registro = '2' | N10: =ISTEXT(D10) -> TRUE | O10: =ISNUMBER(D10) -> FALSE | P10: =OR(N10=TRUE,O10=TRUE) -> TRUE
C11: =IF(P11=TRUE,C10+1,) -> 2 | D11: Código | E11: =IF(P11=TRUE,E10+F10,) -> 2 | F11: 7 | G11: 'EAAnnnn' Donde nnnn es el número del registro de este tipo contenido en el fichero de datos fiscales. | N11: =ISTEXT(D11) -> TRUE | O11: =ISNUMBER(D11) -> FALSE | P11: =OR(N11=TRUE,O11=TRUE) -> TRUE
C12: =IF(P12=TRUE,C11+1,) -> 3 | D12: NIF del Declarante | E12: =IF(P12=TRUE,E11+F11,) -> 9 | F12: 9 | N12: =ISTEXT(D12) -> TRUE | O12: =ISNUMBER(D12) -> FALSE | P12: =OR(N12=TRUE,O12=TRUE) -> TRUE
C13: =IF(P13=TRUE,C12+1,) -> 4 | D13: Nombre del Declarante | E13: =IF(P13=TRUE,E12+F12,) -> 18 | F13: 40 | N13: =ISTEXT(D13) -> TRUE | O13: =ISNUMBER(D13) -> FALSE | P13: =OR(N13=TRUE,O13=TRUE) -> TRUE
C14: =IF(P14=TRUE,C13+1,) -> 5 | D14: % de participación | E14: =IF(P14=TRUE,E13+F13,) -> 58 | F14: 7 | G14: Tres enteros y cuatro decimales | N14: =ISTEXT(D14) -> TRUE | O14: =ISNUMBER(D14) -> FALSE | P14: =OR(N14=TRUE,O14=TRUE) -> TRUE
C15: =IF(P15=TRUE,C14+1,) -> 6 | D15: Subclave | E15: =IF(P15=TRUE,E14+F14,) -> 65 | F15: 2 | G15: Subclaves: '01' - Ley IRPF art.25 apartados 1,2 y 3 '02' - Ley IRPF art. 25 apartado 4 | N15: =ISTEXT(D15) -> TRUE | O15: =ISNUMBER(D15) -> FALSE | P15: =OR(N15=TRUE,O15=TRUE) -> TRUE
C16: =IF(P16=TRUE,C15+1,) -> 7 | D16: Importe | E16: =IF(P16=TRUE,E15+F15,) -> 67 | F16: 13 | N16: =ISTEXT(D16) -> TRUE | O16: =ISNUMBER(D16) -> FALSE | P16: =OR(N16=TRUE,O16=TRUE) -> TRUE
C17: =IF(P17=TRUE,C16+1,) -> 8 | D17: Reducción | E17: =IF(P17=TRUE,E16+F16,) -> 80 | F17: 11 | N17: =ISTEXT(D17) -> TRUE | O17: =ISNUMBER(D17) -> FALSE | P17: =OR(N17=TRUE,O17=TRUE) -> TRUE
C18: =IF(P18=TRUE,C17+1,) -> 0 | E18: =IF(P18=TRUE,E17+F17,) -> 0 | N18: =ISTEXT(D18) -> FALSE | O18: =ISNUMBER(D18) -> FALSE | P18: =OR(N18=TRUE,O18=TRUE) -> FALSE
C19: =IF(P19=TRUE,C18+1,) -> 0 | E19: =IF(P19=TRUE,E18+F18,) -> 0 | N19: =ISTEXT(D19) -> FALSE | O19: =ISNUMBER(D19) -> FALSE | P19: =OR(N19=TRUE,O19=TRUE) -> FALSE
C20: =IF(P20=TRUE,C19+1,) -> 0 | E20: =IF(P20=TRUE,E19+F19,) -> 0 | N20: =ISTEXT(D20) -> FALSE | O20: =ISNUMBER(D20) -> FALSE | P20: =OR(N20=TRUE,O20=TRUE) -> FALSE
C21: =IF(P21=TRUE,C20+1,) -> 0 | E21: =IF(P21=TRUE,E20+F20,) -> 0 | N21: =ISTEXT(D21) -> FALSE | O21: =ISNUMBER(D21) -> FALSE | P21: =OR(N21=TRUE,O21=TRUE) -> FALSE
C22: =IF(P22=TRUE,C21+1,) -> 0 | E22: =IF(P22=TRUE,E21+F21,) -> 0 | N22: =ISTEXT(D22) -> FALSE | O22: =ISNUMBER(D22) -> FALSE | P22: =OR(N22=TRUE,O22=TRUE) -> FALSE
C23: =IF(P23=TRUE,C22+1,) -> 0 | E23: =IF(P23=TRUE,E22+F22,) -> 0 | N23: =ISTEXT(D23) -> FALSE | O23: =ISNUMBER(D23) -> FALSE | P23: =OR(N23=TRUE,O23=TRUE) -> FALSE
C24: =IF(P24=TRUE,C23+1,) -> 0 | E24: =IF(P24=TRUE,E23+F23,) -> 0 | N24: =ISTEXT(D24) -> FALSE | O24: =ISNUMBER(D24) -> FALSE | P24: =OR(N24=TRUE,O24=TRUE) -> FALSE
C25: =IF(P25=TRUE,C24+1,) -> 0 | E25: =IF(P25=TRUE,E24+F24,) -> 0 | N25: =ISTEXT(D25) -> FALSE | O25: =ISNUMBER(D25) -> FALSE | P25: =OR(N25=TRUE,O25=TRUE) -> FALSE
C26: =IF(P26=TRUE,C25+1,) -> 0 | E26: =IF(P26=TRUE,E25+F25,) -> 0 | N26: =ISTEXT(D26) -> FALSE | O26: =ISNUMBER(D26) -> FALSE | P26: =OR(N26=TRUE,O26=TRUE) -> FALSE
C27: =IF(P27=TRUE,C26+1,) -> 0 | E27: =IF(P27=TRUE,E26+F26,) -> 0 | N27: =ISTEXT(D27) -> FALSE | O27: =ISNUMBER(D27) -> FALSE | P27: =OR(N27=TRUE,O27=TRUE) -> FALSE
C28: =IF(P28=TRUE,C27+1,) -> 0 | E28: =IF(P28=TRUE,E27+F27,) -> 0 | N28: =ISTEXT(D28) -> FALSE | O28: =ISNUMBER(D28) -> FALSE | P28: =OR(N28=TRUE,O28=TRUE) -> FALSE
C29: =IF(P29=TRUE,C28+1,) -> 0 | E29: =IF(P29=TRUE,E28+F28,) -> 0 | N29: =ISTEXT(D29) -> FALSE | O29: =ISNUMBER(D29) -> FALSE | P29: =OR(N29=TRUE,O29=TRUE) -> FALSE
... C99: =IF(P99=TRUE,C98+1,) -> 0 | E99: =IF(P99=TRUE,E98+F98,) -> 0 | N99: =ISTEXT(D99) -> FALSE | O99: =ISNUMBER(D99) -> FALSE | P99: =OR(N99=TRUE,O99=TRUE) -> FALSE

Sheet EAB - Atribuc.rdtos cap. inmob
D2: Diseño de registro de datos fiscales y personales
D3: ='CONTROL DE VERSIONES'!G68 -> IRPF 2025
D4: Atribución de rendimientos del capital inmobiliario
C5: =IF(P5=TRUE,C4+1,) -> 0
C6: =IF(P6=TRUE,C5+1,) -> 0
C7: Este concepto de datos fiscales incluye la atribución de los rendimientos de capital inmobiliario con origen en el Modelo 184
C9: Nº | D9: Nombre | E9: Posición | F9: Longitud | G9: Descripción
C10: =IF(P10=TRUE,1,) -> 1 | D10: Tipo | E10: =IF(P10=TRUE,1,) -> 1 | F10: 1 | G10: Tipo de registro = '2' | N10: =ISTEXT(D10) -> TRUE | O10: =ISNUMBER(D10) -> FALSE | P10: =OR(N10=TRUE,O10=TRUE) -> TRUE
C11: =IF(P11=TRUE,C10+1,) -> 2 | D11: Código | E11: =IF(P11=TRUE,E10+F10,) -> 2 | F11: 7 | G11: 'EABnnnn' Donde nnnn es el número del registro de este tipo contenido en el fichero de datos fiscales. | N11: =ISTEXT(D11) -> TRUE | O11: =ISNUMBER(D11) -> FALSE | P11: =OR(N11=TRUE,O11=TRUE) -> TRUE
C12: =IF(P12=TRUE,C11+1,) -> 3 | D12: NIF del Declarante | E12: =IF(P12=TRUE,E11+F11,) -> 9 | F12: 9 | N12: =ISTEXT(D12) -> TRUE | O12: =ISNUMBER(D12) -> FALSE | P12: =OR(N12=TRUE,O12=TRUE) -> TRUE
C13: =IF(P13=TRUE,C12+1,) -> 4 | D13: Nombre del Declarante | E13: =IF(P13=TRUE,E12+F12,) -> 18 | F13: 40 | N13: =ISTEXT(D13) -> TRUE | O13: =ISNUMBER(D13) -> FALSE | P13: =OR(N13=TRUE,O13=TRUE) -> TRUE
C14: =IF(P14=TRUE,C13+1,) -> 5 | D14: % de participación | E14: =IF(P14=TRUE,E13+F13,) -> 58 | F14: 7 | G14: Tres enteros y cuatro decimales | N14: =ISTEXT(D14) -> TRUE | O14: =ISNUMBER(D14) -> FALSE | P14: =OR(N14=TRUE,O14=TRUE) -> TRUE
C15: =IF(P15=TRUE,C14+1,) -> 6 | D15: Importe | E15: =IF(P15=TRUE,E14+F14,) -> 65 | F15: 13 | N15: =ISTEXT(D15) -> TRUE | O15: =ISNUMBER(D15) -> FALSE | P15: =OR(N15=TRUE,O15=TRUE) -> TRUE
C16: =IF(P16=TRUE,C15+1,) -> 7 | D16: Reducción | E16: =IF(P16=TRUE,E15+F15,) -> 78 | F16: 11 | N16: =ISTEXT(D16) -> TRUE | O16: =ISNUMBER(D16) -> FALSE | P16: =OR(N16=TRUE,O16=TRUE) -> TRUE
C17: =IF(P17=TRUE,C16+1,) -> 8 | D17: Naturaleza del inmueble | E17: =IF(P17=TRUE,E16+F16,) -> 89 | F17: 1 | G17: Valores: '1' Urbano '2' Rústico | N17: =ISTEXT(D17) -> TRUE | O17: =ISNUMBER(D17) -> FALSE | P17: =OR(N17=TRUE,O17=TRUE) -> TRUE
C18: =IF(P18=TRUE,C17+1,) -> 9 | D18: Situación del inmueble | E18: =IF(P18=TRUE,E17+F17,) -> 90 | F18: 1 | G18: Valores: '1' - Inmueble con referencia catastral situado en cualquier punto del territorio español excepto País Vasco y Navarra '2' - Inmueble situado en la Comunidad Autónoma del País Vasco '3' - Inmueble situado en la Comunidad Foral de Navarra '4' - Inmueble en cualquiera de las situaciones anteriores pero sin referencia catastral '5' - Inmueble situado en el extranjero | N18: =ISTEXT(D18) -> TRUE | O18: =ISNUMBER(D18) -> FALSE | P18: =OR(N18=TRUE,O18=TRUE) -> TRUE
C19: =IF(P19=TRUE,C18+1,) -> 10 | D19: Ref Catastral del inmueble | E19: =IF(P19=TRUE,E18+F18,) -> 91 | F19: 20 | N19: =ISTEXT(D19) -> TRUE | O19: =ISNUMBER(D19) -> FALSE | P19: =OR(N19=TRUE,O19=TRUE) -> TRUE
C20: =IF(P20=TRUE,C19+1,) -> 11 | D20: Clave Declarado en su relación con el inmueble | E20: =IF(P20=TRUE,E19+F19,) -> 111 | F20: 1 | G20: Valores: 'N' - Nudo propietario 'T' - Titular 'U' - Usufructuario 'O' - Otro derecho real | N20: =ISTEXT(D20) -> TRUE | O20: =ISNUMBER(D20) -> FALSE | P20: =OR(N20=TRUE,O20=TRUE) -> TRUE
C21: =IF(P21=TRUE,C20+1,) -> 12 | D21: % de titularidad del inmueble | E21: =IF(P21=TRUE,E20+F20,) -> 112 | F21: 5 | G21: Tres enteros y dos decimales | N21: =ISTEXT(D21) -> TRUE | O21: =ISNUMBER(D21) -> FALSE | P21: =OR(N21=TRUE,O21=TRUE) -> TRUE
C22: =IF(P22=TRUE,C21+1,) -> 13 | D22: Posiciones reservadas para la AEAT | E22: =IF(P22=TRUE,E21+F21,) -> 117 | F22: 3 | N22: =ISTEXT(D22) -> TRUE | O22: =ISNUMBER(D22) -> FALSE | P22: =OR(N22=TRUE,O22=TRUE) -> TRUE
C23: =IF(P23=TRUE,C22+1,) -> 0 | E23: =IF(P23=TRUE,E22+F22,) -> 0 | N23: =ISTEXT(D23) -> FALSE | O23: =ISNUMBER(D23) -> FALSE | P23: =OR(N23=TRUE,O23=TRUE) -> FALSE
C24: =IF(P24=TRUE,C23+1,) -> 0 | E24: =IF(P24=TRUE,E23+F23,) -> 0 | N24: =ISTEXT(D24) -> FALSE | O24: =ISNUMBER(D24) -> FALSE | P24: =OR(N24=TRUE,O24=TRUE) -> FALSE
C25: =IF(P25=TRUE,C24+1,) -> 0 | E25: =IF(P25=TRUE,E24+F24,) -> 0 | N25: =ISTEXT(D25) -> FALSE | O25: =ISNUMBER(D25) -> FALSE | P25: =OR(N25=TRUE,O25=TRUE) -> FALSE
C26: =IF(P26=TRUE,C25+1,) -> 0 | E26: =IF(P26=TRUE,E25+F25,) -> 0 | N26: =ISTEXT(D26) -> FALSE | O26: =ISNUMBER(D26) -> FALSE | P26: =OR(N26=TRUE,O26=TRUE) -> FALSE
C27: =IF(P27=TRUE,C26+1,) -> 0 | E27: =IF(P27=TRUE,E26+F26,) -> 0 | N27: =ISTEXT(D27) -> FALSE | O27: =ISNUMBER(D27) -> FALSE | P27: =OR(N27=TRUE,O27=TRUE) -> FALSE
C28: =IF(P28=TRUE,C27+1,) -> 0 | E28: =IF(P28=TRUE,E27+F27,) -> 0 | N28: =ISTEXT(D28) -> FALSE | O28: =ISNUMBER(D28) -> FALSE | P28: =OR(N28=TRUE,O28=TRUE) -> FALSE
C29: =IF(P29=TRUE,C28+1,) -> 0 | E29: =IF(P29=TRUE,E28+F28,) -> 0 | N29: =ISTEXT(D29) -> FALSE | O29: =ISNUMBER(D29) -> FALSE | P29: =OR(N29=TRUE,O29=TRUE) -> FALSE
C30: =IF(P30=TRUE,C29+1,) -> 0 | E30: =IF(P30=TRUE,E29+F29,) -> 0 | N30: =ISTEXT(D30) -> FALSE | O30: =ISNUMBER(D30) -> FALSE | P30: =OR(N30=TRUE,O30=TRUE) -> FALSE
C31: =IF(P31=TRUE,C30+1,) -> 0 | E31: =IF(P31=TRUE,E30+F30,) -> 0 | N31: =ISTEXT(D31) -> FALSE | O31: =ISNUMBER(D31) -> FALSE | P31: =OR(N31=TRUE,O31=TRUE) -> FALSE
C32: =IF(P32=TRUE,C31+1,) -> 0 | E32: =IF(P32=TRUE,E31+F31,) -> 0 | N32: =ISTEXT(D32) -> FALSE | O32: =ISNUMBER(D32) -> FALSE | P32: =OR(N32=TRUE,O32=TRUE) -> FALSE
C33: =IF(P33=TRUE,C32+1,) -> 0 | E33: =IF(P33=TRUE,E32+F32,) -> 0 | N33: =ISTEXT(D33) -> FALSE | O33: =ISNUMBER(D33) -> FALSE | P33: =OR(N33=TRUE,O33=TRUE) -> FALSE
C34: =IF(P34=TRUE,C33+1,) -> 0 | E34: =IF(P34=TRUE,E33+F33,) -> 0 | N34: =ISTEXT(D34) -> FALSE | O34: =ISNUMBER(D34) -> FALSE | P34: =OR(N34=TRUE,O34=TRUE) -> FALSE
... C99: =IF(P99=TRUE,C98+1,) -> 0 | E99: =IF(P99=TRUE,E98+F98,) -> 0 | N99: =ISTEXT(D99) -> FALSE | O99: =ISNUMBER(D99) -> FALSE | P99: =OR(N99=TRUE,O99=TRUE) -> FALSE

Sheet EAC - Atribuc.rdtos activ econo
D2: Diseño de registro de datos fiscales y personales
D3: ='CONTROL DE VERSIONES'!G68 -> IRPF 2025
D4: Atribución de rendimientos de actividades económicas
C5: =IF(P5=TRUE,C4+1,) -> 0
C6: =IF(P6=TRUE,C5+1,) -> 0
C7: Este concepto de datos fiscales incluye la atribución de rendimientos de Actividades Económicas con origen en el Modelo 184
C9: Nº | D9: Nombre | E9: Posición | F9: Longitud | G9: Descripción
C10: =IF(P10=TRUE,1,) -> 1 | D10: Tipo | E10: =IF(P10=TRUE,1,) -> 1 | F10: 1 | G10: Tipo de registro = '2' | N10: =ISTEXT(D10) -> TRUE | O10: =ISNUMBER(D10) -> FALSE | P10: =OR(N10=TRUE,O10=TRUE) -> TRUE
C11: =IF(P11=TRUE,C10+1,) -> 2 | D11: Código | E11: =IF(P11=TRUE,E10+F10,) -> 2 | F11: 7 | G11: 'EACnnnn' Donde nnnn es el número del registro de este tipo contenido en el fichero de datos fiscales. | N11: =ISTEXT(D11) -> TRUE | O11: =ISNUMBER(D11) -> FALSE | P11: =OR(N11=TRUE,O11=TRUE) -> TRUE
C12: =IF(P12=TRUE,C11+1,) -> 3 | D12: NIF del Declarante | E12: =IF(P12=TRUE,E11+F11,) -> 9 | F12: 9 | N12: =ISTEXT(D12) -> TRUE | O12: =ISNUMBER(D12) -> FALSE | P12: =OR(N12=TRUE,O12=TRUE) -> TRUE
C13: =IF(P13=TRUE,C12+1,) -> 4 | D13: Nombre del Declarante | E13: =IF(P13=TRUE,E12+F12,) -> 18 | F13: 40 | N13: =ISTEXT(D13) -> TRUE | O13: =ISNUMBER(D13) -> FALSE | P13: =OR(N13=TRUE,O13=TRUE) -> TRUE
C14: =IF(P14=TRUE,C13+1,) -> 5 | D14: % de participación | E14: =IF(P14=TRUE,E13+F13,) -> 58 | F14: 7 | G14: Tres enteros y cuatro decimales | N14: =ISTEXT(D14) -> TRUE | O14: =ISNUMBER(D14) -> FALSE | P14: =OR(N14=TRUE,O14=TRUE) -> TRUE
C15: =IF(P15=TRUE,C14+1,) -> 6 | D15: Rendimiento neto atribuido | E15: =IF(P15=TRUE,E14+F14,) -> 65 | F15: 13 | N15: =ISTEXT(D15) -> TRUE | O15: =ISNUMBER(D15) -> FALSE | P15: =OR(N15=TRUE,O15=TRUE) -> TRUE
C16: =IF(P16=TRUE,C15+1,) -> 7 | D16: Rendimiento neto previo | E16: =IF(P16=TRUE,E15+F15,) -> 78 | F16: 13 | N16: =ISTEXT(D16) -> TRUE | O16: =ISNUMBER(D16) -> FALSE | P16: =OR(N16=TRUE,O16=TRUE) -> TRUE
C17: =IF(P17=TRUE,C16+1,) -> 8 | D17: Reducción art. 32.1 Ley IRPF | E17: =IF(P17=TRUE,E16+F16,) -> 91 | F17: 11 | N17: =ISTEXT(D17) -> TRUE | O17: =ISNUMBER(D17) -> FALSE | P17: =OR(N17=TRUE,O17=TRUE) -> TRUE
C18: =IF(P18=TRUE,C17+1,) -> 9 | D18: Provisiones y Gastos de difícil justificación | E18: =IF(P18=TRUE,E17+F17,) -> 102 | F18: 12 | N18: =ISTEXT(D18) -> TRUE | O18: =ISNUMBER(D18) -> FALSE | P18: =OR(N18=TRUE,O18=TRUE) -> TRUE
C19: =IF(P19=TRUE,C18+1,) -> 10 | D19: Subclave | E19: =IF(P19=TRUE,E18+F18,) -> 114 | F19: 2 | G19: 01 Estimación directa modalidad normal 02 Estimación directa modalidad simplificada 03 Estimación objetiva (excepto actividades agrícolas, ganaderas y forestales) 04 Estimación objetiva (actividades agrícolas, ganaderas y forestales) | N19: =ISTEXT(D19) -> TRUE | O19: =ISNUMBER(D19) -> FALSE | P19: =OR(N19=TRUE,O19=TRUE) -> TRUE
C20: =IF(P20=TRUE,C19+1,) -> 0 | E20: =IF(P20=TRUE,E19+F19,) -> 0 | N20: =ISTEXT(D20) -> FALSE | O20: =ISNUMBER(D20) -> FALSE | P20: =OR(N20=TRUE,O20=TRUE) -> FALSE
C21: =IF(P21=TRUE,C20+1,) -> 0 | E21: =IF(P21=TRUE,E20+F20,) -> 0 | N21: =ISTEXT(D21) -> FALSE | O21: =ISNUMBER(D21) -> FALSE | P21: =OR(N21=TRUE,O21=TRUE) -> FALSE
C22: =IF(P22=TRUE,C21+1,) -> 0 | E22: =IF(P22=TRUE,E21+F21,) -> 0 | N22: =ISTEXT(D22) -> FALSE | O22: =ISNUMBER(D22) -> FALSE | P22: =OR(N22=TRUE,O22=TRUE) -> FALSE
C23: =IF(P23=TRUE,C22+1,) -> 0 | E23: =IF(P23=TRUE,E22+F22,) -> 0 | N23: =ISTEXT(D23) -> FALSE | O23: =ISNUMBER(D23) -> FALSE | P23: =OR(N23=TRUE,O23=TRUE) -> FALSE
C24: =IF(P24=TRUE,C23+1,) -> 0 | E24: =IF(P24=TRUE,E23+F23,) -> 0 | N24: =ISTEXT(D24) -> FALSE | O24: =ISNUMBER(D24) -> FALSE | P24: =OR(N24=TRUE,O24=TRUE) -> FALSE
C25: =IF(P25=TRUE,C24+1,) -> 0 | E25: =IF(P25=TRUE,E24+F24,) -> 0 | N25: =ISTEXT(D25) -> FALSE | O25: =ISNUMBER(D25) -> FALSE | P25: =OR(N25=TRUE,O25=TRUE) -> FALSE
C26: =IF(P26=TRUE,C25+1,) -> 0 | E26: =IF(P26=TRUE,E25+F25,) -> 0 | N26: =ISTEXT(D26) -> FALSE | O26: =ISNUMBER(D26) -> FALSE | P26: =OR(N26=TRUE,O26=TRUE) -> FALSE
C27: =IF(P27=TRUE,C26+1,) -> 0 | E27: =IF(P27=TRUE,E26+F26,) -> 0 | N27: =ISTEXT(D27) -> FALSE | O27: =ISNUMBER(D27) -> FALSE | P27: =OR(N27=TRUE,O27=TRUE) -> FALSE
C28: =IF(P28=TRUE,C27+1,) -> 0 | E28: =IF(P28=TRUE,E27+F27,) -> 0 | N28: =ISTEXT(D28) -> FALSE | O28: =ISNUMBER(D28) -> FALSE | P28: =OR(N28=TRUE,O28=TRUE) -> FALSE
C29: =IF(P29=TRUE,C28+1,) -> 0 | E29: =IF(P29=TRUE,E28+F28,) -> 0 | N29: =ISTEXT(D29) -> FALSE | O29: =ISNUMBER(D29) -> FALSE | P29: =OR(N29=TRUE,O29=TRUE) -> FALSE
C30: =IF(P30=TRUE,C29+1,) -> 0 | E30: =IF(P30=TRUE,E29+F29,) -> 0 | N30: =ISTEXT(D30) -> FALSE | O30: =ISNUMBER(D30) -> FALSE | P30: =OR(N30=TRUE,O30=TRUE) -> FALSE
C31: =IF(P31=TRUE,C30+1,) -> 0 | E31: =IF(P31=TRUE,E30+F30,) -> 0 | N31: =ISTEXT(D31) -> FALSE | O31: =ISNUMBER(D31) -> FALSE | P31: =OR(N31=TRUE,O31=TRUE) -> FALSE
... C99: =IF(P99=TRUE,C98+1,) -> 0 | E99: =IF(P99=TRUE,E98+F98,) -> 0 | N99: =ISTEXT(D99) -> FALSE | O99: =ISNUMBER(D99) -> FALSE | P99: =OR(N99=TRUE,O99=TRUE) -> FALSE

Sheet EAD - Atribuc. ganancias y perd
D2: Diseño de registro de datos fiscales y personales
D3: ='CONTROL DE VERSIONES'!G68 -> IRPF 2025
D4: Atribución de ganancias y pérdidas patrimoniales
C5: =IF(P5=TRUE,C4+1,) -> 0
C6: =IF(P6=TRUE,C5+1,) -> 0
C7: Este concepto de datos fiscales incluye la atribución de ganancias y pérdidas patrimoniales con origen en el Modelo 184
C9: Nº | D9: Nombre | E9: Posición | F9: Longitud | G9: Descripción
C10: =IF(P10=TRUE,1,) -> 1 | D10: Tipo | E10: =IF(P10=TRUE,1,) -> 1 | F10: 1 | G10: Tipo de registro = '2' | N10: =ISTEXT(D10) -> TRUE | O10: =ISNUMBER(D10) -> FALSE | P10: =OR(N10=TRUE,O10=TRUE) -> TRUE
C11: =IF(P11=TRUE,C10+1,) -> 2 | D11: Código | E11: =IF(P11=TRUE,E10+F10,) -> 2 | F11: 7 | G11: 'EADnnnn' Donde nnnn es el número del registro de este tipo contenido en el fichero de datos fiscales. | N11: =ISTEXT(D11) -> TRUE | O11: =ISNUMBER(D11) -> FALSE | P11: =OR(N11=TRUE,O11=TRUE) -> TRUE
C12: =IF(P12=TRUE,C11+1,) -> 3 | D12: NIF del Declarante | E12: =IF(P12=TRUE,E11+F11,) -> 9 | F12: 9 | N12: =ISTEXT(D12) -> TRUE | O12: =ISNUMBER(D12) -> FALSE | P12: =OR(N12=TRUE,O12=TRUE) -> TRUE
C13: =IF(P13=TRUE,C12+1,) -> 4 | D13: Nombre del Declarante | E13: =IF(P13=TRUE,E12+F12,) -> 18 | F13: 40 | N13: =ISTEXT(D13) -> TRUE | O13: =ISNUMBER(D13) -> FALSE | P13: =OR(N13=TRUE,O13=TRUE) -> TRUE
C14: =IF(P14=TRUE,C13+1,) -> 5 | D14: % de participación | E14: =IF(P14=TRUE,E13+F13,) -> 58 | F14: 7 | G14: Tres enteros y cuatro decimales | N14: =ISTEXT(D14) -> TRUE | O14: =ISNUMBER(D14) -> FALSE | P14: =OR(N14=TRUE,O14=TRUE) -> TRUE
C15: =IF(P15=TRUE,C14+1,) -> 6 | D15: Clave | E15: =IF(P15=TRUE,E14+F14,) -> 65 | F15: 1 | G15: Sólo se tratan registros con clave de operación F y G Claves: 'F' - Ganancias y pérdidas patrimoniales no derivadas de transmisiones de elementos patrimoniales 'G' - Ganancias y pérdidas patrimoniales derivadas de transmisiones de lelmentos | N15: =ISTEXT(D15) -> TRUE | O15: =ISNUMBER(D15) -> FALSE | P15: =OR(N15=TRUE,O15=TRUE) -> TRUE
C16: =IF(P16=TRUE,C15+1,) -> 7 | D16: Subclave | E16: =IF(P16=TRUE,E15+F15,) -> 66 | F16: 2 | G16: Subclaves: '01' - Ganancias '02' - Pérdidas | N16: =ISTEXT(D16) -> TRUE | O16: =ISNUMBER(D16) -> FALSE | P16: =OR(N16=TRUE,O16=TRUE) -> TRUE
C17: =IF(P17=TRUE,C16+1,) -> 8 | D17: Importe | E17: =IF(P17=TRUE,E16+F16,) -> 68 | F17: 12 | N17: =ISTEXT(D17) -> TRUE | O17: =ISNUMBER(D17) -> FALSE | P17: =OR(N17=TRUE,O17=TRUE) -> TRUE
C18: =IF(P18=TRUE,C17+1,) -> 0 | E18: =IF(P18=TRUE,E17+F17,) -> 0 | N18: =ISTEXT(D18) -> FALSE | O18: =ISNUMBER(D18) -> FALSE | P18: =OR(N18=TRUE,O18=TRUE) -> FALSE
C19: =IF(P19=TRUE,C18+1,) -> 0 | E19: =IF(P19=TRUE,E18+F18,) -> 0 | N19: =ISTEXT(D19) -> FALSE | O19: =ISNUMBER(D19) -> FALSE | P19: =OR(N19=TRUE,O19=TRUE) -> FALSE
C20: =IF(P20=TRUE,C19+1,) -> 0 | E20: =IF(P20=TRUE,E19+F19,) -> 0 | N20: =ISTEXT(D20) -> FALSE | O20: =ISNUMBER(D20) -> FALSE | P20: =OR(N20=TRUE,O20=TRUE) -> FALSE
C21: =IF(P21=TRUE,C20+1,) -> 0 | E21: =IF(P21=TRUE,E20+F20,) -> 0 | N21: =ISTEXT(D21) -> FALSE | O21: =ISNUMBER(D21) -> FALSE | P21: =OR(N21=TRUE,O21=TRUE) -> FALSE
C22: =IF(P22=TRUE,C21+1,) -> 0 | E22: =IF(P22=TRUE,E21+F21,) -> 0 | N22: =ISTEXT(D22) -> FALSE | O22: =ISNUMBER(D22) -> FALSE | P22: =OR(N22=TRUE,O22=TRUE) -> FALSE
C23: =IF(P23=TRUE,C22+1,) -> 0 | E23: =IF(P23=TRUE,E22+F22,) -> 0 | N23: =ISTEXT(D23) -> FALSE | O23: =ISNUMBER(D23) -> FALSE | P23: =OR(N23=TRUE,O23=TRUE) -> FALSE
C24: =IF(P24=TRUE,C23+1,) -> 0 | E24: =IF(P24=TRUE,E23+F23,) -> 0 | N24: =ISTEXT(D24) -> FALSE | O24: =ISNUMBER(D24) -> FALSE | P24: =OR(N24=TRUE,O24=TRUE) -> FALSE
C25: =IF(P25=TRUE,C24+1,) -> 0 | E25: =IF(P25=TRUE,E24+F24,) -> 0 | N25: =ISTEXT(D25) -> FALSE | O25: =ISNUMBER(D25) -> FALSE | P25: =OR(N25=TRUE,O25=TRUE) -> FALSE
C26: =IF(P26=TRUE,C25+1,) -> 0 | E26: =IF(P26=TRUE,E25+F25,) -> 0 | N26: =ISTEXT(D26) -> FALSE | O26: =ISNUMBER(D26) -> FALSE | P26: =OR(N26=TRUE,O26=TRUE) -> FALSE
C27: =IF(P27=TRUE,C26+1,) -> 0 | E27: =IF(P27=TRUE,E26+F26,) -> 0 | N27: =ISTEXT(D27) -> FALSE | O27: =ISNUMBER(D27) -> FALSE | P27: =OR(N27=TRUE,O27=TRUE) -> FALSE
C28: =IF(P28=TRUE,C27+1,) -> 0 | E28: =IF(P28=TRUE,E27+F27,) -> 0 | N28: =ISTEXT(D28) -> FALSE | O28: =ISNUMBER(D28) -> FALSE | P28: =OR(N28=TRUE,O28=TRUE) -> FALSE
C29: =IF(P29=TRUE,C28+1,) -> 0 | E29: =IF(P29=TRUE,E28+F28,) -> 0 | N29: =ISTEXT(D29) -> FALSE | O29: =ISNUMBER(D29) -> FALSE | P29: =OR(N29=TRUE,O29=TRUE) -> FALSE
... C99: =IF(P99=TRUE,C98+1,) -> 0 | E99: =IF(P99=TRUE,E98+F98,) -> 0 | N99: =ISTEXT(D99) -> FALSE | O99: =ISNUMBER(D99) -> FALSE | P99: =OR(N99=TRUE,O99=TRUE) -> FALSE

Sheet EAE - Atribucion retenciones
D2: Diseño de registro de datos fiscales y personales
D3: ='CONTROL DE VERSIONES'!G68 -> IRPF 2025
D4: Atribución de retenciones e ingresos a cuenta
C5: =IF(P5=TRUE,C4+1,) -> 0
C6: =IF(P6=TRUE,C5+1,) -> 0
C7: Este concepto de datos fiscales incluye la atribución de retenciones e ingresos a cuenta con origen en el Modelo 184
C9: Nº | D9: Nombre | E9: Posición | F9: Longitud | G9: Descripción
C10: =IF(P10=TRUE,1,) -> 1 | D10: Tipo | E10: =IF(P10=TRUE,1,) -> 1 | F10: 1 | G10: Tipo de registro = '2' | N10: =ISTEXT(D10) -> TRUE | O10: =ISNUMBER(D10) -> FALSE | P10: =OR(N10=TRUE,O10=TRUE) -> TRUE
C11: =IF(P11=TRUE,C10+1,) -> 2 | D11: Código | E11: =IF(P11=TRUE,E10+F10,) -> 2 | F11: 7 | G11: 'EAEnnnn' Donde nnnn es el número del registro de este tipo contenido en el fichero de datos fiscales. | N11: =ISTEXT(D11) -> TRUE | O11: =ISNUMBER(D11) -> FALSE | P11: =OR(N11=TRUE,O11=TRUE) -> TRUE
C12: =IF(P12=TRUE,C11+1,) -> 3 | D12: NIF del Declarante | E12: =IF(P12=TRUE,E11+F11,) -> 9 | F12: 9 | N12: =ISTEXT(D12) -> TRUE | O12: =ISNUMBER(D12) -> FALSE | P12: =OR(N12=TRUE,O12=TRUE) -> TRUE
C13: =IF(P13=TRUE,C12+1,) -> 4 | D13: Nombre del Declarante | E13: =IF(P13=TRUE,E12+F12,) -> 18 | F13: 40 | N13: =ISTEXT(D13) -> TRUE | O13: =ISNUMBER(D13) -> FALSE | P13: =OR(N13=TRUE,O13=TRUE) -> TRUE
C14: =IF(P14=TRUE,C13+1,) -> 5 | D14: % de participación | E14: =IF(P14=TRUE,E13+F13,) -> 58 | F14: 7 | G14: Tres enteros y cuatro decimales | N14: =ISTEXT(D14) -> TRUE | O14: =ISNUMBER(D14) -> FALSE | P14: =OR(N14=TRUE,O14=TRUE) -> TRUE
C15: =IF(P15=TRUE,C14+1,) -> 6 | D15: Subclave | E15: =IF(P15=TRUE,E14+F14,) -> 65 | F15: 2 | G15: Sólo se tratan registros con clave de operación K Subclaves: '01' - Por rendimientos del capital mobiliario '02' - Por arrendamiento de inmuebles urbanos '03' - Por rendimientos de actividades económicas '04' - Por ganancias patrimoniales '05' - Por otros conceptos | N15: =ISTEXT(D15) -> TRUE | O15: =ISNUMBER(D15) -> FALSE | P15: =OR(N15=TRUE,O15=TRUE) -> TRUE
C16: =IF(P16=TRUE,C15+1,) -> 7 | D16: Retención | E16: =IF(P16=TRUE,E15+F15,) -> 67 | F16: 12 | N16: =ISTEXT(D16) -> TRUE | O16: =ISNUMBER(D16) -> FALSE | P16: =OR(N16=TRUE,O16=TRUE) -> TRUE
C17: =IF(P17=TRUE,C16+1,) -> 0 | E17: =IF(P17=TRUE,E16+F16,) -> 0 | N17: =ISTEXT(D17) -> FALSE | O17: =ISNUMBER(D17) -> FALSE | P17: =OR(N17=TRUE,O17=TRUE) -> FALSE
C18: =IF(P18=TRUE,C17+1,) -> 0 | E18: =IF(P18=TRUE,E17+F17,) -> 0 | N18: =ISTEXT(D18) -> FALSE | O18: =ISNUMBER(D18) -> FALSE | P18: =OR(N18=TRUE,O18=TRUE) -> FALSE
C19: =IF(P19=TRUE,C18+1,) -> 0 | E19: =IF(P19=TRUE,E18+F18,) -> 0 | N19: =ISTEXT(D19) -> FALSE | O19: =ISNUMBER(D19) -> FALSE | P19: =OR(N19=TRUE,O19=TRUE) -> FALSE
C20: =IF(P20=TRUE,C19+1,) -> 0 | E20: =IF(P20=TRUE,E19+F19,) -> 0 | N20: =ISTEXT(D20) -> FALSE | O20: =ISNUMBER(D20) -> FALSE | P20: =OR(N20=TRUE,O20=TRUE) -> FALSE
C21: =IF(P21=TRUE,C20+1,) -> 0 | E21: =IF(P21=TRUE,E20+F20,) -> 0 | N21: =ISTEXT(D21) -> FALSE | O21: =ISNUMBER(D21) -> FALSE | P21: =OR(N21=TRUE,O21=TRUE) -> FALSE
C22: =IF(P22=TRUE,C21+1,) -> 0 | E22: =IF(P22=TRUE,E21+F21,) -> 0 | N22: =ISTEXT(D22) -> FALSE | O22: =ISNUMBER(D22) -> FALSE | P22: =OR(N22=TRUE,O22=TRUE) -> FALSE
C23: =IF(P23=TRUE,C22+1,) -> 0 | E23: =IF(P23=TRUE,E22+F22,) -> 0 | N23: =ISTEXT(D23) -> FALSE | O23: =ISNUMBER(D23) -> FALSE | P23: =OR(N23=TRUE,O23=TRUE) -> FALSE
C24: =IF(P24=TRUE,C23+1,) -> 0 | E24: =IF(P24=TRUE,E23+F23,) -> 0 | N24: =ISTEXT(D24) -> FALSE | O24: =ISNUMBER(D24) -> FALSE | P24: =OR(N24=TRUE,O24=TRUE) -> FALSE
C25: =IF(P25=TRUE,C24+1,) -> 0 | E25: =IF(P25=TRUE,E24+F24,) -> 0 | N25: =ISTEXT(D25) -> FALSE | O25: =ISNUMBER(D25) -> FALSE | P25: =OR(N25=TRUE,O25=TRUE) -> FALSE
C26: =IF(P26=TRUE,C25+1,) -> 0 | E26: =IF(P26=TRUE,E25+F25,) -> 0 | N26: =ISTEXT(D26) -> FALSE | O26: =ISNUMBER(D26) -> FALSE | P26: =OR(N26=TRUE,O26=TRUE) -> FALSE
C27: =IF(P27=TRUE,C26+1,) -> 0 | E27: =IF(P27=TRUE,E26+F26,) -> 0 | N27: =ISTEXT(D27) -> FALSE | O27: =ISNUMBER(D27) -> FALSE | P27: =OR(N27=TRUE,O27=TRUE) -> FALSE
C28: =IF(P28=TRUE,C27+1,) -> 0 | E28: =IF(P28=TRUE,E27+F27,) -> 0 | N28: =ISTEXT(D28) -> FALSE | O28: =ISNUMBER(D28) -> FALSE | P28: =OR(N28=TRUE,O28=TRUE) -> FALSE
... C99: =IF(P99=TRUE,C98+1,) -> 0 | E99: =IF(P99=TRUE,E98+F98,) -> 0 | N99: =ISTEXT(D99) -> FALSE | O99: =ISNUMBER(D99) -> FALSE | P99: =OR(N99=TRUE,O99=TRUE) -> FALSE

Sheet EAF - Atribucion deducciones
D2: Diseño de registro de datos fiscales y personales
D3: ='CONTROL DE VERSIONES'!G68 -> IRPF 2025
D4: Atribución de deducciones
C5: =IF(P5=TRUE,C4+1,) -> 0
C6: =IF(P6=TRUE,C5+1,) -> 0
C7: Este concepto de datos fiscales incluye la atribución de las deducciones con origen en el Modelo 184
C9: Nº | D9: Nombre | E9: Posición | F9: Longitud | G9: Descripción
C10: =IF(P10=TRUE,1,) -> 1 | D10: Tipo | E10: =IF(P10=TRUE,1,) -> 1 | F10: 1 | G10: Tipo de registro = '2' | N10: =ISTEXT(D10) -> TRUE | O10: =ISNUMBER(D10) -> FALSE | P10: =OR(N10=TRUE,O10=TRUE) -> TRUE
C11: =IF(P11=TRUE,C10+1,) -> 2 | D11: Código | E11: =IF(P11=TRUE,E10+F10,) -> 2 | F11: 7 | G11: 'EAFnnnn' Donde nnnn es el número del registro de este tipo contenido en el fichero de datos fiscales. | N11: =ISTEXT(D11) -> TRUE | O11: =ISNUMBER(D11) -> FALSE | P11: =OR(N11=TRUE,O11=TRUE) -> TRUE
C12: =IF(P12=TRUE,C11+1,) -> 3 | D12: NIF del Declarante | E12: =IF(P12=TRUE,E11+F11,) -> 9 | F12: 9 | N12: =ISTEXT(D12) -> TRUE | O12: =ISNUMBER(D12) -> FALSE | P12: =OR(N12=TRUE,O12=TRUE) -> TRUE
C13: =IF(P13=TRUE,C12+1,) -> 4 | D13: Nombre del Declarante | E13: =IF(P13=TRUE,E12+F12,) -> 18 | F13: 40 | N13: =ISTEXT(D13) -> TRUE | O13: =ISNUMBER(D13) -> FALSE | P13: =OR(N13=TRUE,O13=TRUE) -> TRUE
C14: =IF(P14=TRUE,C13+1,) -> 5 | D14: % de participación | E14: =IF(P14=TRUE,E13+F13,) -> 58 | F14: 7 | G14: Tres enteros y cuatro decimales | N14: =ISTEXT(D14) -> TRUE | O14: =ISNUMBER(D14) -> FALSE | P14: =OR(N14=TRUE,O14=TRUE) -> TRUE
C15: =IF(P15=TRUE,C14+1,) -> 6 | D15: Subclave | E15: =IF(P15=TRUE,E14+F14,) -> 65 | F15: 2 | G15: Sólo se tratan registros con clave de operación I Subclaves: '01' - Por protección Patrimonio Español y Mundial '02' - Por donativos donaciones y aportaciones '03' - Por rentas obtenidas en Ceuta y Melilla '04' - Deducciones en actividades económicas '05' - Deducciones por doble imposición internacnal. '06' - Por inversión en empresas de nueva o reciente creación | N15: =ISTEXT(D15) -> TRUE | O15: =ISNUMBER(D15) -> FALSE | P15: =OR(N15=TRUE,O15=TRUE) -> TRUE
C16: =IF(P16=TRUE,C15+1,) -> 7 | D16: Importe deducción | E16: =IF(P16=TRUE,E15+F15,) -> 67 | F16: 12 | N16: =ISTEXT(D16) -> TRUE | O16: =ISNUMBER(D16) -> FALSE | P16: =OR(N16=TRUE,O16=TRUE) -> TRUE
C17: =IF(P17=TRUE,C16+1,) -> 0 | E17: =IF(P17=TRUE,E16+F16,) -> 0 | N17: =ISTEXT(D17) -> FALSE | O17: =ISNUMBER(D17) -> FALSE | P17: =OR(N17=TRUE,O17=TRUE) -> FALSE
C18: =IF(P18=TRUE,C17+1,) -> 0 | E18: =IF(P18=TRUE,E17+F17,) -> 0 | N18: =ISTEXT(D18) -> FALSE | O18: =ISNUMBER(D18) -> FALSE | P18: =OR(N18=TRUE,O18=TRUE) -> FALSE
C19: =IF(P19=TRUE,C18+1,) -> 0 | E19: =IF(P19=TRUE,E18+F18,) -> 0 | N19: =ISTEXT(D19) -> FALSE | O19: =ISNUMBER(D19) -> FALSE | P19: =OR(N19=TRUE,O19=TRUE) -> FALSE
C20: =IF(P20=TRUE,C19+1,) -> 0 | E20: =IF(P20=TRUE,E19+F19,) -> 0 | N20: =ISTEXT(D20) -> FALSE | O20: =ISNUMBER(D20) -> FALSE | P20: =OR(N20=TRUE,O20=TRUE) -> FALSE
C21: =IF(P21=TRUE,C20+1,) -> 0 | E21: =IF(P21=TRUE,E20+F20,) -> 0 | N21: =ISTEXT(D21) -> FALSE | O21: =ISNUMBER(D21) -> FALSE | P21: =OR(N21=TRUE,O21=TRUE) -> FALSE
C22: =IF(P22=TRUE,C21+1,) -> 0 | E22: =IF(P22=TRUE,E21+F21,) -> 0 | N22: =ISTEXT(D22) -> FALSE | O22: =ISNUMBER(D22) -> FALSE | P22: =OR(N22=TRUE,O22=TRUE) -> FALSE
C23: =IF(P23=TRUE,C22+1,) -> 0 | E23: =IF(P23=TRUE,E22+F22,) -> 0 | N23: =ISTEXT(D23) -> FALSE | O23: =ISNUMBER(D23) -> FALSE | P23: =OR(N23=TRUE,O23=TRUE) -> FALSE
C24: =IF(P24=TRUE,C23+1,) -> 0 | E24: =IF(P24=TRUE,E23+F23,) -> 0 | N24: =ISTEXT(D24) -> FALSE | O24: =ISNUMBER(D24) -> FALSE | P24: =OR(N24=TRUE,O24=TRUE) -> FALSE
C25: =IF(P25=TRUE,C24+1,) -> 0 | E25: =IF(P25=TRUE,E24+F24,) -> 0 | N25: =ISTEXT(D25) -> FALSE | O25: =ISNUMBER(D25) -> FALSE | P25: =OR(N25=TRUE,O25=TRUE) -> FALSE
C26: =IF(P26=TRUE,C25+1,) -> 0 | E26: =IF(P26=TRUE,E25+F25,) -> 0 | N26: =ISTEXT(D26) -> FALSE | O26: =ISNUMBER(D26) -> FALSE | P26: =OR(N26=TRUE,O26=TRUE) -> FALSE
C27: =IF(P27=TRUE,C26+1,) -> 0 | E27: =IF(P27=TRUE,E26+F26,) -> 0 | N27: =ISTEXT(D27) -> FALSE | O27: =ISNUMBER(D27) -> FALSE | P27: =OR(N27=TRUE,O27=TRUE) -> FALSE
C28: =IF(P28=TRUE,C27+1,) -> 0 | E28: =IF(P28=TRUE,E27+F27,) -> 0 | N28: =ISTEXT(D28) -> FALSE | O28: =ISNUMBER(D28) -> FALSE | P28: =OR(N28=TRUE,O28=TRUE) -> FALSE
... C99: =IF(P99=TRUE,C98+1,) -> 0 | E99: =IF(P99=TRUE,E98+F98,) -> 0 | N99: =ISTEXT(D99) -> FALSE | O99: =ISNUMBER(D99) -> FALSE | P99: =OR(N99=TRUE,O99=TRUE) -> FALSE

Sheet AMI - Amortización Inmuebles
D2: Diseño de registro de datos fiscales y personales
D3: ='CONTROL DE VERSIONES'!G68 -> IRPF 2025
D4: Información relativa a la Amortización de Inmuebles declarada por el contribuyente
C5: =IF(P5=TRUE,C4+1,) -> 0
C6: =IF(P6=TRUE,C5+1,) -> 0
C7: Este concepto remite la información presentada por el contribuyente en su declaración de IRPF de 2024 dentro del bloque de “Amortización del inmueble principal y mejoras.” y “Amortización del inmueble accesorio y mejoras”
C9: Nº | D9: Nombre | E9: Posición | F9: Longitud | G9: Descripción
C10: =IF(P10=TRUE,1,) -> 1 | D10: Tipo | E10: =IF(P10=TRUE,1,) -> 1 | F10: 1 | G10: Tipo de registro = '2' | N10: =ISTEXT(D10) -> TRUE | O10: =ISNUMBER(D10) -> FALSE | P10: =OR(N10=TRUE,O10=TRUE) -> TRUE
C11: =IF(P11=TRUE,C10+1,) -> 2 | D11: Código | E11: =IF(P11=TRUE,E10+F10,) -> 2 | F11: 7 | G11: 'AMInnnn' Donde nnnn es el número del registro de este tipo contenido en el fichero de datos fiscales. | N11: =ISTEXT(D11) -> TRUE | O11: =ISNUMBER(D11) -> FALSE | P11: =OR(N11=TRUE,O11=TRUE) -> TRUE
C12: =IF(P12=TRUE,C11+1,) -> 3 | D12: Referencia Catastral | E12: =IF(P12=TRUE,E11+F11,) -> 9 | F12: 20 | N12: =ISTEXT(D12) -> TRUE | O12: =ISNUMBER(D12) -> FALSE | P12: =OR(N12=TRUE,O12=TRUE) -> TRUE
C13: =IF(P13=TRUE,C12+1,) -> 4 | D13: Tipo de adquisición | E13: =IF(P13=TRUE,E12+F12,) -> 29 | F13: 1 | G13: '1' - Onerosa (compraventa, permuta, etc.) '2' - Lucrativa (herencia,legado, donación, etc.) '3' - Onerosa y Lucrativa | N13: =ISTEXT(D13) -> TRUE | O13: =ISNUMBER(D13) -> FALSE | P13: =OR(N13=TRUE,O13=TRUE) -> TRUE
C14: =IF(P14=TRUE,C13+1,) -> 5 | D14: Fecha de adquisición | E14: =IF(P14=TRUE,E13+F13,) -> 30 | F14: 8 | G14: AAAAMMDD | N14: =ISTEXT(D14) -> TRUE | O14: =ISNUMBER(D14) -> FALSE | P14: =OR(N14=TRUE,O14=TRUE) -> TRUE
C15: =IF(P15=TRUE,C14+1,) -> 6 | D15: Importe de la adquisición | E15: =IF(P15=TRUE,E14+F14,) -> 38 | F15: 13 | N15: =ISTEXT(D15) -> TRUE | O15: =ISNUMBER(D15) -> FALSE | P15: =OR(N15=TRUE,O15=TRUE) -> TRUE
C16: =IF(P16=TRUE,C15+1,) -> 7 | D16: Gastos en la adquisición | E16: =IF(P16=TRUE,E15+F15,) -> 51 | F16: 13 | N16: =ISTEXT(D16) -> TRUE | O16: =ISNUMBER(D16) -> FALSE | P16: =OR(N16=TRUE,O16=TRUE) -> TRUE
C17: =IF(P17=TRUE,C16+1,) -> 8 | D17: Importe mejoras años anteriores | E17: =IF(P17=TRUE,E16+F16,) -> 64 | F17: 13 | G17: Se calculará como una sumatoria de los siguientes importes: - Importe de la mejora realizadas en años anteriores - Importe de las mejoras consignadas por el contribuyente para 2024. | N17: =ISTEXT(D17) -> TRUE | O17: =ISNUMBER(D17) -> FALSE | P17: =OR(N17=TRUE,O17=TRUE) -> TRUE
C18: =IF(P18=TRUE,C17+1,) -> 9 | D18: Tipo de titularidad | E18: =IF(P18=TRUE,E17+F17,) -> 77 | F18: 1 | G18: Valores.: 'I' - Titularidad Individual 'C' - Titularidad común | N18: =ISTEXT(D18) -> TRUE | O18: =ISNUMBER(D18) -> FALSE | P18: =OR(N18=TRUE,O18=TRUE) -> TRUE
C19: =IF(P19=TRUE,C18+1,) -> 0 | E19: =IF(P19=TRUE,E18+F18,) -> 0 | N19: =ISTEXT(D19) -> FALSE | O19: =ISNUMBER(D19) -> FALSE | P19: =OR(N19=TRUE,O19=TRUE) -> FALSE
C20: =IF(P20=TRUE,C19+1,) -> 0 | E20: =IF(P20=TRUE,E19+F19,) -> 0 | N20: =ISTEXT(D20) -> FALSE | O20: =ISNUMBER(D20) -> FALSE | P20: =OR(N20=TRUE,O20=TRUE) -> FALSE
C21: =IF(P21=TRUE,C20+1,) -> 0 | E21: =IF(P21=TRUE,E20+F20,) -> 0 | N21: =ISTEXT(D21) -> FALSE | O21: =ISNUMBER(D21) -> FALSE | P21: =OR(N21=TRUE,O21=TRUE) -> FALSE
C22: =IF(P22=TRUE,C21+1,) -> 0 | E22: =IF(P22=TRUE,E21+F21,) -> 0 | N22: =ISTEXT(D22) -> FALSE | O22: =ISNUMBER(D22) -> FALSE | P22: =OR(N22=TRUE,O22=TRUE) -> FALSE
C23: =IF(P23=TRUE,C22+1,) -> 0 | E23: =IF(P23=TRUE,E22+F22,) -> 0 | N23: =ISTEXT(D23) -> FALSE | O23: =ISNUMBER(D23) -> FALSE | P23: =OR(N23=TRUE,O23=TRUE) -> FALSE
C24: =IF(P24=TRUE,C23+1,) -> 0 | E24: =IF(P24=TRUE,E23+F23,) -> 0 | N24: =ISTEXT(D24) -> FALSE | O24: =ISNUMBER(D24) -> FALSE | P24: =OR(N24=TRUE,O24=TRUE) -> FALSE
C25: =IF(P25=TRUE,C24+1,) -> 0 | E25: =IF(P25=TRUE,E24+F24,) -> 0 | N25: =ISTEXT(D25) -> FALSE | O25: =ISNUMBER(D25) -> FALSE | P25: =OR(N25=TRUE,O25=TRUE) -> FALSE
C26: =IF(P26=TRUE,C25+1,) -> 0 | E26: =IF(P26=TRUE,E25+F25,) -> 0 | N26: =ISTEXT(D26) -> FALSE | O26: =ISNUMBER(D26) -> FALSE | P26: =OR(N26=TRUE,O26=TRUE) -> FALSE
C27: =IF(P27=TRUE,C26+1,) -> 0 | E27: =IF(P27=TRUE,E26+F26,) -> 0 | N27: =ISTEXT(D27) -> FALSE | O27: =ISNUMBER(D27) -> FALSE | P27: =OR(N27=TRUE,O27=TRUE) -> FALSE
C28: =IF(P28=TRUE,C27+1,) -> 0 | E28: =IF(P28=TRUE,E27+F27,) -> 0 | N28: =ISTEXT(D28) -> FALSE | O28: =ISNUMBER(D28) -> FALSE | P28: =OR(N28=TRUE,O28=TRUE) -> FALSE
C29: =IF(P29=TRUE,C28+1,) -> 0 | E29: =IF(P29=TRUE,E28+F28,) -> 0 | N29: =ISTEXT(D29) -> FALSE | O29: =ISNUMBER(D29) -> FALSE | P29: =OR(N29=TRUE,O29=TRUE) -> FALSE
C30: =IF(P30=TRUE,C29+1,) -> 0 | E30: =IF(P30=TRUE,E29+F29,) -> 0 | N30: =ISTEXT(D30) -> FALSE | O30: =ISNUMBER(D30) -> FALSE | P30: =OR(N30=TRUE,O30=TRUE) -> FALSE
... C99: =IF(P99=TRUE,C98+1,) -> 0 | E99: =IF(P99=TRUE,E98+F98,) -> 0 | N99: =ISTEXT(D99) -> FALSE | O99: =ISNUMBER(D99) -> FALSE | P99: =OR(N99=TRUE,O99=TRUE) -> FALSE

Sheet FIE - Venta fondos inv. CON ret
D2: Diseño de registro de datos fiscales y personales
D3: ='CONTROL DE VERSIONES'!G68 -> IRPF 2025
D4: Ventas de fondos de inversión con retención
C5: =IF(P5=TRUE,C4+1,) -> 0
C6: =IF(P6=TRUE,C5+1,) -> 0
C7: Este concepto de datos fiscales incluye las ventas de fondos de inversión con retención fiscal con origen en el Modelo 187
C9: Nº | D9: Nombre | E9: Posición | F9: Longitud | G9: Descripción
C10: =IF(P10=TRUE,1,) -> 1 | D10: Tipo | E10: =IF(P10=TRUE,1,) -> 1 | F10: 1 | G10: Tipo de registro = '2' | N10: =ISTEXT(D10) -> TRUE | O10: =ISNUMBER(D10) -> FALSE | P10: =OR(N10=TRUE,O10=TRUE) -> TRUE
C11: =IF(P11=TRUE,C10+1,) -> 2 | D11: Código | E11: =IF(P11=TRUE,E10+F10,) -> 2 | F11: 7 | G11: 'FIEnnnn' Donde nnnn es el número del registro de este tipo contenido en el fichero de datos fiscales. | N11: =ISTEXT(D11) -> TRUE | O11: =ISNUMBER(D11) -> FALSE | P11: =OR(N11=TRUE,O11=TRUE) -> TRUE
C12: =IF(P12=TRUE,C11+1,) -> 3 | D12: NIF del Fondo | E12: =IF(P12=TRUE,E11+F11,) -> 9 | F12: 9 | N12: =ISTEXT(D12) -> TRUE | O12: =ISNUMBER(D12) -> FALSE | P12: =OR(N12=TRUE,O12=TRUE) -> TRUE
C13: =IF(P13=TRUE,C12+1,) -> 4 | D13: Nombre del Fondo | E13: =IF(P13=TRUE,E12+F12,) -> 18 | F13: 40 | N13: =ISTEXT(D13) -> TRUE | O13: =ISNUMBER(D13) -> FALSE | P13: =OR(N13=TRUE,O13=TRUE) -> TRUE
C14: =IF(P14=TRUE,C13+1,) -> 5 | D14: NIF Gestora | E14: =IF(P14=TRUE,E13+F13,) -> 58 | F14: 9 | N14: =ISTEXT(D14) -> TRUE | O14: =ISNUMBER(D14) -> FALSE | P14: =OR(N14=TRUE,O14=TRUE) -> TRUE
C15: =IF(P15=TRUE,C14+1,) -> 6 | D15: Nombre Gestora | E15: =IF(P15=TRUE,E14+F14,) -> 67 | F15: 40 | N15: =ISTEXT(D15) -> TRUE | O15: =ISNUMBER(D15) -> FALSE | P15: =OR(N15=TRUE,O15=TRUE) -> TRUE
C16: =IF(P16=TRUE,C15+1,) -> 7 | D16: Fecha de adquisición | E16: =IF(P16=TRUE,E15+F15,) -> 107 | F16: 8 | G16: AAAAMMDD (Aplica sólo si ganancia patrimonial reducida = A) | N16: =ISTEXT(D16) -> TRUE | O16: =ISNUMBER(D16) -> FALSE | P16: =OR(N16=TRUE,O16=TRUE) -> TRUE
C17: =IF(P17=TRUE,C16+1,) -> 8 | D17: Fecha de operación | E17: =IF(P17=TRUE,E16+F16,) -> 115 | F17: 8 | G17: AAAAMMDD | N17: =ISTEXT(D17) -> TRUE | O17: =ISNUMBER(D17) -> FALSE | P17: =OR(N17=TRUE,O17=TRUE) -> TRUE
C18: =IF(P18=TRUE,C17+1,) -> 9 | D18: Ganancia Pat. Reducidad (DT9ª Ley 35/2006) | E18: =IF(P18=TRUE,E17+F17,) -> 123 | F18: 1 | G18: Valores: 'A' - Ganancia Patrimonial aplicando lo dispuesto en la DT9ª de la Ley 35/2006 'B' - Ganancia patrimonial sin aplicar lo dispuesto en la DT9ª de la Ley 35/2006 ' ' - En cualquier otro caso | N18: =ISTEXT(D18) -> TRUE | O18: =ISNUMBER(D18) -> FALSE | P18: =OR(N18=TRUE,O18=TRUE) -> TRUE
C19: =IF(P19=TRUE,C18+1,) -> 10 | D19: Ganancia | E19: =IF(P19=TRUE,E18+F18,) -> 124 | F19: 15 | N19: =ISTEXT(D19) -> TRUE | O19: =ISNUMBER(D19) -> FALSE | P19: =OR(N19=TRUE,O19=TRUE) -> TRUE
C20: =IF(P20=TRUE,C19+1,) -> 11 | D20: Pérdida | E20: =IF(P20=TRUE,E19+F19,) -> 139 | F20: 15 | N20: =ISTEXT(D20) -> TRUE | O20: =ISNUMBER(D20) -> FALSE | P20: =OR(N20=TRUE,O20=TRUE) -> TRUE
C21: =IF(P21=TRUE,C20+1,) -> 12 | D21: Retención | E21: =IF(P21=TRUE,E20+F20,) -> 154 | F21: 13 | N21: =ISTEXT(D21) -> TRUE | O21: =ISNUMBER(D21) -> FALSE | P21: =OR(N21=TRUE,O21=TRUE) -> TRUE
C22: =IF(P22=TRUE,C21+1,) -> 13 | D22: Tipo resultado | E22: =IF(P22=TRUE,E21+F21,) -> 167 | F22: 1 | G22: Valores: 'O' - Hay comunicación a la entidad obligada a practicar la retención... 'R' - No concurren las circunstancias anteriores | N22: =ISTEXT(D22) -> TRUE | O22: =ISNUMBER(D22) -> FALSE | P22: =OR(N22=TRUE,O22=TRUE) -> TRUE
C23: =IF(P23=TRUE,C22+1,) -> 14 | D23: Importe enajenación | E23: =IF(P23=TRUE,E22+F22,) -> 168 | F23: 13 | N23: =ISTEXT(D23) -> TRUE | O23: =ISNUMBER(D23) -> FALSE | P23: =OR(N23=TRUE,O23=TRUE) -> TRUE
C24: =IF(P24=TRUE,C23+1,) -> 15 | D24: Importe adquisición | E24: =IF(P24=TRUE,E23+F23,) -> 181 | F24: 13 | G24: (Importe enajenación - ganancia o + pérdida) Importe ficticio calculado a partir de los campos, importe enajenación, ganancias y pérdidas | N24: =ISTEXT(D24) -> TRUE | O24: =ISNUMBER(D24) -> FALSE | P24: =OR(N24=TRUE,O24=TRUE) -> TRUE
C25: =IF(P25=TRUE,C24+1,) -> 16 | D25: Valor de adquisición | E25: =IF(P25=TRUE,E24+F24,) -> 194 | F25: 13 | G25: (aplica sólo cuando la ganancia patrimonia reducida = A) | N25: =ISTEXT(D25) -> TRUE | O25: =ISNUMBER(D25) -> FALSE | P25: =OR(N25=TRUE,O25=TRUE) -> TRUE
C26: =IF(P26=TRUE,C25+1,) -> 17 | D26: Valor Patrimonio 2005 | E26: =IF(P26=TRUE,E25+F25,) -> 207 | F26: 13 | G26: (aplica sólo cuando la ganancia patrimonia reducida = A) | N26: =ISTEXT(D26) -> TRUE | O26: =ISNUMBER(D26) -> FALSE | P26: =OR(N26=TRUE,O26=TRUE) -> TRUE
C27: =IF(P27=TRUE,C26+1,) -> 18 | D27: Reducción aplicada DT9 | E27: =IF(P27=TRUE,E26+F26,) -> 220 | F27: 13 | G27: (aplica sólo cuando la ganancia patrimonia reducida = A) | N27: =ISTEXT(D27) -> TRUE | O27: =ISNUMBER(D27) -> FALSE | P27: =OR(N27=TRUE,O27=TRUE) -> TRUE
C28: =IF(P28=TRUE,C27+1,) -> 0 | E28: =IF(P28=TRUE,E27+F27,) -> 0 | N28: =ISTEXT(D28) -> FALSE | O28: =ISNUMBER(D28) -> FALSE | P28: =OR(N28=TRUE,O28=TRUE) -> FALSE
C29: =IF(P29=TRUE,C28+1,) -> 0 | E29: =IF(P29=TRUE,E28+F28,) -> 0 | N29: =ISTEXT(D29) -> FALSE | O29: =ISNUMBER(D29) -> FALSE | P29: =OR(N29=TRUE,O29=TRUE) -> FALSE
C30: =IF(P30=TRUE,C29+1,) -> 0 | E30: =IF(P30=TRUE,E29+F29,) -> 0 | N30: =ISTEXT(D30) -> FALSE | O30: =ISNUMBER(D30) -> FALSE | P30: =OR(N30=TRUE,O30=TRUE) -> FALSE
C31: =IF(P31=TRUE,C30+1,) -> 0 | E31: =IF(P31=TRUE,E30+F30,) -> 0 | N31: =ISTEXT(D31) -> FALSE | O31: =ISNUMBER(D31) -> FALSE | P31: =OR(N31=TRUE,O31=TRUE) -> FALSE
C32: =IF(P32=TRUE,C31+1,) -> 0 | E32: =IF(P32=TRUE,E31+F31,) -> 0 | N32: =ISTEXT(D32) -> FALSE | O32: =ISNUMBER(D32) -> FALSE | P32: =OR(N32=TRUE,O32=TRUE) -> FALSE
C33: =IF(P33=TRUE,C32+1,) -> 0 | E33: =IF(P33=TRUE,E32+F32,) -> 0 | N33: =ISTEXT(D33) -> FALSE | O33: =ISNUMBER(D33) -> FALSE | P33: =OR(N33=TRUE,O33=TRUE) -> FALSE
C34: =IF(P34=TRUE,C33+1,) -> 0 | E34: =IF(P34=TRUE,E33+F33,) -> 0 | N34: =ISTEXT(D34) -> FALSE | O34: =ISNUMBER(D34) -> FALSE | P34: =OR(N34=TRUE,O34=TRUE) -> FALSE
C35: =IF(P35=TRUE,C34+1,) -> 0 | E35: =IF(P35=TRUE,E34+F34,) -> 0 | N35: =ISTEXT(D35) -> FALSE | O35: =ISNUMBER(D35) -> FALSE | P35: =OR(N35=TRUE,O35=TRUE) -> FALSE
C36: =IF(P36=TRUE,C35+1,) -> 0 | E36: =IF(P36=TRUE,E35+F35,) -> 0 | N36: =ISTEXT(D36) -> FALSE | O36: =ISNUMBER(D36) -> FALSE | P36: =OR(N36=TRUE,O36=TRUE) -> FALSE
C37: =IF(P37=TRUE,C36+1,) -> 0 | E37: =IF(P37=TRUE,E36+F36,) -> 0 | N37: =ISTEXT(D37) -> FALSE | O37: =ISNUMBER(D37) -> FALSE | P37: =OR(N37=TRUE,O37=TRUE) -> FALSE
C38: =IF(P38=TRUE,C37+1,) -> 0 | E38: =IF(P38=TRUE,E37+F37,) -> 0 | N38: =ISTEXT(D38) -> FALSE | O38: =ISNUMBER(D38) -> FALSE | P38: =OR(N38=TRUE,O38=TRUE) -> FALSE
C39: =IF(P39=TRUE,C38+1,) -> 0 | E39: =IF(P39=TRUE,E38+F38,) -> 0 | N39: =ISTEXT(D39) -> FALSE | O39: =ISNUMBER(D39) -> FALSE | P39: =OR(N39=TRUE,O39=TRUE) -> FALSE
... C99: =IF(P99=TRUE,C98+1,) -> 0 | E99: =IF(P99=TRUE,E98+F98,) -> 0 | N99: =ISTEXT(D99) -> FALSE | O99: =ISNUMBER(D99) -> FALSE | P99: =OR(N99=TRUE,O99=TRUE) -> FALSE

Sheet FIC - Venta fondos inv. SIN ret
D2: Diseño de registro de datos fiscales y personales
D3: ='CONTROL DE VERSIONES'!G68 -> IRPF 2025
D4: Ventas de fondos de inversión cotizados, sin retención
C5: =IF(P5=TRUE,C4+1,) -> 0
C6: =IF(P6=TRUE,C5+1,) -> 0
C7: Este concepto de datos fiscales incluye las ventas de fondos de inversión cotizados, sin retención fiscal con origen en el Modelo 187
C9: Nº | D9: Nombre | E9: Posición | F9: Longitud | G9: Descripción
C10: =IF(P10=TRUE,1,) -> 1 | D10: Tipo | E10: =IF(P10=TRUE,1,) -> 1 | F10: 1 | G10: Tipo de registro = '2' | N10: =ISTEXT(D10) -> TRUE | O10: =ISNUMBER(D10) -> FALSE | P10: =OR(N10=TRUE,O10=TRUE) -> TRUE
C11: =IF(P11=TRUE,C10+1,) -> 2 | D11: Código | E11: =IF(P11=TRUE,E10+F10,) -> 2 | F11: 7 | G11: 'FICnnnn' Donde nnnn es el número del registro de este tipo contenido en el fichero de datos fiscales. | N11: =ISTEXT(D11) -> TRUE | O11: =ISNUMBER(D11) -> FALSE | P11: =OR(N11=TRUE,O11=TRUE) -> TRUE
C12: =IF(P12=TRUE,C11+1,) -> 3 | D12: NIF del Fondo | E12: =IF(P12=TRUE,E11+F11,) -> 9 | F12: 9 | N12: =ISTEXT(D12) -> TRUE | O12: =ISNUMBER(D12) -> FALSE | P12: =OR(N12=TRUE,O12=TRUE) -> TRUE
C13: =IF(P13=TRUE,C12+1,) -> 4 | D13: Nombre del Fondo | E13: =IF(P13=TRUE,E12+F12,) -> 18 | F13: 40 | N13: =ISTEXT(D13) -> TRUE | O13: =ISNUMBER(D13) -> FALSE | P13: =OR(N13=TRUE,O13=TRUE) -> TRUE
C14: =IF(P14=TRUE,C13+1,) -> 5 | D14: ISIN Fondo | E14: =IF(P14=TRUE,E13+F13,) -> 58 | F14: 12 | N14: =ISTEXT(D14) -> TRUE | O14: =ISNUMBER(D14) -> FALSE | P14: =OR(N14=TRUE,O14=TRUE) -> TRUE
C15: =IF(P15=TRUE,C14+1,) -> 6 | D15: NIF Gestora | E15: =IF(P15=TRUE,E14+F14,) -> 70 | F15: 9 | N15: =ISTEXT(D15) -> TRUE | O15: =ISNUMBER(D15) -> FALSE | P15: =OR(N15=TRUE,O15=TRUE) -> TRUE
C16: =IF(P16=TRUE,C15+1,) -> 7 | D16: Nombre Gestora | E16: =IF(P16=TRUE,E15+F15,) -> 79 | F16: 40 | N16: =ISTEXT(D16) -> TRUE | O16: =ISNUMBER(D16) -> FALSE | P16: =OR(N16=TRUE,O16=TRUE) -> TRUE
C17: =IF(P17=TRUE,C16+1,) -> 8 | D17: Fecha de adquisición | E17: =IF(P17=TRUE,E16+F16,) -> 119 | F17: 8 | G17: AAAAMMDD (Aplica sólo si ganancia patrimonial reducida = A) | N17: =ISTEXT(D17) -> TRUE | O17: =ISNUMBER(D17) -> FALSE | P17: =OR(N17=TRUE,O17=TRUE) -> TRUE
C18: =IF(P18=TRUE,C17+1,) -> 9 | D18: Fecha de operación | E18: =IF(P18=TRUE,E17+F17,) -> 127 | F18: 8 | G18: AAAAMMDD | N18: =ISTEXT(D18) -> TRUE | O18: =ISNUMBER(D18) -> FALSE | P18: =OR(N18=TRUE,O18=TRUE) -> TRUE
C19: =IF(P19=TRUE,C18+1,) -> 10 | D19: Valor | E19: =IF(P19=TRUE,E18+F18,) -> 135 | F19: 1 | G19: Valor: 'C' - Fondos Cotizados | N19: =ISTEXT(D19) -> TRUE | O19: =ISNUMBER(D19) -> FALSE | P19: =OR(N19=TRUE,O19=TRUE) -> TRUE
C20: =IF(P20=TRUE,C19+1,) -> 11 | D20: Número de títulos | E20: =IF(P20=TRUE,E19+F19,) -> 136 | F20: 16 | G20: Diez enteros y seis decimales | N20: =ISTEXT(D20) -> TRUE | O20: =ISNUMBER(D20) -> FALSE | P20: =OR(N20=TRUE,O20=TRUE) -> TRUE
C21: =IF(P21=TRUE,C20+1,) -> 12 | D21: Ganancia Pat. Reducidad (DT9ª Ley 35/2006) | E21: =IF(P21=TRUE,E20+F20,) -> 152 | F21: 1 | G21: Valores: 'A' - Ganancia Patrimonial aplicando lo dispuesto en la DT9ª de la Ley 35/2006 'B' - Ganancia patrimonial sin aplicar lo dispuesto en la DT9ª de la Ley 35/2006 ' ' - En cualquier otro caso | N21: =ISTEXT(D21) -> TRUE | O21: =ISNUMBER(D21) -> FALSE | P21: =OR(N21=TRUE,O21=TRUE) -> TRUE
C22: =IF(P22=TRUE,C21+1,) -> 13 | D22: Ganancia | E22: =IF(P22=TRUE,E21+F21,) -> 153 | F22: 15 | N22: =ISTEXT(D22) -> TRUE | O22: =ISNUMBER(D22) -> FALSE | P22: =OR(N22=TRUE,O22=TRUE) -> TRUE
C23: =IF(P23=TRUE,C22+1,) -> 14 | D23: Pérdida | E23: =IF(P23=TRUE,E22+F22,) -> 168 | F23: 15 | N23: =ISTEXT(D23) -> TRUE | O23: =ISNUMBER(D23) -> FALSE | P23: =OR(N23=TRUE,O23=TRUE) -> TRUE
C24: =IF(P24=TRUE,C23+1,) -> 15 | D24: Importe de la Venta | E24: =IF(P24=TRUE,E23+F23,) -> 183 | F24: 13 | N24: =ISTEXT(D24) -> TRUE | O24: =ISNUMBER(D24) -> FALSE | P24: =OR(N24=TRUE,O24=TRUE) -> TRUE
C25: =IF(P25=TRUE,C24+1,) -> 16 | D25: Valor de adquisición | E25: =IF(P25=TRUE,E24+F24,) -> 196 | F25: 13 | G25: (aplica sólo cuando la ganancia patrimonia reducida = A) | N25: =ISTEXT(D25) -> TRUE | O25: =ISNUMBER(D25) -> FALSE | P25: =OR(N25=TRUE,O25=TRUE) -> TRUE
C26: =IF(P26=TRUE,C25+1,) -> 17 | D26: Valor Patrimonio 2005 | E26: =IF(P26=TRUE,E25+F25,) -> 209 | F26: 13 | G26: (aplica sólo cuando la ganancia patrimonia reducida = A) | N26: =ISTEXT(D26) -> TRUE | O26: =ISNUMBER(D26) -> FALSE | P26: =OR(N26=TRUE,O26=TRUE) -> TRUE
C27: =IF(P27=TRUE,C26+1,) -> 18 | D27: Reducción aplicada DT9 | E27: =IF(P27=TRUE,E26+F26,) -> 222 | F27: 13 | G27: (aplica sólo cuando la ganancia patrimonia reducida = A) | N27: =ISTEXT(D27) -> TRUE | O27: =ISNUMBER(D27) -> FALSE | P27: =OR(N27=TRUE,O27=TRUE) -> TRUE
C28: =IF(P28=TRUE,C27+1,) -> 19 | D28: Importe Adquisición | E28: =IF(P28=TRUE,E27+F27,) -> 235 | F28: 13 | G28: (Importe venta – Ganancia o + Pérdida) IMPORTE FICTICIO CALCULADO A PARTIR DE LOS CAMPOS IMPORTE VENTA, GANANCIA Y PÉRDIDA. | N28: =ISTEXT(D28) -> TRUE | O28: =ISNUMBER(D28) -> FALSE | P28: =OR(N28=TRUE,O28=TRUE) -> TRUE
C29: =IF(P29=TRUE,C28+1,) -> 0 | E29: =IF(P29=TRUE,E28+F28,) -> 0 | N29: =ISTEXT(D29) -> FALSE | O29: =ISNUMBER(D29) -> FALSE | P29: =OR(N29=TRUE,O29=TRUE) -> FALSE
C30: =IF(P30=TRUE,C29+1,) -> 0 | E30: =IF(P30=TRUE,E29+F29,) -> 0 | N30: =ISTEXT(D30) -> FALSE | O30: =ISNUMBER(D30) -> FALSE | P30: =OR(N30=TRUE,O30=TRUE) -> FALSE
C31: =IF(P31=TRUE,C30+1,) -> 0 | E31: =IF(P31=TRUE,E30+F30,) -> 0 | N31: =ISTEXT(D31) -> FALSE | O31: =ISNUMBER(D31) -> FALSE | P31: =OR(N31=TRUE,O31=TRUE) -> FALSE
C32: =IF(P32=TRUE,C31+1,) -> 0 | E32: =IF(P32=TRUE,E31+F31,) -> 0 | N32: =ISTEXT(D32) -> FALSE | O32: =ISNUMBER(D32) -> FALSE | P32: =OR(N32=TRUE,O32=TRUE) -> FALSE
C33: =IF(P33=TRUE,C32+1,) -> 0 | E33: =IF(P33=TRUE,E32+F32,) -> 0 | N33: =ISTEXT(D33) -> FALSE | O33: =ISNUMBER(D33) -> FALSE | P33: =OR(N33=TRUE,O33=TRUE) -> FALSE
C34: =IF(P34=TRUE,C33+1,) -> 0 | E34: =IF(P34=TRUE,E33+F33,) -> 0 | N34: =ISTEXT(D34) -> FALSE | O34: =ISNUMBER(D34) -> FALSE | P34: =OR(N34=TRUE,O34=TRUE) -> FALSE
C35: =IF(P35=TRUE,C34+1,) -> 0 | E35: =IF(P35=TRUE,E34+F34,) -> 0 | N35: =ISTEXT(D35) -> FALSE | O35: =ISNUMBER(D35) -> FALSE | P35: =OR(N35=TRUE,O35=TRUE) -> FALSE
C36: =IF(P36=TRUE,C35+1,) -> 0 | E36: =IF(P36=TRUE,E35+F35,) -> 0 | N36: =ISTEXT(D36) -> FALSE | O36: =ISNUMBER(D36) -> FALSE | P36: =OR(N36=TRUE,O36=TRUE) -> FALSE
C37: =IF(P37=TRUE,C36+1,) -> 0 | E37: =IF(P37=TRUE,E36+F36,) -> 0 | N37: =ISTEXT(D37) -> FALSE | O37: =ISNUMBER(D37) -> FALSE | P37: =OR(N37=TRUE,O37=TRUE) -> FALSE
C38: =IF(P38=TRUE,C37+1,) -> 0 | E38: =IF(P38=TRUE,E37+F37,) -> 0 | N38: =ISTEXT(D38) -> FALSE | O38: =ISNUMBER(D38) -> FALSE | P38: =OR(N38=TRUE,O38=TRUE) -> FALSE
C39: =IF(P39=TRUE,C38+1,) -> 0 | E39: =IF(P39=TRUE,E38+F38,) -> 0 | N39: =ISTEXT(D39) -> FALSE | O39: =ISNUMBER(D39) -> FALSE | P39: =OR(N39=TRUE,O39=TRUE) -> FALSE
C40: =IF(P40=TRUE,C39+1,) -> 0 | E40: =IF(P40=TRUE,E39+F39,) -> 0 | N40: =ISTEXT(D40) -> FALSE | O40: =ISNUMBER(D40) -> FALSE | P40: =OR(N40=TRUE,O40=TRUE) -> FALSE
... C99: =IF(P99=TRUE,C98+1,) -> 0 | E99: =IF(P99=TRUE,E98+F98,) -> 0 | N99: =ISTEXT(D99) -> FALSE | O99: =ISNUMBER(D99) -> FALSE | P99: =OR(N99=TRUE,O99=TRUE) -> FALSE

Sheet FID - Venta transm. transit. 9
D2: Diseño de registro de datos fiscales y personales
D3: ='CONTROL DE VERSIONES'!G68 -> IRPF 2025
D4: Valor de transmisión sobre el que se aplicó la disposición transitoria 9ª de la ley de IRPF
C5: =IF(P5=TRUE,C4+1,) -> 0
C6: =IF(P6=TRUE,C5+1,) -> 0
C7: Este concepto de datos fiscales incluye el valor de transmisión al que resulta aplicable la D.T. 9ª, en las ganancias y pérdidas patrimoniales sometidas a retención o ingreso a cuenta derivadas de transmisiones o reembolsos de acciones o participaciones de instituciones de inversión colectiva (sociedades y fondos de inversión). Información obtenida de la declaración I.R.P.F. 2015 y/o 2016 y/o 2017 y/o 2018 y/o 2019 y/o 2020 y/o 2021 y/o 2022 y/o 2023 y/o 2024
C9: Nº | D9: Nombre | E9: Posición | F9: Longitud | G9: Descripción
C10: =IF(P10=TRUE,1,) -> 1 | D10: Tipo | E10: =IF(P10=TRUE,1,) -> 1 | F10: 1 | G10: Tipo de registro = '2' | N10: =ISTEXT(D10) -> TRUE | O10: =ISNUMBER(D10) -> FALSE | P10: =OR(N10=TRUE,O10=TRUE) -> TRUE
C11: =IF(P11=TRUE,C10+1,) -> 2 | D11: Código | E11: =IF(P11=TRUE,E10+F10,) -> 2 | F11: 7 | G11: 'FIDnnnn' Donde nnnn es el número del registro de este tipo contenido en el fichero de datos fiscales. | N11: =ISTEXT(D11) -> TRUE | O11: =ISNUMBER(D11) -> FALSE | P11: =OR(N11=TRUE,O11=TRUE) -> TRUE
C12: =IF(P12=TRUE,C11+1,) -> 3 | D12: Importe | E12: =IF(P12=TRUE,E11+F11,) -> 9 | F12: 15 | G12: Sumatorio siguientes casillas: - De la declaración IRPF 2024: [{ ∑(1588) y ficticias + ∑(314) y ficticias + ∑(330) y ficticias + ∑(345) y ficticias + ∑(1636) y ficticias+ ∑(406) y ficticias}] + ∑(1829) y ficticias} - De la declaración IRPF 2023: [{ ∑(1588) y ficticias + ∑(314) y ficticias + ∑(330) y ficticias + ∑(345) y ficticias + ∑(1636) y ficticias+ ∑(406) y ficticias}] + ∑(1829) y ficticias} - De la declaración IRPF 2022: [{ ∑(1588) y ficticias + ∑(314) y ficticias + ∑(330) y ficticias + ∑(345) y ficticias + ∑(1636) y ficticias+ ∑(406) y ficticias}] + ∑(1829) y ficticias} - De la declaración IRPF 2021: [{ ∑(1588) y ficticias + ∑(314) y ficticias + ∑(330) y ficticias + ∑(345) y ficticias + ∑(1636) y ficticias+ ∑(406) y ficticias}] - De la declaración IRPF 2020: [{ ∑(1588) y ficticias + ∑(314) y ficticias + ∑(330) y ficticias + ∑(345) y ficticias + ∑(1636) y ficticias+ ∑(406) y ficticias}] - De la declaración IRPF 2019: [{ ∑(1588) y ficticias + ∑(314) y ficticias + ∑(330) y ficticias + ∑(345) y ficticias + ∑(1636) y ficticias+ ∑(406) y ficticias}] - De la declaración IRPF 2018: [{ ∑(235) y ficticias + ∑(314) y ficticias + ∑(330) y ficticias + ∑(345) y ficticias + ∑(366) y ficticias+ ∑(406) y ficticias}] - De la declaración IRPF 2017: [{ ∑(222) y ficticias + ∑(297) y ficticias + ∑(312) y ficticias + ∑(327) y ficticias + ∑(348) y ficticias+ ∑(388) y ficticias}] - De la declaración IRPF 2016: [{ ∑(212) y ficticias + ∑(277) y ficticias + ∑(292) y ficticias + ∑(313) y ficticias+ ∑(350) y ficticias}]. - De la declaración IRPF 2015: [{ ∑(203) y ficticias + ∑(272) y ficticias + ∑(287) y ficticias + ∑(308) y ficticias + ∑(342) y ficticias}]. | N12: =ISTEXT(D12) -> TRUE | O12: =ISNUMBER(D12) -> FALSE | P12: =OR(N12=TRUE,O12=TRUE) -> TRUE
N13: =ISTEXT(D13) -> FALSE | O13: =ISNUMBER(D13) -> FALSE | P13: =OR(N13=TRUE,O13=TRUE) -> FALSE
C14: =IF(P14=TRUE,C13+1,) -> 0 | E14: =IF(P14=TRUE,E13+F13,) -> 0 | N14: =ISTEXT(D14) -> FALSE | O14: =ISNUMBER(D14) -> FALSE | P14: =OR(N14=TRUE,O14=TRUE) -> FALSE
C15: =IF(P15=TRUE,C14+1,) -> 0 | E15: =IF(P15=TRUE,E14+F14,) -> 0 | N15: =ISTEXT(D15) -> FALSE | O15: =ISNUMBER(D15) -> FALSE | P15: =OR(N15=TRUE,O15=TRUE) -> FALSE
C16: =IF(P16=TRUE,C15+1,) -> 0 | E16: =IF(P16=TRUE,E15+F15,) -> 0 | N16: =ISTEXT(D16) -> FALSE | O16: =ISNUMBER(D16) -> FALSE | P16: =OR(N16=TRUE,O16=TRUE) -> FALSE
C17: =IF(P17=TRUE,C16+1,) -> 0 | E17: =IF(P17=TRUE,E16+F16,) -> 0 | N17: =ISTEXT(D17) -> FALSE | O17: =ISNUMBER(D17) -> FALSE | P17: =OR(N17=TRUE,O17=TRUE) -> FALSE
C18: =IF(P18=TRUE,C17+1,) -> 0 | E18: =IF(P18=TRUE,E17+F17,) -> 0 | N18: =ISTEXT(D18) -> FALSE | O18: =ISNUMBER(D18) -> FALSE | P18: =OR(N18=TRUE,O18=TRUE) -> FALSE
C19: =IF(P19=TRUE,C18+1,) -> 0 | E19: =IF(P19=TRUE,E18+F18,) -> 0 | N19: =ISTEXT(D19) -> FALSE | O19: =ISNUMBER(D19) -> FALSE | P19: =OR(N19=TRUE,O19=TRUE) -> FALSE
C20: =IF(P20=TRUE,C19+1,) -> 0 | E20: =IF(P20=TRUE,E19+F19,) -> 0 | N20: =ISTEXT(D20) -> FALSE | O20: =ISNUMBER(D20) -> FALSE | P20: =OR(N20=TRUE,O20=TRUE) -> FALSE
C21: =IF(P21=TRUE,C20+1,) -> 0 | E21: =IF(P21=TRUE,E20+F20,) -> 0 | N21: =ISTEXT(D21) -> FALSE | O21: =ISNUMBER(D21) -> FALSE | P21: =OR(N21=TRUE,O21=TRUE) -> FALSE
C22: =IF(P22=TRUE,C21+1,) -> 0 | E22: =IF(P22=TRUE,E21+F21,) -> 0 | N22: =ISTEXT(D22) -> FALSE | O22: =ISNUMBER(D22) -> FALSE | P22: =OR(N22=TRUE,O22=TRUE) -> FALSE
C23: =IF(P23=TRUE,C22+1,) -> 0 | E23: =IF(P23=TRUE,E22+F22,) -> 0 | N23: =ISTEXT(D23) -> FALSE | O23: =ISNUMBER(D23) -> FALSE | P23: =OR(N23=TRUE,O23=TRUE) -> FALSE
C24: =IF(P24=TRUE,C23+1,) -> 0 | E24: =IF(P24=TRUE,E23+F23,) -> 0 | N24: =ISTEXT(D24) -> FALSE | O24: =ISNUMBER(D24) -> FALSE | P24: =OR(N24=TRUE,O24=TRUE) -> FALSE
C25: =IF(P25=TRUE,C24+1,) -> 0 | E25: =IF(P25=TRUE,E24+F24,) -> 0 | N25: =ISTEXT(D25) -> FALSE | O25: =ISNUMBER(D25) -> FALSE | P25: =OR(N25=TRUE,O25=TRUE) -> FALSE
... C99: =IF(P99=TRUE,C98+1,) -> 0 | E99: =IF(P99=TRUE,E98+F98,) -> 0 | N99: =ISTEXT(D99) -> FALSE | O99: =ISNUMBER(D99) -> FALSE | P99: =OR(N99=TRUE,O99=TRUE) -> FALSE

Sheet DS - Venta derechos CON retenc
D2: Diseño de registro de datos fiscales y personales
D3: ='CONTROL DE VERSIONES'!G68 -> IRPF 2025
D4: Ventas derechos de suscripción con retención
C5: =IF(P5=TRUE,C4+1,) -> 0
C6: =IF(P6=TRUE,C5+1,) -> 0
C7: Este concepto de datos fiscales incluye las ventas de derechos de suscripción con retención que se comunican en el Modelo 187
C9: Nº | D9: Nombre | E9: Posición | F9: Longitud | G9: Descripción
C10: =IF(P10=TRUE,1,) -> 1 | D10: Tipo | E10: =IF(P10=TRUE,1,) -> 1 | F10: 1 | G10: Tipo de registro = '2' | N10: =ISTEXT(D10) -> TRUE | O10: =ISNUMBER(D10) -> FALSE | P10: =OR(N10=TRUE,O10=TRUE) -> TRUE
C11: =IF(P11=TRUE,C10+1,) -> 2 | D11: Código | E11: =IF(P11=TRUE,E10+F10,) -> 2 | F11: 7 | G11: 'DSnnnnn' Donde nnnn es el número del registro de este tipo contenido en el fichero de datos fiscales. | N11: =ISTEXT(D11) -> TRUE | O11: =ISNUMBER(D11) -> FALSE | P11: =OR(N11=TRUE,O11=TRUE) -> TRUE
C12: =IF(P12=TRUE,C11+1,) -> 3 | D12: NIF Sociedad | E12: =IF(P12=TRUE,E11+F11,) -> 9 | F12: 9 | N12: =ISTEXT(D12) -> TRUE | O12: =ISNUMBER(D12) -> FALSE | P12: =OR(N12=TRUE,O12=TRUE) -> TRUE
C13: =IF(P13=TRUE,C12+1,) -> 4 | D13: Nombre sociedad | E13: =IF(P13=TRUE,E12+F12,) -> 18 | F13: 40 | N13: =ISTEXT(D13) -> TRUE | O13: =ISNUMBER(D13) -> FALSE | P13: =OR(N13=TRUE,O13=TRUE) -> TRUE
C14: =IF(P14=TRUE,C13+1,) -> 5 | D14: NIF declarante | E14: =IF(P14=TRUE,E13+F13,) -> 58 | F14: 9 | N14: =ISTEXT(D14) -> TRUE | O14: =ISNUMBER(D14) -> FALSE | P14: =OR(N14=TRUE,O14=TRUE) -> TRUE
C15: =IF(P15=TRUE,C14+1,) -> 6 | D15: Nombre DTE | E15: =IF(P15=TRUE,E14+F14,) -> 67 | F15: 40 | N15: =ISTEXT(D15) -> TRUE | O15: =ISNUMBER(D15) -> FALSE | P15: =OR(N15=TRUE,O15=TRUE) -> TRUE
C16: =IF(P16=TRUE,C15+1,) -> 7 | D16: Fecha adquisición | E16: =IF(P16=TRUE,E15+F15,) -> 107 | F16: 8 | N16: =ISTEXT(D16) -> TRUE | O16: =ISNUMBER(D16) -> FALSE | P16: =OR(N16=TRUE,O16=TRUE) -> TRUE
C17: =IF(P17=TRUE,C16+1,) -> 8 | D17: Fecha operación | E17: =IF(P17=TRUE,E16+F16,) -> 115 | F17: 8 | N17: =ISTEXT(D17) -> TRUE | O17: =ISNUMBER(D17) -> FALSE | P17: =OR(N17=TRUE,O17=TRUE) -> TRUE
C18: =IF(P18=TRUE,C17+1,) -> 9 | D18: Ganacia pat. reducida (DT 9ª Ley 35/2006) | E18: =IF(P18=TRUE,E17+F17,) -> 123 | F18: 1 | G18: Valores : 'A' Ganancia patrimonial aplicando lo dispuesto en la DT 9ª de la Ley 35/2006 'B' Ganancia patrimonial sin aplicación de lo dispuesto en la DT 9ª de la Ley 35/2006 ' ' En cualquier otro caso | N18: =ISTEXT(D18) -> TRUE | O18: =ISNUMBER(D18) -> FALSE | P18: =OR(N18=TRUE,O18=TRUE) -> TRUE
C19: =IF(P19=TRUE,C18+1,) -> 10 | D19: Ganancia | E19: =IF(P19=TRUE,E18+F18,) -> 124 | F19: 15 | N19: =ISTEXT(D19) -> TRUE | O19: =ISNUMBER(D19) -> FALSE | P19: =OR(N19=TRUE,O19=TRUE) -> TRUE
C20: =IF(P20=TRUE,C19+1,) -> 11 | D20: Pérdida | E20: =IF(P20=TRUE,E19+F19,) -> 139 | F20: 15 | N20: =ISTEXT(D20) -> TRUE | O20: =ISNUMBER(D20) -> FALSE | P20: =OR(N20=TRUE,O20=TRUE) -> TRUE
C21: =IF(P21=TRUE,C20+1,) -> 12 | D21: Retención | E21: =IF(P21=TRUE,E20+F20,) -> 154 | F21: 13 | N21: =ISTEXT(D21) -> TRUE | O21: =ISNUMBER(D21) -> FALSE | P21: =OR(N21=TRUE,O21=TRUE) -> TRUE
C22: =IF(P22=TRUE,C21+1,) -> 13 | D22: Importe enajenación | E22: =IF(P22=TRUE,E21+F21,) -> 167 | F22: 13 | N22: =ISTEXT(D22) -> TRUE | O22: =ISNUMBER(D22) -> FALSE | P22: =OR(N22=TRUE,O22=TRUE) -> TRUE
C23: =IF(P23=TRUE,C22+1,) -> 14 | D23: Gastos de enajenación | E23: =IF(P23=TRUE,E22+F22,) -> 180 | F23: 13 | N23: =ISTEXT(D23) -> TRUE | O23: =ISNUMBER(D23) -> FALSE | P23: =OR(N23=TRUE,O23=TRUE) -> TRUE
C24: =IF(P24=TRUE,C23+1,) -> 15 | D24: Valor adquisición | E24: =IF(P24=TRUE,E23+F23,) -> 193 | F24: 13 | G24: Aplica sólo cuando ganancia patrimonial reducida = A | N24: =ISTEXT(D24) -> TRUE | O24: =ISNUMBER(D24) -> FALSE | P24: =OR(N24=TRUE,O24=TRUE) -> TRUE
C25: =IF(P25=TRUE,C24+1,) -> 16 | D25: Valor I Patrimonio 2005 | E25: =IF(P25=TRUE,E24+F24,) -> 206 | F25: 13 | G25: Aplica sólo cuando ganancia patrimonial reducida = A | N25: =ISTEXT(D25) -> TRUE | O25: =ISNUMBER(D25) -> FALSE | P25: =OR(N25=TRUE,O25=TRUE) -> TRUE
C26: =IF(P26=TRUE,C25+1,) -> 17 | D26: Reducción aplicada DT 9ª | E26: =IF(P26=TRUE,E25+F25,) -> 219 | F26: 13 | G26: Aplica sólo cuando ganancia patrimonial reducida = A | N26: =ISTEXT(D26) -> TRUE | O26: =ISNUMBER(D26) -> FALSE | P26: =OR(N26=TRUE,O26=TRUE) -> TRUE
C27: =IF(P27=TRUE,C26+1,) -> 0 | E27: =IF(P27=TRUE,E26+F26,) -> 0 | N27: =ISTEXT(D27) -> FALSE | O27: =ISNUMBER(D27) -> FALSE | P27: =OR(N27=TRUE,O27=TRUE) -> FALSE
C28: =IF(P28=TRUE,C27+1,) -> 0 | E28: =IF(P28=TRUE,E27+F27,) -> 0 | N28: =ISTEXT(D28) -> FALSE | O28: =ISNUMBER(D28) -> FALSE | P28: =OR(N28=TRUE,O28=TRUE) -> FALSE
C29: =IF(P29=TRUE,C28+1,) -> 0 | E29: =IF(P29=TRUE,E28+F28,) -> 0 | N29: =ISTEXT(D29) -> FALSE | O29: =ISNUMBER(D29) -> FALSE | P29: =OR(N29=TRUE,O29=TRUE) -> FALSE
C30: =IF(P30=TRUE,C29+1,) -> 0 | E30: =IF(P30=TRUE,E29+F29,) -> 0 | N30: =ISTEXT(D30) -> FALSE | O30: =ISNUMBER(D30) -> FALSE | P30: =OR(N30=TRUE,O30=TRUE) -> FALSE
C31: =IF(P31=TRUE,C30+1,) -> 0 | E31: =IF(P31=TRUE,E30+F30,) -> 0 | N31: =ISTEXT(D31) -> FALSE | O31: =ISNUMBER(D31) -> FALSE | P31: =OR(N31=TRUE,O31=TRUE) -> FALSE
C32: =IF(P32=TRUE,C31+1,) -> 0 | E32: =IF(P32=TRUE,E31+F31,) -> 0 | N32: =ISTEXT(D32) -> FALSE | O32: =ISNUMBER(D32) -> FALSE | P32: =OR(N32=TRUE,O32=TRUE) -> FALSE
C33: =IF(P33=TRUE,C32+1,) -> 0 | E33: =IF(P33=TRUE,E32+F32,) -> 0 | N33: =ISTEXT(D33) -> FALSE | O33: =ISNUMBER(D33) -> FALSE | P33: =OR(N33=TRUE,O33=TRUE) -> FALSE
C34: =IF(P34=TRUE,C33+1,) -> 0 | E34: =IF(P34=TRUE,E33+F33,) -> 0 | N34: =ISTEXT(D34) -> FALSE | O34: =ISNUMBER(D34) -> FALSE | P34: =OR(N34=TRUE,O34=TRUE) -> FALSE
C35: =IF(P35=TRUE,C34+1,) -> 0 | E35: =IF(P35=TRUE,E34+F34,) -> 0 | N35: =ISTEXT(D35) -> FALSE | O35: =ISNUMBER(D35) -> FALSE | P35: =OR(N35=TRUE,O35=TRUE) -> FALSE
C36: =IF(P36=TRUE,C35+1,) -> 0 | E36: =IF(P36=TRUE,E35+F35,) -> 0 | N36: =ISTEXT(D36) -> FALSE | O36: =ISNUMBER(D36) -> FALSE | P36: =OR(N36=TRUE,O36=TRUE) -> FALSE
C37: =IF(P37=TRUE,C36+1,) -> 0 | E37: =IF(P37=TRUE,E36+F36,) -> 0 | N37: =ISTEXT(D37) -> FALSE | O37: =ISNUMBER(D37) -> FALSE | P37: =OR(N37=TRUE,O37=TRUE) -> FALSE
C38: =IF(P38=TRUE,C37+1,) -> 0 | E38: =IF(P38=TRUE,E37+F37,) -> 0 | N38: =ISTEXT(D38) -> FALSE | O38: =ISNUMBER(D38) -> FALSE | P38: =OR(N38=TRUE,O38=TRUE) -> FALSE
... C99: =IF(P99=TRUE,C98+1,) -> 0 | E99: =IF(P99=TRUE,E98+F98,) -> 0 | N99: =ISTEXT(D99) -> FALSE | O99: =ISNUMBER(D99) -> FALSE | P99: =OR(N99=TRUE,O99=TRUE) -> FALSE

Sheet TVD - Venta derechos SIN retenc
D2: Diseño de registro de datos fiscales y personales
D3: ='CONTROL DE VERSIONES'!G68 -> IRPF 2025
D4: Ventas derechos de suscripcion sin retención
C5: =IF(P5=TRUE,C4+1,) -> 0
C6: =IF(P6=TRUE,C5+1,) -> 0
C7: Este concepto de datos fiscales incluye las ventas de derechos de suscripción sin retención que se comunican en el Modelo 198
C9: Nº | D9: Nombre | E9: Posición | F9: Longitud | G9: Descripción
C10: =IF(P10=TRUE,1,) -> 1 | D10: Tipo | E10: =IF(P10=TRUE,1,) -> 1 | F10: 1 | G10: Tipo de registro = '2' | N10: =ISTEXT(D10) -> TRUE | O10: =ISNUMBER(D10) -> FALSE | P10: =OR(N10=TRUE,O10=TRUE) -> TRUE
C11: =IF(P11=TRUE,C10+1,) -> 2 | D11: Código | E11: =IF(P11=TRUE,E10+F10,) -> 2 | F11: 7 | G11: 'TVDnnnn' Donde nnnn es el número del registro de este tipo contenido en el fichero de datos fiscales. | N11: =ISTEXT(D11) -> TRUE | O11: =ISNUMBER(D11) -> FALSE | P11: =OR(N11=TRUE,O11=TRUE) -> TRUE
C12: =IF(P12=TRUE,C11+1,) -> 3 | D12: NIF Emisor | E12: =IF(P12=TRUE,E11+F11,) -> 9 | F12: 9 | N12: =ISTEXT(D12) -> TRUE | O12: =ISNUMBER(D12) -> FALSE | P12: =OR(N12=TRUE,O12=TRUE) -> TRUE
C13: =IF(P13=TRUE,C12+1,) -> 4 | D13: Nombre emisor | E13: =IF(P13=TRUE,E12+F12,) -> 18 | F13: 40 | N13: =ISTEXT(D13) -> TRUE | O13: =ISNUMBER(D13) -> FALSE | P13: =OR(N13=TRUE,O13=TRUE) -> TRUE
C14: =IF(P14=TRUE,C13+1,) -> 5 | D14: NIF declarante | E14: =IF(P14=TRUE,E13+F13,) -> 58 | F14: 9 | N14: =ISTEXT(D14) -> TRUE | O14: =ISNUMBER(D14) -> FALSE | P14: =OR(N14=TRUE,O14=TRUE) -> TRUE
C15: =IF(P15=TRUE,C14+1,) -> 6 | D15: Nombre DTE | E15: =IF(P15=TRUE,E14+F14,) -> 67 | F15: 40 | N15: =ISTEXT(D15) -> TRUE | O15: =ISNUMBER(D15) -> FALSE | P15: =OR(N15=TRUE,O15=TRUE) -> TRUE
C16: =IF(P16=TRUE,C15+1,) -> 7 | D16: Fecha operación | E16: =IF(P16=TRUE,E15+F15,) -> 107 | F16: 8 | G16: AAAAMMDD | N16: =ISTEXT(D16) -> TRUE | O16: =ISNUMBER(D16) -> FALSE | P16: =OR(N16=TRUE,O16=TRUE) -> TRUE
C17: =IF(P17=TRUE,C16+1,) -> 8 | D17: Clave mercado | E17: =IF(P17=TRUE,E16+F16,) -> 115 | F17: 1 | G17: Valor: ‘A’ - Mercado secundario oficial de valores español ‘B’ - Mercado secundario oficial de valores extranjeros de la UE ‘C’ - Otros mercados nacionales ‘D’ - Otros mercados extranjeros ‘F’ - Operaciones intervenidas por fedatarios públicos ‘O’ - Operaciones realizadas fuera de mercado (O.T.C.) ‘P’ - Mercado secundario de valores extranjeros (excluidos los de la UE) | N17: =ISTEXT(D17) -> TRUE | O17: =ISNUMBER(D17) -> FALSE | P17: =OR(N17=TRUE,O17=TRUE) -> TRUE
C18: =IF(P18=TRUE,C17+1,) -> 9 | D18: Valor | E18: =IF(P18=TRUE,E17+F17,) -> 116 | F18: 1 | G18: Valor: 'H' Derechos suscripción | N18: =ISTEXT(D18) -> TRUE | O18: =ISNUMBER(D18) -> FALSE | P18: =OR(N18=TRUE,O18=TRUE) -> TRUE
C19: =IF(P19=TRUE,C18+1,) -> 10 | D19: Titulares | E19: =IF(P19=TRUE,E18+F18,) -> 117 | F19: 3 | N19: =ISTEXT(D19) -> TRUE | O19: =ISNUMBER(D19) -> FALSE | P19: =OR(N19=TRUE,O19=TRUE) -> TRUE
C20: =IF(P20=TRUE,C19+1,) -> 11 | D20: Importe venta | E20: =IF(P20=TRUE,E19+F19,) -> 120 | F20: 15 | N20: =ISTEXT(D20) -> TRUE | O20: =ISNUMBER(D20) -> FALSE | P20: =OR(N20=TRUE,O20=TRUE) -> TRUE
C21: =IF(P21=TRUE,C20+1,) -> 12 | D21: Declarado | E21: =IF(P21=TRUE,E20+F20,) -> 135 | F21: 1 | G21: Valores: 'B' - Perceptor participaciones preferentes 'C' - Tercero 'E' - Entidad central de contrapartida 'N' - Nudo propietario 'P' - Prestamista 'Q' - Prestatario 'T' - Titular 'U' - Usufructuario | N21: =ISTEXT(D21) -> TRUE | O21: =ISNUMBER(D21) -> FALSE | P21: =OR(N21=TRUE,O21=TRUE) -> TRUE
C22: =IF(P22=TRUE,C21+1,) -> 0 | E22: =IF(P22=TRUE,E21+F21,) -> 0 | N22: =ISTEXT(D22) -> FALSE | O22: =ISNUMBER(D22) -> FALSE | P22: =OR(N22=TRUE,O22=TRUE) -> FALSE
C23: =IF(P23=TRUE,C22+1,) -> 0 | E23: =IF(P23=TRUE,E22+F22,) -> 0 | N23: =ISTEXT(D23) -> FALSE | O23: =ISNUMBER(D23) -> FALSE | P23: =OR(N23=TRUE,O23=TRUE) -> FALSE
C24: =IF(P24=TRUE,C23+1,) -> 0 | E24: =IF(P24=TRUE,E23+F23,) -> 0 | N24: =ISTEXT(D24) -> FALSE | O24: =ISNUMBER(D24) -> FALSE | P24: =OR(N24=TRUE,O24=TRUE) -> FALSE
C25: =IF(P25=TRUE,C24+1,) -> 0 | E25: =IF(P25=TRUE,E24+F24,) -> 0 | N25: =ISTEXT(D25) -> FALSE | O25: =ISNUMBER(D25) -> FALSE | P25: =OR(N25=TRUE,O25=TRUE) -> FALSE
C26: =IF(P26=TRUE,C25+1,) -> 0 | E26: =IF(P26=TRUE,E25+F25,) -> 0 | N26: =ISTEXT(D26) -> FALSE | O26: =ISNUMBER(D26) -> FALSE | P26: =OR(N26=TRUE,O26=TRUE) -> FALSE
C27: =IF(P27=TRUE,C26+1,) -> 0 | E27: =IF(P27=TRUE,E26+F26,) -> 0 | N27: =ISTEXT(D27) -> FALSE | O27: =ISNUMBER(D27) -> FALSE | P27: =OR(N27=TRUE,O27=TRUE) -> FALSE
C28: =IF(P28=TRUE,C27+1,) -> 0 | E28: =IF(P28=TRUE,E27+F27,) -> 0 | N28: =ISTEXT(D28) -> FALSE | O28: =ISNUMBER(D28) -> FALSE | P28: =OR(N28=TRUE,O28=TRUE) -> FALSE
C29: =IF(P29=TRUE,C28+1,) -> 0 | E29: =IF(P29=TRUE,E28+F28,) -> 0 | N29: =ISTEXT(D29) -> FALSE | O29: =ISNUMBER(D29) -> FALSE | P29: =OR(N29=TRUE,O29=TRUE) -> FALSE
